Workbook

Sheet START_HERE
B2: MASTER FIRM PANEL
B6: Purpose | C6: Consolidated transition-readiness workbook based on the supplied example, eight sector reports, and their supporting files.
B7: Coverage | C7: 82 firm-sector observations across 8 sectors. PI Industries occurs in two sectors; do not count observations as unique firms.
B8: Start here | C8: Use Master_Panel for the familiar 44 variables plus audit columns. Filter analysis_include = Yes for complete workbook-coded observations without a known report conflict.
B9: Read the scores carefully | C9: DQS_total is calculated only when all ten indicators are numeric. Report_DQS_total is separate and can exist when indicator-level evidence is missing. Report-only matrices are not independently verified.
B10: Important conflict | C10: Fertilisers report Table 15 says only four firms are fully coded; the supporting workbook contains eleven full scores and a different roster. Both versions are retained and conflicts are excluded from the default analysis set. This is not a final research dataset.
B11: Missing data | C11: Yellow cells = missing/not provided, never zero. Zero scores mean the supplied source assigned zero. No missing score, year, revenue, or regulatory status was invented.
B12: Regulatory scope | C12: CCTS_obligated is blank pending firm/unit-level final notification evidence. Original flags remain on Original_Master. Exposure to a sector or CBAM is not proof of legal obligation.
B13: Finance | C13: Monetary amounts are ₹ crore; ratios are fractions. ROA uses year-end assets. Building borrowing-cost proxies include non-interest charges and can exceed 100%; do not treat them as pure interest rates.
B14: Source hierarchy | C14: Source-workbook final indicator scores are retained; report totals are shown alongside. Contradictions trigger review, not an automatic choice of whichever value is larger or more complete.
B15: Useful sheets | C15: Sector_Summary, Evidence_Log, Report_Findings, Paper_Financials, Building_FY_Panel, Double_Coding, Reliability, Checks, Flags, Change_Log, Data_Dictionary, Source_Index.
B16: Audit trail | C16: Original_Master, Original_Support and Original_Flags preserve the example’s cached values. All carried values remain source claims; company reports have not been independently re-audited.
B17: Workbook use | C17: Blue text = transcribed input; black = calculated formula; yellow = missing. Filters and frozen headings are enabled. Formulas have cached results and recalculate in Excel.
... B21: New conflict | C21: Khaitan has the same total in report and workbook, but the quantification subscore differs (0 vs 2). It is now excluded from the default analysis set.

Sheet Master_Panel
A1: firm_name | B1: sector | C1: CCTS_obligated | D1: listed | E1: exchange | F1: ownership | G1: BRSR_filer | H1: I1 | I1: I2 | J1: I3 | K1: I4 | L1: I5 | M1: I6 | N1: I7 | O1: I8 | P1: I9 | Q1: I10 | R1: DQS_total | S1: DQS_100 | T1: sub_quantification | U1: sub_strategy | V1: sub_credibility | W1: reporting_FY | X1: coder_id | Y1: second_coder_score | Z1: agreed_score | AA1: CBAM_covered_product | AB1: export_intensity | AC1: EU_export | AD1: PAT_legacy_entity | AE1: revenue | AF1: total_assets | AG1: PAT | AH1: ROA | AI1: total_debt | AJ1: finance_cost | AK1: cost_of_debt_proxy | AL1: capex | AM1: size_band | AN1: source_document | AO1: reporting_year | AP1: page_or_section | AQ1: URL | AR1: date_accessed | AS1: observation_id | AT1: coding_status | AU1: report_DQS_total | AV1: report_source | AW1: report_page_or_section | AX1: score_conflict | AY1: analysis_include | AZ1: financial_data_status | BA1: duplicate_entity_note | BB1: indicators_available | BC1: DQS_difference_vs_report | BD1: review_note | BE1: company_source_link_status | BF1: reported_CBAM_exposure_flag | BG1: reported_CCTS_exposure | BH1: reported_CCTS_units | BI1: reported_DQS_indicators_coded | BJ1: reported_adjusted_PAT | BK1: reported_assurance | BL1: reported_book_value | BM1: reported_consolidated_PAT | BN1: reported_cost_of_debt_year_end | BO1: reported_export_band | BP1: reported_long_term_debt | BQ1: reported_market_cap | BR1: reported_net_debt | BS1: reported_net_margin | BT1: reported_planned_green_capex_band | BU1: value_chain_segment | BV1: document_review_status | BW1: reviewed_documents | BX1: remaining_missing_fields
A2: Tata Steel Ltd | B2: Steel | D2: 1 | E2: NSE or BSE | F2: listed private | G2: 1 | H2: 3 | I2: 2 | J2: 1 | K2: 2 | L2: 2 | M2: 1 | N2: 0 | O2: 1 | P2: 3 | Q2: 3 | R2: =IF(COUNT(H2:Q2)=10,SUM(H2:Q2),"") -> 18 | S2: =IF(ISNUMBER(R2),R2/30*100,"") -> 60 | T2: =IF(COUNT(H2:J2,L2)=4,SUM(H2:J2,L2),"") -> 8 | U2: =IF(COUNT(K2,M2:O2)=4,SUM(K2,M2:O2),"") -> 4 | V2: =IF(COUNT(P2:Q2)=2,SUM(P2:Q2),"") -> 6 | W2: FY2024-25 | X2: Coder A / B (reconciled) | Y2: 30 | Z2: =IF(ISNUMBER(R2),R2,"") -> 18 | AB2: 0.03325071 | AC2: 1 | AE2: 218543 | AF2: 275459 | AG2: 3174 | AH2: =IF(AND(ISNUMBER(AG2),ISNUMBER(AF2),AF2>0),AG2/AF2,"") -> 0.011522586 | AI2: 94801 | AJ2: 7341 | AM2: Large | AN2: Annual Report (BRSR embedded) | AO2: FY2025 | AP2: per indicator - see Evidence_Log | AS2: OBS-001 | AT2: Workbook final scores; two coders supplied | AU2: 18 | AV2: Steel_Sector_Report.pdf | AW2: PDF p.22; Table 19 | AX2: No | AY2: Yes | AZ2: Inherited source values; verify scope/year | BB2: =COUNT(H2:Q2) -> 10 | BC2: =IF(AND(ISNUMBER(R2),ISNUMBER(AU2)),R2-AU2,"") -> 0 | BF2: 1 | BN2: 0.077435892 | BV2: Reviewed supplied PDF/DOCX and related sources | BW2: Steel group/Steel_Sector_Report.pdf | Steel group/data/ANOVA OUTPUT.docx | Steel group/data/CONJOINT ANALYSIS.docx | Steel group/data/Cronbach Alpha Calculation.xlsx | Steel group/data/DQS- excel.xlsx | Steel group/data/MDS OUTPUT.docx | Steel group/data/RMSM Form Responses.xlsx | BX2: CCTS_obligated, CBAM_covered_product, PAT_legacy_entity, cost_of_debt_proxy, capex, URL, date_accessed; Official unit-level legal notices, exact exchange identity, access dates, and additional comparable annual capex/finance inputs are not supplied. No valid prior-year debt series was located for average-debt proxy.
A3: JSW Steel Ltd | B3: Steel | D3: 1 | E3: NSE or BSE | F3: listed private | G3: 1 | H3: 2 | I3: 2 | J3: 3 | K3: 2 | L3: 1 | M3: 1 | N3: 0 | O3: 1 | P3: 3 | Q3: 1 | R3: =IF(COUNT(H3:Q3)=10,SUM(H3:Q3),"") -> 16 | S3: =IF(ISNUMBER(R3),R3/30*100,"") -> 53.333333 | T3: =IF(COUNT(H3:J3,L3)=4,SUM(H3:J3,L3),"") -> 8 | U3: =IF(COUNT(K3,M3:O3)=4,SUM(K3,M3:O3),"") -> 4 | V3: =IF(COUNT(P3:Q3)=2,SUM(P3:Q3),"") -> 4 | W3: FY2025-26 | X3: Coder A / B (reconciled) | Y3: 16 | Z3: =IF(ISNUMBER(R3),R3,"") -> 16 | AB3: 0.047558404 | AC3: 1 | AE3: 168824 | AF3: 240445 | AG3: 3491 | AH3: =IF(AND(ISNUMBER(AG3),ISNUMBER(AF3),AF3>0),AG3/AF3,"") -> 0.014518913 | AI3: 98752 | AJ3: 8412 | AM3: Large | AN3: Business Responsibility and Sustainability Report (standalone filing) | AO3: FY2025 | AP3: per indicator - see Evidence_Log | AS3: OBS-002 | AT3: Workbook final scores; two coders supplied | AU3: 16 | AV3: Steel_Sector_Report.pdf | AW3: PDF p.22; Table 19 | AX3: No | AY3: Yes | AZ3: Inherited source values; verify scope/year | BB3: =COUNT(H3:Q3) -> 10 | BC3: =IF(AND(ISNUMBER(R3),ISNUMBER(AU3)),R3-AU3,"") -> 0 | BF3: 1 | BN3: 0.085183085 | BV3: Reviewed supplied PDF/DOCX and related sources | BW3: Steel group/Steel_Sector_Report.pdf | Steel group/data/ANOVA OUTPUT.docx | Steel group/data/CONJOINT ANALYSIS.docx | Steel group/data/Cronbach Alpha Calculation.xlsx | Steel group/data/DQS- excel.xlsx | Steel group/data/MDS OUTPUT.docx | Steel group/data/RMSM Form Responses.xlsx | BX3: CCTS_obligated, CBAM_covered_product, PAT_legacy_entity, cost_of_debt_proxy, capex, URL, date_accessed; Official unit-level legal notices, exact exchange identity, access dates, and additional comparable annual capex/finance inputs are not supplied. No valid prior-year debt series was located for average-debt proxy.
A4: Steel Authority of India (SAIL) | B4: Steel | D4: 1 | E4: NSE or BSE | F4: PSU | G4: 1 | H4: 2 | I4: 2 | J4: 2 | K4: 2 | L4: 1 | M4: 0 | N4: 0 | O4: 1 | P4: 3 | Q4: 3 | R4: =IF(COUNT(H4:Q4)=10,SUM(H4:Q4),"") -> 16 | S4: =IF(ISNUMBER(R4),R4/30*100,"") -> 53.333333 | T4: =IF(COUNT(H4:J4,L4)=4,SUM(H4:J4,L4),"") -> 7 | U4: =IF(COUNT(K4,M4:O4)=4,SUM(K4,M4:O4),"") -> 3 | V4: =IF(COUNT(P4:Q4)=2,SUM(P4:Q4),"") -> 6 | W4: FY2024-25 | X4: Coder A / B (reconciled) | Y4: 17 | Z4: =IF(ISNUMBER(R4),R4,"") -> 16 | AB4: 0.0048012764 | AC4: unknown | AE4: 102479 | AF4: 136718 | AG4: 2372 | AH4: =IF(AND(ISNUMBER(AG4),ISNUMBER(AF4),AF4>0),AG4/AF4,"") -> 0.017349581 | AI4: 36934 | AJ4: 2793 | AM4: Large | AN4: Business Responsibility and Sustainability Report (standalone filing) | AO4: FY2025 | AP4: per indicator - see Evidence_Log | AS4: OBS-003 | AT4: Workbook final scores; two coders supplied | AU4: 16 | AV4: Steel_Sector_Report.pdf | AW4: PDF p.22; Table 19 | AX4: No | AY4: Yes | AZ4: Inherited source values; verify scope/year | BB4: =COUNT(H4:Q4) -> 10 | BC4: =IF(AND(ISNUMBER(R4),ISNUMBER(AU4)),R4-AU4,"") -> 0 | BF4: 1 | BN4: 0.075621379 | BV4: Reviewed supplied PDF/DOCX and related sources | BW4: Steel group/Steel_Sector_Report.pdf | Steel group/data/ANOVA OUTPUT.docx | Steel group/data/CONJOINT ANALYSIS.docx | Steel group/data/Cronbach Alpha Calculation.xlsx | Steel group/data/DQS- excel.xlsx | Steel group/data/MDS OUTPUT.docx | Steel group/data/RMSM Form Responses.xlsx | BX4: CCTS_obligated, CBAM_covered_product, EU_export, PAT_legacy_entity, cost_of_debt_proxy, capex, URL, date_accessed; Official unit-level legal notices, exact exchange identity, access dates, and additional comparable annual capex/finance inputs are not supplied. No valid prior-year debt series was located for average-debt proxy.
A5: Jindal Steel Ltd (JSPL) | B5: Steel | D5: 1 | E5: NSE or BSE | F5: listed private | G5: 1 | H5: 2 | I5: 2 | J5: 3 | K5: 3 | L5: 1 | M5: 2 | N5: 0 | O5: 2 | P5: 3 | Q5: 1 | R5: =IF(COUNT(H5:Q5)=10,SUM(H5:Q5),"") -> 19 | S5: =IF(ISNUMBER(R5),R5/30*100,"") -> 63.333333 | T5: =IF(COUNT(H5:J5,L5)=4,SUM(H5:J5,L5),"") -> 8 | U5: =IF(COUNT(K5,M5:O5)=4,SUM(K5,M5:O5),"") -> 7 | V5: =IF(COUNT(P5:Q5)=2,SUM(P5:Q5),"") -> 4 | W5: FY2025-26 | X5: Coder A / B (reconciled) | Y5: 21 | Z5: =IF(ISNUMBER(R5),R5,"") -> 19 | AB5: 0.052451675 | AC5: unknown | AE5: 50129 | AF5: 85766 | AG5: 2846 | AH5: =IF(AND(ISNUMBER(AG5),ISNUMBER(AF5),AF5>0),AG5/AF5,"") -> 0.033183313 | AI5: 18406 | AJ5: 1312 | AM5: Large | AN5: Integrated Report (BRSR embedded) | AO5: FY2025 | AP5: per indicator - see Evidence_Log | AS5: OBS-004 | AT5: Workbook final scores; two coders supplied | AU5: 19 | AV5: Steel_Sector_Report.pdf | AW5: PDF p.22; Table 19 | AX5: No | AY5: Yes | AZ5: Inherited source values; verify scope/year | BB5: =COUNT(H5:Q5) -> 10 | BC5: =IF(AND(ISNUMBER(R5),ISNUMBER(AU5)),R5-AU5,"") -> 0 | BF5: 0 | BN5: 0.071281104 | BV5: Reviewed supplied PDF/DOCX and related sources | BW5: Steel group/Steel_Sector_Report.pdf | Steel group/data/ANOVA OUTPUT.docx | Steel group/data/CONJOINT ANALYSIS.docx | Steel group/data/Cronbach Alpha Calculation.xlsx | Steel group/data/DQS- excel.xlsx | Steel group/data/MDS OUTPUT.docx | Steel group/data/RMSM Form Responses.xlsx | BX5: CCTS_obligated, CBAM_covered_product, EU_export, PAT_legacy_entity, cost_of_debt_proxy, capex, URL, date_accessed; Official unit-level legal notices, exact exchange identity, access dates, and additional comparable annual capex/finance inputs are not supplied. No valid prior-year debt series was located for average-debt proxy.
A6: Jindal Stainless Ltd | B6: Steel | D6: 1 | E6: NSE or BSE | F6: listed private | G6: 1 | H6: 3 | I6: 2 | J6: 2 | K6: 2 | L6: 2 | M6: 0 | N6: 0 | O6: 1 | P6: 3 | Q6: 2 | R6: =IF(COUNT(H6:Q6)=10,SUM(H6:Q6),"") -> 17 | S6: =IF(ISNUMBER(R6),R6/30*100,"") -> 56.666667 | T6: =IF(COUNT(H6:J6,L6)=4,SUM(H6:J6,L6),"") -> 9 | U6: =IF(COUNT(K6,M6:O6)=4,SUM(K6,M6:O6),"") -> 3 | V6: =IF(COUNT(P6:Q6)=2,SUM(P6:Q6),"") -> 5 | W6: FY2024-25 | X6: Coder A / B (reconciled) | Y6: 17 | Z6: =IF(ISNUMBER(R6),R6,"") -> 17 | AB6: 0.14722451 | AC6: 1 | AE6: 39312 | AF6: 35917 | AG6: 2500 | AH6: =IF(AND(ISNUMBER(AG6),ISNUMBER(AF6),AF6>0),AG6/AF6,"") -> 0.069604922 | AI6: 6402 | AJ6: 612 | AM6: Large | AN6: Business Responsibility and Sustainability Report (standalone filing) | AO6: FY2025 | AP6: per indicator - see Evidence_Log | AS6: OBS-005 | AT6: Workbook final scores; two coders supplied | AU6: 17 | AV6: Steel_Sector_Report.pdf | AW6: PDF p.22; Table 19 | AX6: No | AY6: Yes | AZ6: Inherited source values; verify scope/year | BB6: =COUNT(H6:Q6) -> 10 | BC6: =IF(AND(ISNUMBER(R6),ISNUMBER(AU6)),R6-AU6,"") -> 0 | BF6: 1 | BN6: 0.095595127 | BV6: Reviewed supplied PDF/DOCX and related sources | BW6: Steel group/Steel_Sector_Report.pdf | Steel group/data/ANOVA OUTPUT.docx | Steel group/data/CONJOINT ANALYSIS.docx | Steel group/data/Cronbach Alpha Calculation.xlsx | Steel group/data/DQS- excel.xlsx | Steel group/data/MDS OUTPUT.docx | Steel group/data/RMSM Form Responses.xlsx | BX6: CCTS_obligated, CBAM_covered_product, PAT_legacy_entity, cost_of_debt_proxy, capex, URL, date_accessed; Official unit-level legal notices, exact exchange identity, access dates, and additional comparable annual capex/finance inputs are not supplied. No valid prior-year debt series was located for average-debt proxy.
A7: NMDC Steel Ltd | B7: Steel | D7: 1 | E7: NSE or BSE | F7: PSU | G7: 1 | H7: 3 | I7: 2 | J7: 1 | K7: 1 | L7: 1 | M7: 1 | N7: 0 | O7: 1 | P7: 3 | Q7: 1 | R7: =IF(COUNT(H7:Q7)=10,SUM(H7:Q7),"") -> 14 | S7: =IF(ISNUMBER(R7),R7/30*100,"") -> 46.666667 | T7: =IF(COUNT(H7:J7,L7)=4,SUM(H7:J7,L7),"") -> 7 | U7: =IF(COUNT(K7,M7:O7)=4,SUM(K7,M7:O7),"") -> 3 | V7: =IF(COUNT(P7:Q7)=2,SUM(P7:Q7),"") -> 4 | X7: Coder A / B (reconciled) | Y7: 14 | Z7: =IF(ISNUMBER(R7),R7,"") -> 14 | AB7: 0 | AC7: unknown | AE7: 8503 | AF7: 28470 | AG7: -2374 | AH7: =IF(AND(ISNUMBER(AG7),ISNUMBER(AF7),AF7>0),AG7/AF7,"") -> -0.08338602 | AI7: 5909 | AJ7: 652 | AM7: Mid | AN7: Annual Report, NMDC Limited (BRSR embedded) | AO7: FY2025 | AP7: per indicator - see Evidence_Log | AS7: OBS-006 | AT7: Workbook final scores; two coders supplied | AU7: 14 | AV7: Steel_Sector_Report.pdf | AW7: PDF p.22; Table 19 | AX7: No | AY7: Yes | AZ7: Inherited source values; verify scope/year | BB7: =COUNT(H7:Q7) -> 10 | BC7: =IF(AND(ISNUMBER(R7),ISNUMBER(AU7)),R7-AU7,"") -> 0 | BF7: 0 | BN7: 0.11034016 | BV7: Reviewed supplied PDF/DOCX and related sources | BW7: Steel group/Steel_Sector_Report.pdf | Steel group/data/ANOVA OUTPUT.docx | Steel group/data/CONJOINT ANALYSIS.docx | Steel group/data/Cronbach Alpha Calculation.xlsx | Steel group/data/DQS- excel.xlsx | Steel group/data/MDS OUTPUT.docx | Steel group/data/RMSM Form Responses.xlsx | BX7: CCTS_obligated, reporting_FY, CBAM_covered_product, EU_export, PAT_legacy_entity, cost_of_debt_proxy, capex, URL, date_accessed; Official unit-level legal notices, exact exchange identity, access dates, and additional comparable annual capex/finance inputs are not supplied. No valid prior-year debt series was located for average-debt proxy. NMDC Limited/NMDC Steel Ltd entity mismatch prevents copying miner disclosure/year/capex into steel row.
A8: Shyam Metalics & Energy Ltd | B8: Steel | D8: 1 | E8: NSE or BSE | F8: listed private | G8: 1 | H8: 2 | I8: 1 | J8: 0 | K8: 0 | L8: 0 | M8: 1 | N8: 0 | O8: 1 | P8: 0 | Q8: 1 | R8: =IF(COUNT(H8:Q8)=10,SUM(H8:Q8),"") -> 6 | S8: =IF(ISNUMBER(R8),R8/30*100,"") -> 20 | T8: =IF(COUNT(H8:J8,L8)=4,SUM(H8:J8,L8),"") -> 3 | U8: =IF(COUNT(K8,M8:O8)=4,SUM(K8,M8:O8),"") -> 2 | V8: =IF(COUNT(P8:Q8)=2,SUM(P8:Q8),"") -> 1 | W8: FY2024-25 | X8: Coder A / B (reconciled) | Y8: 6 | Z8: =IF(ISNUMBER(R8),R8,"") -> 6 | AB8: 0.0054868543 | AC8: unknown | AE8: 15138 | AF8: 16320 | AG8: 909 | AH8: =IF(AND(ISNUMBER(AG8),ISNUMBER(AF8),AF8>0),AG8/AF8,"") -> 0.055698529 | AI8: 789 | AJ8: 144 | AM8: Mid | AN8: Business Responsibility and Sustainability Report + Annual Report | AO8: FY2025 | AP8: per indicator - see Evidence_Log | AS8: OBS-007 | AT8: Workbook final scores; two coders supplied | AU8: 6 | AV8: Steel_Sector_Report.pdf | AW8: PDF p.22; Table 19 | AX8: No | AY8: Yes | AZ8: Inherited source values; verify scope/year | BB8: =COUNT(H8:Q8) -> 10 | BC8: =IF(AND(ISNUMBER(R8),ISNUMBER(AU8)),R8-AU8,"") -> 0 | BF8: 1 | BN8: 0.18250951 | BV8: Reviewed supplied PDF/DOCX and related sources | BW8: Steel group/Steel_Sector_Report.pdf | Steel group/data/ANOVA OUTPUT.docx | Steel group/data/CONJOINT ANALYSIS.docx | Steel group/data/Cronbach Alpha Calculation.xlsx | Steel group/data/DQS- excel.xlsx | Steel group/data/MDS OUTPUT.docx | Steel group/data/RMSM Form Responses.xlsx | BX8: CCTS_obligated, CBAM_covered_product, EU_export, PAT_legacy_entity, cost_of_debt_proxy, capex, URL, date_accessed; Official unit-level legal notices, exact exchange identity, access dates, and additional comparable annual capex/finance inputs are not supplied. No valid prior-year debt series was located for average-debt proxy.
A9: Godawari Power & Ispat Ltd | B9: Steel | D9: 1 | E9: NSE or BSE | F9: listed private | G9: 1 | H9: 3 | I9: 0 | J9: 0 | K9: 2 | L9: 2 | M9: 2 | N9: 0 | O9: 1 | P9: 1 | Q9: 2 | R9: =IF(COUNT(H9:Q9)=10,SUM(H9:Q9),"") -> 13 | S9: =IF(ISNUMBER(R9),R9/30*100,"") -> 43.333333 | T9: =IF(COUNT(H9:J9,L9)=4,SUM(H9:J9,L9),"") -> 5 | U9: =IF(COUNT(K9,M9:O9)=4,SUM(K9,M9:O9),"") -> 5 | V9: =IF(COUNT(P9:Q9)=2,SUM(P9:Q9),"") -> 3 | W9: FY2024-25 | X9: Coder A / B (reconciled) | Y9: 17 | Z9: =IF(ISNUMBER(R9),R9,"") -> 13 | AB9: 0.013298659 | AC9: unknown | AE9: 5375.73 | AF9: 6157 | AG9: 813 | AH9: =IF(AND(ISNUMBER(AG9),ISNUMBER(AF9),AF9>0),AG9/AF9,"") -> 0.13204483 | AI9: 309 | AJ9: 55.39 | AM9: Mid | AN9: Annual Report (BRSR embedded) | AO9: FY2025 | AP9: per indicator - see Evidence_Log | AS9: OBS-008 | AT9: Workbook final scores; two coders supplied | AU9: 13 | AV9: Steel_Sector_Report.pdf | AW9: PDF p.22; Table 19 | AX9: No | AY9: Yes | AZ9: Inherited source values; verify scope/year | BB9: =COUNT(H9:Q9) -> 10 | BC9: =IF(AND(ISNUMBER(R9),ISNUMBER(AU9)),R9-AU9,"") -> 0 | BF9: 0 | BN9: 0.17925566 | BV9: Reviewed supplied PDF/DOCX and related sources | BW9: Steel group/Steel_Sector_Report.pdf | Steel group/data/ANOVA OUTPUT.docx | Steel group/data/CONJOINT ANALYSIS.docx | Steel group/data/Cronbach Alpha Calculation.xlsx | Steel group/data/DQS- excel.xlsx | Steel group/data/MDS OUTPUT.docx | Steel group/data/RMSM Form Responses.xlsx | BX9: CCTS_obligated, CBAM_covered_product, EU_export, PAT_legacy_entity, cost_of_debt_proxy, capex, URL, date_accessed; Official unit-level legal notices, exact exchange identity, access dates, and additional comparable annual capex/finance inputs are not supplied. No valid prior-year debt series was located for average-debt proxy.
A10: Kalyani Steels Ltd | B10: Steel | D10: 1 | E10: NSE or BSE | F10: listed private | G10: 1 | H10: 2 | I10: 0 | J10: 0 | K10: 0 | L10: 0 | M10: 2 | N10: 0 | O10: 0 | P10: 0 | Q10: 1 | R10: =IF(COUNT(H10:Q10)=10,SUM(H10:Q10),"") -> 5 | S10: =IF(ISNUMBER(R10),R10/30*100,"") -> 16.666667 | T10: =IF(COUNT(H10:J10,L10)=4,SUM(H10:J10,L10),"") -> 2 | U10: =IF(COUNT(K10,M10:O10)=4,SUM(K10,M10:O10),"") -> 2 | V10: =IF(COUNT(P10:Q10)=2,SUM(P10:Q10),"") -> 1 | W10: FY2025-26 | X10: Coder A / B (reconciled) | Y10: 5 | Z10: =IF(ISNUMBER(R10),R10,"") -> 5 | AB10: 0.0070479314 | AC10: unknown | AD10: 1 | AE10: 1982 | AF10: 2732 | AG10: 256 | AH10: =IF(AND(ISNUMBER(AG10),ISNUMBER(AF10),AF10>0),AG10/AF10,"") -> 0.093704246 | AI10: 438 | AJ10: 19 | AM10: Mid | AN10: Annual Report (BRSR embedded) | AO10: FY2025 | AP10: per indicator - see Evidence_Log | AS10: OBS-009 | AT10: Workbook final scores; two coders supplied | AU10: 5 | AV10: Steel_Sector_Report.pdf | AW10: PDF p.22; Table 19 | AX10: No | AY10: Yes | AZ10: Inherited source values; verify scope/year | BB10: =COUNT(H10:Q10) -> 10 | BC10: =IF(AND(ISNUMBER(R10),ISNUMBER(AU10)),R10-AU10,"") -> 0 | BF10: 0 | BN10: 0.043378995 | BV10: Reviewed supplied PDF/DOCX and related sources | BW10: Steel group/Steel_Sector_Report.pdf | Steel group/data/ANOVA OUTPUT.docx | Steel group/data/CONJOINT ANALYSIS.docx | Steel group/data/Cronbach Alpha Calculation.xlsx | Steel group/data/DQS- excel.xlsx | Steel group/data/MDS OUTPUT.docx | Steel group/data/RMSM Form Responses.xlsx | BX10: CCTS_obligated, CBAM_covered_product, EU_export, cost_of_debt_proxy, capex, URL, date_accessed; Official unit-level legal notices, exact exchange identity, access dates, and additional comparable annual capex/finance inputs are not supplied. No valid prior-year debt series was located for average-debt proxy.
A11: Dalmia Bharat | B11: Cement | D11: 1 | G11: 1 | H11: 3 | I11: 3 | J11: 3 | K11: 3 | L11: 2 | M11: 2 | N11: 0 | O11: 2 | P11: 3 | Q11: 2 | R11: =IF(COUNT(H11:Q11)=10,SUM(H11:Q11),"") -> 23 | S11: =IF(ISNUMBER(R11),R11/30*100,"") -> 76.666667 | T11: =IF(COUNT(H11:J11,L11)=4,SUM(H11:J11,L11),"") -> 11 | U11: =IF(COUNT(K11,M11:O11)=4,SUM(K11,M11:O11),"") -> 7 | V11: =IF(COUNT(P11:Q11)=2,SUM(P11:Q11),"") -> 5 | W11: FY 2025-26 | AA11: 1 | AC11: unknown | AH11: =IF(AND(ISNUMBER(AG11),ISNUMBER(AF11),AF11>0),AG11/AF11,"") | AN11: Dalmia Bharat IR 2025-26; Dalmia Bharat IR 2025-26 (reviewed) | AP11: per indicator - see Evidence_Log | AS11: OBS-010 | AT11: Workbook coded; single coder | AU11: 23 | AV11: Cement_Report.pdf | AW11: PDF p.13; section 7.2 | AX11: No | AY11: Yes | AZ11: Not supplied | BB11: =COUNT(H11:Q11) -> 10 | BC11: =IF(AND(ISNUMBER(R11),ISNUMBER(AU11)),R11-AU11,"") -> 0 | BH11: 12 | BO11: <0.1% | BV11: Reviewed supplied PDF/DOCX and related sources | BW11: Cement/Annexure A.xlsx | Cement/Annexure B.docx | Cement/Annexure C.xlsx | Cement/Annexure D.xlsx | Cement/Annexure E.xlsx | Cement/Cement_Report.pdf | BX11: CCTS_obligated, exchange, ownership, coder_id, second_coder_score, agreed_score, export_intensity, EU_export, PAT_legacy_entity, revenue, total_assets, PAT, ROA, total_debt, finance_cost, cost_of_debt_proxy, capex, size_band, reporting_year, URL, date_accessed; No firm-level revenue/PAT/assets/debt/finance-cost table in supplied report or Word interviews. Survey and MDS values are respondent/perception data and cannot fill company financials. Single-coder identity and second coder are unrecorded. EU-specific exports not disclosed. Exact company-report URLs and access dates not supplied.
A12: Shree Cement | B12: Cement | D12: 1 | G12: 1 | H12: 3 | I12: 3 | J12: 3 | K12: 3 | L12: 2 | M12: 2 | N12: 0 | O12: 1 | P12: 3 | Q12: 2 | R12: =IF(COUNT(H12:Q12)=10,SUM(H12:Q12),"") -> 22 | S12: =IF(ISNUMBER(R12),R12/30*100,"") -> 73.333333 | T12: =IF(COUNT(H12:J12,L12)=4,SUM(H12:J12,L12),"") -> 11 | U12: =IF(COUNT(K12,M12:O12)=4,SUM(K12,M12:O12),"") -> 6 | V12: =IF(COUNT(P12:Q12)=2,SUM(P12:Q12),"") -> 5 | W12: FY 2025-26 | AA12: 1 | AB12: 0 | AC12: unknown | AH12: =IF(AND(ISNUMBER(AG12),ISNUMBER(AF12),AF12>0),AG12/AF12,"") | AN12: Shree Cement IR 2025-26; Shree Cement IR 2025-26 (reviewed) | AP12: per indicator - see Evidence_Log | AS12: OBS-011 | AT12: Workbook coded; single coder | AU12: 22 | AV12: Cement_Report.pdf | AW12: PDF p.13; section 7.2 | AX12: No | AY12: Yes | AZ12: Not supplied | BB12: =COUNT(H12:Q12) -> 10 | BC12: =IF(AND(ISNUMBER(R12),ISNUMBER(AU12)),R12-AU12,"") -> 0 | BH12: 7 | BV12: Reviewed supplied PDF/DOCX and related sources | BW12: Cement/Annexure A.xlsx | Cement/Annexure B.docx | Cement/Annexure C.xlsx | Cement/Annexure D.xlsx | Cement/Annexure E.xlsx | Cement/Cement_Report.pdf | BX12: CCTS_obligated, exchange, ownership, coder_id, second_coder_score, agreed_score, EU_export, PAT_legacy_entity, revenue, total_assets, PAT, ROA, total_debt, finance_cost, cost_of_debt_proxy, capex, size_band, reporting_year, URL, date_accessed; No firm-level revenue/PAT/assets/debt/finance-cost table in supplied report or Word interviews. Survey and MDS values are respondent/perception data and cannot fill company financials. Single-coder identity and second coder are unrecorded. EU-specific exports not disclosed. Exact company-report URLs and access dates not supplied.
A13: ACC Limited | B13: Cement | D13: 1 | G13: 1 | H13: 3 | I13: 2 | J13: 3 | K13: 3 | L13: 2 | M13: 2 | N13: 3 | O13: 3 | P13: 2 | Q13: 2 | R13: =IF(COUNT(H13:Q13)=10,SUM(H13:Q13),"") -> 25 | S13: =IF(ISNUMBER(R13),R13/30*100,"") -> 83.333333 | T13: =IF(COUNT(H13:J13,L13)=4,SUM(H13:J13,L13),"") -> 10 | U13: =IF(COUNT(K13,M13:O13)=4,SUM(K13,M13:O13),"") -> 11 | V13: =IF(COUNT(P13:Q13)=2,SUM(P13:Q13),"") -> 4 | W13: FY 2024-25 | AA13: 1 | AB13: 0 | AC13: unknown | AD13: 1 | AH13: =IF(AND(ISNUMBER(AG13),ISNUMBER(AF13),AF13>0),AG13/AF13,"") | AN13: ACC IR 2024-25 | AP13: per indicator - see Evidence_Log | AS13: OBS-012 | AT13: Workbook coded; single coder | AU13: 25 | AV13: Cement_Report.pdf | AW13: PDF p.13; section 7.2 | AX13: No | AY13: Yes | AZ13: Not supplied | BB13: =COUNT(H13:Q13) -> 10 | BC13: =IF(AND(ISNUMBER(R13),ISNUMBER(AU13)),R13-AU13,"") -> 0 | BV13: Reviewed supplied PDF/DOCX and related sources | BW13: Cement/Annexure A.xlsx | Cement/Annexure B.docx | Cement/Annexure C.xlsx | Cement/Annexure D.xlsx | Cement/Annexure E.xlsx | Cement/Cement_Report.pdf | BX13: CCTS_obligated, exchange, ownership, coder_id, second_coder_score, agreed_score, EU_export, revenue, total_assets, PAT, ROA, total_debt, finance_cost, cost_of_debt_proxy, capex, size_band, reporting_year, URL, date_accessed; No firm-level revenue/PAT/assets/debt/finance-cost table in supplied report or Word interviews. Survey and MDS values are respondent/perception data and cannot fill company financials. Single-coder identity and second coder are unrecorded. EU-specific exports not disclosed. Exact company-report URLs and access dates not supplied.
A14: JK Cement | B14: Cement | D14: 1 | G14: 1 | H14: 3 | I14: 3 | J14: 3 | K14: 3 | L14: 3 | M14: 3 | N14: 3 | O14: 3 | P14: 3 | Q14: 2 | R14: =IF(COUNT(H14:Q14)=10,SUM(H14:Q14),"") -> 29 | S14: =IF(ISNUMBER(R14),R14/30*100,"") -> 96.666667 | T14: =IF(COUNT(H14:J14,L14)=4,SUM(H14:J14,L14),"") -> 12 | U14: =IF(COUNT(K14,M14:O14)=4,SUM(K14,M14:O14),"") -> 12 | V14: =IF(COUNT(P14:Q14)=2,SUM(P14:Q14),"") -> 5 | W14: FY 2025-26 | AA14: 1 | AC14: unknown | AH14: =IF(AND(ISNUMBER(AG14),ISNUMBER(AF14),AF14>0),AG14/AF14,"") | AN14: JK Cement IR 2025-26 | AP14: per indicator - see Evidence_Log | AS14: OBS-013 | AT14: Workbook coded; single coder | AU14: 29 | AV14: Cement_Report.pdf | AW14: PDF p.13; section 7.2 | AX14: No | AY14: Yes | AZ14: Not supplied | BB14: =COUNT(H14:Q14) -> 10 | BC14: =IF(AND(ISNUMBER(R14),ISNUMBER(AU14)),R14-AU14,"") -> 0 | BO14: Negligible | BV14: Reviewed supplied PDF/DOCX and related sources | BW14: Cement/Annexure A.xlsx | Cement/Annexure B.docx | Cement/Annexure C.xlsx | Cement/Annexure D.xlsx | Cement/Annexure E.xlsx | Cement/Cement_Report.pdf | BX14: CCTS_obligated, exchange, ownership, coder_id, second_coder_score, agreed_score, export_intensity, EU_export, PAT_legacy_entity, revenue, total_assets, PAT, ROA, total_debt, finance_cost, cost_of_debt_proxy, capex, size_band, reporting_year, URL, date_accessed; No firm-level revenue/PAT/assets/debt/finance-cost table in supplied report or Word interviews. Survey and MDS values are respondent/perception data and cannot fill company financials. Single-coder identity and second coder are unrecorded. EU-specific exports not disclosed. Exact company-report URLs and access dates not supplied.
A15: UltraTech | B15: Cement | D15: 1 | G15: 1 | H15: 3 | I15: 3 | J15: 3 | K15: 3 | L15: 2 | M15: 2 | N15: 3 | O15: 3 | P15: 3 | Q15: 2 | R15: =IF(COUNT(H15:Q15)=10,SUM(H15:Q15),"") -> 27 | S15: =IF(ISNUMBER(R15),R15/30*100,"") -> 90 | T15: =IF(COUNT(H15:J15,L15)=4,SUM(H15:J15,L15),"") -> 11 | U15: =IF(COUNT(K15,M15:O15)=4,SUM(K15,M15:O15),"") -> 11 | V15: =IF(COUNT(P15:Q15)=2,SUM(P15:Q15),"") -> 5 | W15: FY 2025-26 | AA15: 1 | AB15: 0.0025 | AC15: unknown | AH15: =IF(AND(ISNUMBER(AG15),ISNUMBER(AF15),AF15>0),AG15/AF15,"") | AN15: UltraTech IR & Sustainability Report 2025-26 | AP15: per indicator - see Evidence_Log | AS15: OBS-014 | AT15: Workbook coded; single coder | AU15: 27 | AV15: Cement_Report.pdf | AW15: PDF p.13; section 7.2 | AX15: No | AY15: Yes | AZ15: Not supplied | BB15: =COUNT(H15:Q15) -> 10 | BC15: =IF(AND(ISNUMBER(R15),ISNUMBER(AU15)),R15-AU15,"") -> 0 | BH15: 49 | BV15: Reviewed supplied PDF/DOCX and related sources | BW15: Cement/Annexure A.xlsx | Cement/Annexure B.docx | Cement/Annexure C.xlsx | Cement/Annexure D.xlsx | Cement/Annexure E.xlsx | Cement/Cement_Report.pdf | BX15: CCTS_obligated, exchange, ownership, coder_id, second_coder_score, agreed_score, EU_export, PAT_legacy_entity, revenue, total_assets, PAT, ROA, total_debt, finance_cost, cost_of_debt_proxy, capex, size_band, reporting_year, URL, date_accessed; No firm-level revenue/PAT/assets/debt/finance-cost table in supplied report or Word interviews. Survey and MDS values are respondent/perception data and cannot fill company financials. Single-coder identity and second coder are unrecorded. EU-specific exports not disclosed. Exact company-report URLs and access dates not supplied.
A16: Ambuja Cements | B16: Cement | D16: 1 | G16: 1 | H16: 3 | I16: 1 | J16: 3 | K16: 3 | L16: 1 | M16: 2 | N16: 0 | O16: 3 | P16: 3 | Q16: 2 | R16: =IF(COUNT(H16:Q16)=10,SUM(H16:Q16),"") -> 21 | S16: =IF(ISNUMBER(R16),R16/30*100,"") -> 70 | T16: =IF(COUNT(H16:J16,L16)=4,SUM(H16:J16,L16),"") -> 8 | U16: =IF(COUNT(K16,M16:O16)=4,SUM(K16,M16:O16),"") -> 8 | V16: =IF(COUNT(P16:Q16)=2,SUM(P16:Q16),"") -> 5 | W16: FY 2024-25 | AA16: 1 | AB16: 0 | AC16: unknown | AD16: 1 | AH16: =IF(AND(ISNUMBER(AG16),ISNUMBER(AF16),AF16>0),AG16/AF16,"") | AN16: Ambuja IR 2024-25; Ambuja IR 2024-25 (reviewed) | AP16: per indicator - see Evidence_Log | AS16: OBS-015 | AT16: Workbook coded; single coder | AU16: 21 | AV16: Cement_Report.pdf | AW16: PDF p.13; section 7.2 | AX16: No | AY16: Yes | AZ16: Not supplied | BB16: =COUNT(H16:Q16) -> 10 | BC16: =IF(AND(ISNUMBER(R16),ISNUMBER(AU16)),R16-AU16,"") -> 0 | BV16: Reviewed supplied PDF/DOCX and related sources | BW16: Cement/Annexure A.xlsx | Cement/Annexure B.docx | Cement/Annexure C.xlsx | Cement/Annexure D.xlsx | Cement/Annexure E.xlsx | Cement/Cement_Report.pdf | BX16: CCTS_obligated, exchange, ownership, coder_id, second_coder_score, agreed_score, EU_export, revenue, total_assets, PAT, ROA, total_debt, finance_cost, cost_of_debt_proxy, capex, size_band, reporting_year, URL, date_accessed; No firm-level revenue/PAT/assets/debt/finance-cost table in supplied report or Word interviews. Survey and MDS values are respondent/perception data and cannot fill company financials. Single-coder identity and second coder are unrecorded. EU-specific exports not disclosed. Exact company-report URLs and access dates not supplied.
A17: JSW Cement | B17: Cement | D17: 1 | G17: 1 | H17: 3 | I17: 2 | J17: 3 | K17: 3 | L17: 1 | M17: 2 | N17: 0 | O17: 2 | P17: 3 | Q17: 2 | R17: =IF(COUNT(H17:Q17)=10,SUM(H17:Q17),"") -> 21 | S17: =IF(ISNUMBER(R17),R17/30*100,"") -> 70 | T17: =IF(COUNT(H17:J17,L17)=4,SUM(H17:J17,L17),"") -> 9 | U17: =IF(COUNT(K17,M17:O17)=4,SUM(K17,M17:O17),"") -> 7 | V17: =IF(COUNT(P17:Q17)=2,SUM(P17:Q17),"") -> 5 | W17: FY 2025-26 | AA17: 1 | AB17: 0 | AC17: unknown | AH17: =IF(AND(ISNUMBER(AG17),ISNUMBER(AF17),AF17>0),AG17/AF17,"") | AN17: JSW Cement IAR 2025-26; JSW Cement IAR 2025-26 (reviewed) | AP17: per indicator - see Evidence_Log | AS17: OBS-016 | AT17: Workbook coded; single coder | AU17: 21 | AV17: Cement_Report.pdf | AW17: PDF p.13; section 7.2 | AX17: No | AY17: Yes | AZ17: Not supplied | BB17: =COUNT(H17:Q17) -> 10 | BC17: =IF(AND(ISNUMBER(R17),ISNUMBER(AU17)),R17-AU17,"") -> 0 | BV17: Reviewed supplied PDF/DOCX and related sources | BW17: Cement/Annexure A.xlsx | Cement/Annexure B.docx | Cement/Annexure C.xlsx | Cement/Annexure D.xlsx | Cement/Annexure E.xlsx | Cement/Cement_Report.pdf | BX17: CCTS_obligated, exchange, ownership, coder_id, second_coder_score, agreed_score, EU_export, PAT_legacy_entity, revenue, total_assets, PAT, ROA, total_debt, finance_cost, cost_of_debt_proxy, capex, size_band, reporting_year, URL, date_accessed; No firm-level revenue/PAT/assets/debt/finance-cost table in supplied report or Word interviews. Survey and MDS values are respondent/perception data and cannot fill company financials. Single-coder identity and second coder are unrecorded. EU-specific exports not disclosed. Exact company-report URLs and access dates not supplied.
A18: Hindalco | B18: Aluminium | D18: 1 | F18: listed private | G18: 1 | H18: 3 | I18: 3 | J18: 3 | K18: 3 | L18: 3 | M18: 3 | N18: 3 | O18: 3 | P18: 3 | Q18: 3 | R18: =IF(COUNT(H18:Q18)=10,SUM(H18:Q18),"") -> 30 | S18: =IF(ISNUMBER(R18),R18/30*100,"") -> 100 | T18: =IF(COUNT(H18:J18,L18)=4,SUM(H18:J18,L18),"") -> 12 | U18: =IF(COUNT(K18,M18:O18)=4,SUM(K18,M18:O18),"") -> 12 | V18: =IF(COUNT(P18:Q18)=2,SUM(P18:Q18),"") -> 6 | W18: FY2024-25 | AA18: 1 | AE18: 238496 | AF18: 265991 | AG18: 16002 | AH18: =IF(AND(ISNUMBER(AG18),ISNUMBER(AF18),AF18>0),AG18/AF18,"") -> 0.06015993 | AK18: 0.0587 | AN18: Hindalco Integrated Annual Report 2024-25 incl. BRSR and assurance (report ref. 5) | AO18: FY2024-25 | AP18: not given in the sector report | PDF pp.14–15, Table 8 (DQS); PDF p.23, Table 14 (financials) | AS18: OBS-017 | AT18: Report matrix only; not independently verified | AU18: 30 | AV18: Aluminium_Report.pdf | AW18: PDF pp.14–15; Table 8 | AX18: No | AY18: No | AZ18: Inherited source values; verify scope/year | BB18: =COUNT(H18:Q18) -> 10 | BC18: =IF(AND(ISNUMBER(R18),ISNUMBER(AU18)),R18-AU18,"") -> 0 | BD18: Report scores transcribed as stated; underlying primary disclosure and indicator anchors need verification. | BU18: Primary | BV18: Reviewed supplied PDF/DOCX and related sources | BW18: Aluminium Group/Aluminium_Report.pdf (all pages) | Aluminium Group/Compiled_Interview_Transcripts.docx (all paragraphs and table) | Aluminium Group/Call_logs.xlsx (Call logs sheet; contact values not copied) | BX18: CCTS_obligated, exchange, coder_id, second_coder_score, agreed_score, export_intensity, EU_export, PAT_legacy_entity, total_debt, finance_cost, capex, size_band, URL, date_accessed; No exchange name, exact export/EU-export share, PAT legacy status, finance-cost numerator, debt balance, total capex, coder identity or access date supplied. Table 14 reports the already-transcribed financial values but does not supply debt, finance cost or capex inputs. The interview firms differ from the ten listed disclosure-panel names, so their loan/export claims cannot populate these rows. Firm-level CCTS obligation needs legal/unit evidence not present.
A19: Vedanta | B19: Aluminium | D19: 1 | F19: listed private | G19: 1 | H19: 3 | I19: 3 | J19: 3 | K19: 3 | L19: 3 | M19: 3 | N19: 3 | O19: 3 | P19: 3 | Q19: 3 | R19: =IF(COUNT(H19:Q19)=10,SUM(H19:Q19),"") -> 30 | S19: =IF(ISNUMBER(R19),R19/30*100,"") -> 100 | T19: =IF(COUNT(H19:J19,L19)=4,SUM(H19:J19,L19),"") -> 12 | U19: =IF(COUNT(K19,M19:O19)=4,SUM(K19,M19:O19),"") -> 12 | V19: =IF(COUNT(P19:Q19)=2,SUM(P19:Q19),"") -> 6 | W19: FY2024-25 | AA19: 1 | AH19: =IF(AND(ISNUMBER(AG19),ISNUMBER(AF19),AF19>0),AG19/AF19,"") | AN19: Vedanta Integrated Report and Annual Accounts FY2024-25; Climate Action Report 2025 (ref. 14) | AP19: not given in the sector report | PDF pp.14–15, Table 8 (DQS); PDF p.23, Table 14 (financial data availability) | AQ19: https://www.vedantalimited.com/eng/esg-reporting.php | AS19: OBS-018 | AT19: Report matrix only; not independently verified | AU19: 30 | AV19: Aluminium_Report.pdf | AW19: PDF pp.14–15; Table 8 | AX19: No | AY19: No | AZ19: Not supplied | BB19: =COUNT(H19:Q19) -> 10 | BC19: =IF(AND(ISNUMBER(R19),ISNUMBER(AU19)),R19-AU19,"") -> 0 | BD19: Report scores transcribed as stated; underlying primary disclosure and indicator anchors need verification. | BU19: Primary | BV19: Reviewed supplied PDF/DOCX and related sources | BW19: Aluminium Group/Aluminium_Report.pdf (all pages) | Aluminium Group/Compiled_Interview_Transcripts.docx (all paragraphs and table) | Aluminium Group/Call_logs.xlsx (Call logs sheet; contact values not copied) | BX19: CCTS_obligated, exchange, coder_id, second_coder_score, agreed_score, export_intensity, EU_export, PAT_legacy_entity, revenue, total_assets, PAT, ROA, total_debt, finance_cost, cost_of_debt_proxy, capex, size_band, reporting_year, date_accessed; No exchange name, exact export/EU-export share, PAT legacy status, finance-cost numerator, debt balance, total capex, coder identity or access date supplied. Table 14 explicitly says no financial document sourced for this firm; no financial values can be filled from these documents. The interview firms differ from the ten listed disclosure-panel names, so their loan/export claims cannot populate these rows. Firm-level CCTS obligation needs legal/unit evidence not present.
A20: NALCO | B20: Aluminium | D20: 1 | F20: PSU | G20: 1 | H20: 3 | I20: 3 | J20: 3 | K20: 3 | L20: 3 | M20: 3 | N20: 3 | O20: 3 | P20: 3 | Q20: 3 | R20: =IF(COUNT(H20:Q20)=10,SUM(H20:Q20),"") -> 30 | S20: =IF(ISNUMBER(R20),R20/30*100,"") -> 100 | T20: =IF(COUNT(H20:J20,L20)=4,SUM(H20:J20,L20),"") -> 12 | U20: =IF(COUNT(K20,M20:O20)=4,SUM(K20,M20:O20),"") -> 12 | V20: =IF(COUNT(P20:Q20)=2,SUM(P20:Q20),"") -> 6 | W20: FY2024-25 | AA20: 1 | AE20: 16662.21 | AF20: 22882 | AG20: 5324.67 | AH20: =IF(AND(ISNUMBER(AG20),ISNUMBER(AF20),AF20>0),AG20/AF20,"") -> 0.23270125 | AN20: NALCO 44th Annual Report 2024-25 incl. BRSR (ref. 9) | AO20: FY2024-25 | AP20: not given in the sector report | PDF pp.14–15, Table 8 (DQS); PDF p.23, Table 14 (financials) | AS20: OBS-019 | AT20: Report matrix only; not independently verified | AU20: 30 | AV20: Aluminium_Report.pdf | AW20: PDF pp.14–15; Table 8 | AX20: No | AY20: No | AZ20: Inherited source values; verify scope/year | BB20: =COUNT(H20:Q20) -> 10 | BC20: =IF(AND(ISNUMBER(R20),ISNUMBER(AU20)),R20-AU20,"") -> 0 | BD20: Report scores transcribed as stated; underlying primary disclosure and indicator anchors need verification. | BU20: Primary | BV20: Reviewed supplied PDF/DOCX and related sources | BW20: Aluminium Group/Aluminium_Report.pdf (all pages) | Aluminium Group/Compiled_Interview_Transcripts.docx (all paragraphs and table) | Aluminium Group/Call_logs.xlsx (Call logs sheet; contact values not copied) | BX20: CCTS_obligated, exchange, coder_id, second_coder_score, agreed_score, export_intensity, EU_export, PAT_legacy_entity, total_debt, finance_cost, cost_of_debt_proxy, capex, size_band, URL, date_accessed; No exchange name, exact export/EU-export share, PAT legacy status, finance-cost numerator, debt balance, total capex, coder identity or access date supplied. Cost-of-debt proxy is N/M because of no material borrowing, not a numeric zero. Total assets ~₹22,882 crore are approximate. The interview firms differ from the ten listed disclosure-panel names, so their loan/export claims cannot populate these rows. Firm-level CCTS obligation needs legal/unit evidence not present.
A21: BALCO | B21: Aluminium | F21: Vedanta Group majority-owned | H21: 3 | I21: 0 | J21: 0 | K21: 2 | L21: 2 | M21: 1 | N21: 3 | O21: 3 | P21: 3 | Q21: 0 | R21: =IF(COUNT(H21:Q21)=10,SUM(H21:Q21),"") -> 17 | S21: =IF(ISNUMBER(R21),R21/30*100,"") -> 56.666667 | T21: =IF(COUNT(H21:J21,L21)=4,SUM(H21:J21,L21),"") -> 5 | U21: =IF(COUNT(K21,M21:O21)=4,SUM(K21,M21:O21),"") -> 9 | V21: =IF(COUNT(P21:Q21)=2,SUM(P21:Q21),"") -> 3 | W21: FY2024-25 | AA21: 1 | AH21: =IF(AND(ISNUMBER(AG21),ISNUMBER(AF21),AF21>0),AG21/AF21,"") | AN21: BALCO Integrated Annual Report and sustainability pages | AP21: not given in the sector report | PDF pp.14–15, Table 8 (DQS); PDF p.23, Table 14 (financial data availability) | AS21: OBS-020 | AT21: Report matrix only; not independently verified | AU21: 17 | AV21: Aluminium_Report.pdf | AW21: PDF pp.14–15; Table 8 | AX21: No | AY21: No | AZ21: Not supplied | BB21: =COUNT(H21:Q21) -> 10 | BC21: =IF(AND(ISNUMBER(R21),ISNUMBER(AU21)),R21-AU21,"") -> 0 | BD21: Report scores transcribed as stated; underlying primary disclosure and indicator anchors need verification. | BU21: Primary | BV21: Reviewed supplied PDF/DOCX and related sources | BW21: Aluminium Group/Aluminium_Report.pdf (all pages) | Aluminium Group/Compiled_Interview_Transcripts.docx (all paragraphs and table) | Aluminium Group/Call_logs.xlsx (Call logs sheet; contact values not copied) | BX21: CCTS_obligated, listed, exchange, BRSR_filer, coder_id, second_coder_score, agreed_score, export_intensity, EU_export, PAT_legacy_entity, revenue, total_assets, PAT, ROA, total_debt, finance_cost, cost_of_debt_proxy, capex, size_band, reporting_year, URL, date_accessed; No exchange name, exact export/EU-export share, PAT legacy status, finance-cost numerator, debt balance, total capex, coder identity or access date supplied. Table 14 explicitly says no financial document sourced for this firm; no financial values can be filled from these documents. The interview firms differ from the ten listed disclosure-panel names, so their loan/export claims cannot populate these rows. Firm-level CCTS obligation needs legal/unit evidence not present.
A22: Maan Aluminium | B22: Aluminium | D22: 1 | H22: 3 | I22: 0 | J22: 0 | K22: 0 | L22: 0 | M22: 0 | N22: 3 | O22: 2 | P22: 2 | Q22: 0 | R22: =IF(COUNT(H22:Q22)=10,SUM(H22:Q22),"") -> 10 | S22: =IF(ISNUMBER(R22),R22/30*100,"") -> 33.333333 | T22: =IF(COUNT(H22:J22,L22)=4,SUM(H22:J22,L22),"") -> 3 | U22: =IF(COUNT(K22,M22:O22)=4,SUM(K22,M22:O22),"") -> 5 | V22: =IF(COUNT(P22:Q22)=2,SUM(P22:Q22),"") -> 2 | W22: FY2024-25 | AE22: 810.17 | AF22: 299.63 | AG22: 15.51 | AH22: =IF(AND(ISNUMBER(AG22),ISNUMBER(AF22),AF22>0),AG22/AF22,"") -> 0.051763842 | AK22: 0.0536 | AN22: Aluminium sector report, Table 8 | AO22: FY2024-25 | AP22: not given in the sector report | PDF pp.14–15, Table 8 (DQS); PDF p.23, Table 14 (financials) | AS22: OBS-021 | AT22: Report matrix only; not independently verified | AU22: 10 | AV22: Aluminium_Report.pdf | AW22: PDF pp.14–15; Table 8 | AX22: No | AY22: No | AZ22: Inherited source values; verify scope/year | BB22: =COUNT(H22:Q22) -> 10 | BC22: =IF(AND(ISNUMBER(R22),ISNUMBER(AU22)),R22-AU22,"") -> 0 | BD22: Report scores transcribed as stated; underlying primary disclosure and indicator anchors need verification. | BU22: Downstream/Secondary | BV22: Reviewed supplied PDF/DOCX and related sources | BW22: Aluminium Group/Aluminium_Report.pdf (all pages) | Aluminium Group/Compiled_Interview_Transcripts.docx (all paragraphs and table) | Aluminium Group/Call_logs.xlsx (Call logs sheet; contact values not copied) | BX22: CCTS_obligated, exchange, ownership, BRSR_filer, coder_id, second_coder_score, agreed_score, CBAM_covered_product, export_intensity, EU_export, PAT_legacy_entity, total_debt, finance_cost, capex, size_band, URL, date_accessed; No exchange name, exact export/EU-export share, PAT legacy status, finance-cost numerator, debt balance, total capex, coder identity or access date supplied. Table 14 reports the already-transcribed financial values but does not supply debt, finance cost or capex inputs. The interview firms differ from the ten listed disclosure-panel names, so their loan/export claims cannot populate these rows. Firm-level CCTS obligation needs legal/unit evidence not present.
A23: Century Extrusions | B23: Aluminium | D23: 1 | H23: 3 | I23: 0 | J23: 0 | K23: 0 | L23: 0 | M23: 0 | N23: 2 | O23: 2 | P23: 2 | Q23: 0 | R23: =IF(COUNT(H23:Q23)=10,SUM(H23:Q23),"") -> 9 | S23: =IF(ISNUMBER(R23),R23/30*100,"") -> 30 | T23: =IF(COUNT(H23:J23,L23)=4,SUM(H23:J23,L23),"") -> 3 | U23: =IF(COUNT(K23,M23:O23)=4,SUM(K23,M23:O23),"") -> 4 | V23: =IF(COUNT(P23:Q23)=2,SUM(P23:Q23),"") -> 2 | W23: FY2024-25 | AE23: 479.3 | AG23: 10.97 | AH23: =IF(AND(ISNUMBER(AG23),ISNUMBER(AF23),AF23>0),AG23/AF23,"") | AN23: Aluminium sector report, Table 8 | AO23: FY2025-26 | AP23: not given in the sector report | PDF pp.14–15, Table 8 (DQS); PDF p.23, Table 14 (financials) | AS23: OBS-022 | AT23: Report matrix only; not independently verified | AU23: 9 | AV23: Aluminium_Report.pdf | AW23: PDF pp.14–15; Table 8 | AX23: No | AY23: No | AZ23: Inherited source values; verify scope/year | BB23: =COUNT(H23:Q23) -> 10 | BC23: =IF(AND(ISNUMBER(R23),ISNUMBER(AU23)),R23-AU23,"") -> 0 | BD23: Report scores transcribed as stated; underlying primary disclosure and indicator anchors need verification. | BU23: Downstream/Secondary | BV23: Reviewed supplied PDF/DOCX and related sources | BW23: Aluminium Group/Aluminium_Report.pdf (all pages) | Aluminium Group/Compiled_Interview_Transcripts.docx (all paragraphs and table) | Aluminium Group/Call_logs.xlsx (Call logs sheet; contact values not copied) | BX23: CCTS_obligated, exchange, ownership, BRSR_filer, coder_id, second_coder_score, agreed_score, CBAM_covered_product, export_intensity, EU_export, PAT_legacy_entity, total_assets, ROA, total_debt, finance_cost, cost_of_debt_proxy, capex, size_band, URL, date_accessed; No exchange name, exact export/EU-export share, PAT legacy status, finance-cost numerator, debt balance, total capex, coder identity or access date supplied. Financial context is FY2025-26, whereas DQS is FY2024-25; assets/ROA/debt proxy are N/A and cannot be reconstructed. The interview firms differ from the ten listed disclosure-panel names, so their loan/export claims cannot populate these rows. Firm-level CCTS obligation needs legal/unit evidence not present.
A24: PG Foils | B24: Aluminium | D24: 1 | H24: 3 | I24: 0 | J24: 0 | K24: 0 | L24: 0 | M24: 0 | N24: 2 | O24: 2 | P24: 2 | Q24: 0 | R24: =IF(COUNT(H24:Q24)=10,SUM(H24:Q24),"") -> 9 | S24: =IF(ISNUMBER(R24),R24/30*100,"") -> 30 | T24: =IF(COUNT(H24:J24,L24)=4,SUM(H24:J24,L24),"") -> 3 | U24: =IF(COUNT(K24,M24:O24)=4,SUM(K24,M24:O24),"") -> 4 | V24: =IF(COUNT(P24:Q24)=2,SUM(P24:Q24),"") -> 2 | W24: FY2024-25 | AE24: 491.4 | AF24: 423.81 | AG24: 31.66 | AH24: =IF(AND(ISNUMBER(AG24),ISNUMBER(AF24),AF24>0),AG24/AF24,"") -> 0.074703287 | AN24: PG Foils annual report and corporate disclosures FY2024-25 (ref. 11) | AO24: FY2024-25 | AP24: not given in the sector report | PDF pp.14–15, Table 8 (DQS); PDF p.23, Table 14 (financials) | AS24: OBS-023 | AT24: Report matrix only; not independently verified | AU24: 9 | AV24: Aluminium_Report.pdf | AW24: PDF pp.14–15; Table 8 | AX24: No | AY24: No | AZ24: Inherited source values; verify scope/year | BB24: =COUNT(H24:Q24) -> 10 | BC24: =IF(AND(ISNUMBER(R24),ISNUMBER(AU24)),R24-AU24,"") -> 0 | BD24: Report scores transcribed as stated; underlying primary disclosure and indicator anchors need verification. | BU24: Downstream/Secondary | BV24: Reviewed supplied PDF/DOCX and related sources | BW24: Aluminium Group/Aluminium_Report.pdf (all pages) | Aluminium Group/Compiled_Interview_Transcripts.docx (all paragraphs and table) | Aluminium Group/Call_logs.xlsx (Call logs sheet; contact values not copied) | BX24: CCTS_obligated, exchange, ownership, BRSR_filer, coder_id, second_coder_score, agreed_score, CBAM_covered_product, export_intensity, EU_export, PAT_legacy_entity, total_debt, finance_cost, cost_of_debt_proxy, capex, size_band, URL, date_accessed; No exchange name, exact export/EU-export share, PAT legacy status, finance-cost numerator, debt balance, total capex, coder identity or access date supplied. Table 14 reports the already-transcribed financial values but does not supply debt, finance cost or capex inputs. The interview firms differ from the ten listed disclosure-panel names, so their loan/export claims cannot populate these rows. Firm-level CCTS obligation needs legal/unit evidence not present.
A25: Manaksia Aluminium | B25: Aluminium | D25: 1 | H25: 3 | I25: 0 | J25: 0 | K25: 0 | L25: 0 | M25: 0 | N25: 2 | O25: 1 | P25: 2 | Q25: 0 | R25: =IF(COUNT(H25:Q25)=10,SUM(H25:Q25),"") -> 8 | S25: =IF(ISNUMBER(R25),R25/30*100,"") -> 26.666667 | T25: =IF(COUNT(H25:J25,L25)=4,SUM(H25:J25,L25),"") -> 3 | U25: =IF(COUNT(K25,M25:O25)=4,SUM(K25,M25:O25),"") -> 3 | V25: =IF(COUNT(P25:Q25)=2,SUM(P25:Q25),"") -> 2 | W25: FY2024-25 | AE25: 509.15 | AF25: 504.26 | AG25: 6.05 | AH25: =IF(AND(ISNUMBER(AG25),ISNUMBER(AF25),AF25>0),AG25/AF25,"") -> 0.011997779 | AK25: 0.1339 | AN25: Aluminium sector report, Table 8 | AO25: FY2024-25 | AP25: not given in the sector report | PDF pp.14–15, Table 8 (DQS); PDF p.23, Table 14 (financials) | AS25: OBS-024 | AT25: Report matrix only; not independently verified | AU25: 8 | AV25: Aluminium_Report.pdf | AW25: PDF pp.14–15; Table 8 | AX25: No | AY25: No | AZ25: Inherited source values; verify scope/year | BB25: =COUNT(H25:Q25) -> 10 | BC25: =IF(AND(ISNUMBER(R25),ISNUMBER(AU25)),R25-AU25,"") -> 0 | BD25: Report scores transcribed as stated; underlying primary disclosure and indicator anchors need verification. | BU25: Downstream/Secondary | BV25: Reviewed supplied PDF/DOCX and related sources | BW25: Aluminium Group/Aluminium_Report.pdf (all pages) | Aluminium Group/Compiled_Interview_Transcripts.docx (all paragraphs and table) | Aluminium Group/Call_logs.xlsx (Call logs sheet; contact values not copied) | BX25: CCTS_obligated, exchange, ownership, BRSR_filer, coder_id, second_coder_score, agreed_score, CBAM_covered_product, export_intensity, EU_export, PAT_legacy_entity, total_debt, finance_cost, capex, size_band, URL, date_accessed; No exchange name, exact export/EU-export share, PAT legacy status, finance-cost numerator, debt balance, total capex, coder identity or access date supplied. Table 14 reports the already-transcribed financial values but does not supply debt, finance cost or capex inputs. The interview firms differ from the ten listed disclosure-panel names, so their loan/export claims cannot populate these rows. Firm-level CCTS obligation needs legal/unit evidence not present.
A26: Alufluoride | B26: Aluminium | D26: 1 | H26: 3 | I26: 0 | J26: 0 | K26: 0 | L26: 0 | M26: 0 | N26: 2 | O26: 1 | P26: 2 | Q26: 0 | R26: =IF(COUNT(H26:Q26)=10,SUM(H26:Q26),"") -> 8 | S26: =IF(ISNUMBER(R26),R26/30*100,"") -> 26.666667 | T26: =IF(COUNT(H26:J26,L26)=4,SUM(H26:J26,L26),"") -> 3 | U26: =IF(COUNT(K26,M26:O26)=4,SUM(K26,M26:O26),"") -> 3 | V26: =IF(COUNT(P26:Q26)=2,SUM(P26:Q26),"") -> 2 | W26: FY2024-25 | AE26: 188.52 | AF26: 149.23 | AG26: 18.09 | AH26: =IF(AND(ISNUMBER(AG26),ISNUMBER(AF26),AF26>0),AG26/AF26,"") -> 0.12122227 | AK26: 0.1264 | AN26: Aluminium sector report, Table 8 | AO26: FY2024-25 | AP26: not given in the sector report | PDF pp.14–15, Table 8 (DQS); PDF p.23, Table 14 (financials) | AS26: OBS-025 | AT26: Report matrix only; not independently verified | AU26: 8 | AV26: Aluminium_Report.pdf | AW26: PDF pp.14–15; Table 8 | AX26: No | AY26: No | AZ26: Inherited source values; verify scope/year | BB26: =COUNT(H26:Q26) -> 10 | BC26: =IF(AND(ISNUMBER(R26),ISNUMBER(AU26)),R26-AU26,"") -> 0 | BD26: Report scores transcribed as stated; underlying primary disclosure and indicator anchors need verification. | BU26: Downstream/Secondary | BV26: Reviewed supplied PDF/DOCX and related sources | BW26: Aluminium Group/Aluminium_Report.pdf (all pages) | Aluminium Group/Compiled_Interview_Transcripts.docx (all paragraphs and table) | Aluminium Group/Call_logs.xlsx (Call logs sheet; contact values not copied) | BX26: CCTS_obligated, exchange, ownership, BRSR_filer, coder_id, second_coder_score, agreed_score, CBAM_covered_product, export_intensity, EU_export, PAT_legacy_entity, total_debt, finance_cost, capex, size_band, URL, date_accessed; No exchange name, exact export/EU-export share, PAT legacy status, finance-cost numerator, debt balance, total capex, coder identity or access date supplied. Table 14 reports the already-transcribed financial values but does not supply debt, finance cost or capex inputs. The interview firms differ from the ten listed disclosure-panel names, so their loan/export claims cannot populate these rows. Firm-level CCTS obligation needs legal/unit evidence not present.
A27: Euro Panel Products | B27: Aluminium | D27: 1 | H27: 3 | I27: 0 | J27: 0 | K27: 0 | L27: 0 | M27: 0 | N27: 1 | O27: 1 | P27: 2 | Q27: 0 | R27: =IF(COUNT(H27:Q27)=10,SUM(H27:Q27),"") -> 7 | S27: =IF(ISNUMBER(R27),R27/30*100,"") -> 23.333333 | T27: =IF(COUNT(H27:J27,L27)=4,SUM(H27:J27,L27),"") -> 3 | U27: =IF(COUNT(K27,M27:O27)=4,SUM(K27,M27:O27),"") -> 2 | V27: =IF(COUNT(P27:Q27)=2,SUM(P27:Q27),"") -> 2 | W27: FY2024-25 | AH27: =IF(AND(ISNUMBER(AG27),ISNUMBER(AF27),AF27>0),AG27/AF27,"") | AN27: Aluminium sector report, Table 8 | AP27: not given in the sector report | PDF pp.14–15, Table 8 (DQS); PDF p.23, Table 14 (financial data availability) | AS27: OBS-026 | AT27: Report matrix only; not independently verified | AU27: 7 | AV27: Aluminium_Report.pdf | AW27: PDF pp.14–15; Table 8 | AX27: No | AY27: No | AZ27: Not supplied | BB27: =COUNT(H27:Q27) -> 10 | BC27: =IF(AND(ISNUMBER(R27),ISNUMBER(AU27)),R27-AU27,"") -> 0 | BD27: Report scores transcribed as stated; underlying primary disclosure and indicator anchors need verification. | BU27: Downstream/Secondary | BV27: Reviewed supplied PDF/DOCX and related sources | BW27: Aluminium Group/Aluminium_Report.pdf (all pages) | Aluminium Group/Compiled_Interview_Transcripts.docx (all paragraphs and table) | Aluminium Group/Call_logs.xlsx (Call logs sheet; contact values not copied) | BX27: CCTS_obligated, exchange, ownership, BRSR_filer, coder_id, second_coder_score, agreed_score, CBAM_covered_product, export_intensity, EU_export, PAT_legacy_entity, revenue, total_assets, PAT, ROA, total_debt, finance_cost, cost_of_debt_proxy, capex, size_band, reporting_year, URL, date_accessed; No exchange name, exact export/EU-export share, PAT legacy status, finance-cost numerator, debt balance, total capex, coder identity or access date supplied. Table 14 explicitly says no financial document sourced for this firm; no financial values can be filled from these documents. The interview firms differ from the ten listed disclosure-panel names, so their loan/export claims cannot populate these rows. Firm-level CCTS obligation needs legal/unit evidence not present.
A28: IFFCO | B28: Fertilisers & chemicals | D28: 0 | F28: cooperative | G28: 0 | R28: =IF(COUNT(H28:Q28)=10,SUM(H28:Q28),"") | S28: =IF(ISNUMBER(R28),R28/30*100,"") | T28: =IF(COUNT(H28:J28,L28)=4,SUM(H28:J28,L28),"") | U28: =IF(COUNT(K28,M28:O28)=4,SUM(K28,M28:O28),"") | V28: =IF(COUNT(P28:Q28)=2,SUM(P28:Q28),"") | W28: FY2025-26 | X28: Research coder | AC28: unknown | AH28: =IF(AND(ISNUMBER(AG28),ISNUMBER(AF28),AF28>0),AG28/AF28,"") | AM28: Large | AN28: IFFCO Annual Report / public disclosures | AP28: per indicator - see Evidence_Log | AQ28: IFFCO official annual-report portal | AS28: OBS-027 | AT28: Out of scope (BRSR); no zero assigned | AV28: Fertilisers_and_Chemicals_Report.pdf | AW28: PDF pp.18–20; Tables 15–16 | AX28: No | AY28: No | AZ28: Not supplied | BB28: =COUNT(H28:Q28) -> 0 | BC28: =IF(AND(ISNUMBER(R28),ISNUMBER(AU28)),R28-AU28,"") | BF28: 1 | BG28: Directly covered or expected to have direct compliance obligations | BI28: 0 | BK28: No BRSR (not SEBI-listed) | BO28: <10% | BT28: 5–15%; 15–30% | BV28: Reviewed supplied PDF/DOCX and related sources | BW28: Fertilisers_and_Chemicals_Report.pdf | Fertilisers_and_Chemicals_Report.docx | Supporting material/Primary Interview Transcripts.docx | Supporting material/Shared Survey Form.pdf | Supporting material/Disclosure_Coding_Sheet.xlsx | Supporting material/Survey_Responses.xlsx | Supporting material/Respondent_Log.xlsx | BX28: CCTS_obligated, exchange, I1, I2, I3, I4, I5, I6, I7, I8, I9, I10, DQS_total, DQS_100, sub_quantification, sub_strategy, sub_credibility, second_coder_score, agreed_score, CBAM_covered_product, export_intensity, EU_export, PAT_legacy_entity, revenue, total_assets, PAT, ROA, total_debt, finance_cost, cost_of_debt_proxy, capex, reporting_year, date_accessed; No exact export ratio/EU destination, exchange, final unit-level CCTS obligation, PAT legacy status, comparable total capex, finance costs or second-coder values are provided. DQS is out of scope, not zero; report states public financials not found.
A29: DCM Shriram | B29: Fertilisers & chemicals | D29: 1 | F29: listed private | H29: 3 | I29: 3 | J29: 2 | K29: 3 | L29: 2 | M29: 2 | N29: 0 | O29: 2 | P29: 2 | Q29: 2 | R29: =IF(COUNT(H29:Q29)=10,SUM(H29:Q29),"") -> 21 | S29: =IF(ISNUMBER(R29),R29/30*100,"") -> 70 | T29: =IF(COUNT(H29:J29,L29)=4,SUM(H29:J29,L29),"") -> 10 | U29: =IF(COUNT(K29,M29:O29)=4,SUM(K29,M29:O29),"") -> 7 | V29: =IF(COUNT(P29:Q29)=2,SUM(P29:Q29),"") -> 4 | W29: FY2024-25 | X29: Research coder | AC29: unknown | AE29: 13538 | AH29: =IF(AND(ISNUMBER(AG29),ISNUMBER(AF29),AF29>0),AG29/AF29,"") | AM29: Large | AN29: FY2024-25 Annual Report + Sustainability Report | AO29: FY2025-26 | AP29: per indicator - see Evidence_Log | AQ29: Public company filing / annual-report source | AS29: OBS-028 | AT29: CONFLICT: workbook vs report — review | AV29: Fertilisers_and_Chemicals_Report.pdf | AW29: PDF pp.18–20; Tables 15–16 | AX29: Yes | AY29: No | AZ29: Report financials transcribed; ₹856cr is adjusted for a one-time ₹239cr deferred-tax credit, not unqualified PAT. ₹1,767cr is NET debt, not total debt. | BB29: =COUNT(H29:Q29) -> 10 | BC29: =IF(AND(ISNUMBER(R29),ISNUMBER(AU29)),R29-AU29,"") | BD29: Resolve report/workbook version and sample mismatch before analysis. | BF29: 1 | BG29: Directly covered or expected to have direct compliance obligations | BI29: 2 | BJ29: 856 | BK29: Limited (Deloitte) | BO29: 10–30% | BR29: 1767 | BT29: 5–15% | BV29: Reviewed supplied PDF/DOCX and related sources | BW29: Fertilisers_and_Chemicals_Report.pdf | Fertilisers_and_Chemicals_Report.docx | Supporting material/Primary Interview Transcripts.docx | Supporting material/Shared Survey Form.pdf | Supporting material/Disclosure_Coding_Sheet.xlsx | Supporting material/Survey_Responses.xlsx | Supporting material/Respondent_Log.xlsx | BX29: CCTS_obligated, exchange, BRSR_filer, second_coder_score, agreed_score, CBAM_covered_product, export_intensity, EU_export, PAT_legacy_entity, total_assets, PAT, ROA, total_debt, finance_cost, cost_of_debt_proxy, capex, date_accessed; No exact export ratio/EU destination, exchange, final unit-level CCTS obligation, PAT legacy status, comparable total capex, finance costs or second-coder values are provided.
A30: National Fertilizers Limited (NFL) | B30: Fertilisers & chemicals | D30: 1 | F30: PSU | G30: 1 | H30: 3 | I30: 2 | J30: 2 | K30: 2 | L30: 1 | M30: 1 | N30: 0 | O30: 1 | P30: 2 | Q30: 2 | R30: =IF(COUNT(H30:Q30)=10,SUM(H30:Q30),"") -> 16 | S30: =IF(ISNUMBER(R30),R30/30*100,"") -> 53.333333 | T30: =IF(COUNT(H30:J30,L30)=4,SUM(H30:J30,L30),"") -> 8 | U30: =IF(COUNT(K30,M30:O30)=4,SUM(K30,M30:O30),"") -> 4 | V30: =IF(COUNT(P30:Q30)=2,SUM(P30:Q30),"") -> 4 | W30: FY2024-25 | X30: Research coder | AC30: unknown | AE30: 21567.9 | AG30: 169.7 | AH30: =IF(AND(ISNUMBER(AG30),ISNUMBER(AF30),AF30>0),AG30/AF30,"") | AM30: Large | AN30: FY2024-25 Annual Report + BRSR | AO30: FY2025-26 | AP30: per indicator - see Evidence_Log | AQ30: Public company filing / annual-report source | AS30: OBS-029 | AT30: CONFLICT: workbook vs report — review | AV30: Fertilisers_and_Chemicals_Report.pdf | AW30: PDF pp.18–20; Tables 15–16 | AX30: Yes | AY30: No | AZ30: Report financials transcribed; PAT ₹169.7cr explicitly standalone; consolidated PAT ₹211.5cr stored separately. Revenue basis is not specified, so do not assume a consolidated revenue/PAT combination. | BB30: =COUNT(H30:Q30) -> 10 | BC30: =IF(AND(ISNUMBER(R30),ISNUMBER(AU30)),R30-AU30,"") | BD30: Resolve report/workbook version and sample mismatch before analysis. | BF30: 1 | BG30: Directly covered or expected to have direct compliance obligations | BI30: 0 | BM30: 211.5 | BO30: <10% | BT30: 5–15% | BV30: Reviewed supplied PDF/DOCX and related sources | BW30: Fertilisers_and_Chemicals_Report.pdf | Fertilisers_and_Chemicals_Report.docx | Supporting material/Primary Interview Transcripts.docx | Supporting material/Shared Survey Form.pdf | Supporting material/Disclosure_Coding_Sheet.xlsx | Supporting material/Survey_Responses.xlsx | Supporting material/Respondent_Log.xlsx | BX30: CCTS_obligated, exchange, second_coder_score, agreed_score, CBAM_covered_product, export_intensity, EU_export, PAT_legacy_entity, total_assets, ROA, total_debt, finance_cost, cost_of_debt_proxy, capex, date_accessed; No exact export ratio/EU destination, exchange, final unit-level CCTS obligation, PAT legacy status, comparable total capex, finance costs or second-coder values are provided.
A31: Chambal Fertilisers & Chemicals | B31: Fertilisers & chemicals | D31: 1 | F31: listed private | G31: 1 | H31: 2 | I31: 1 | J31: 2 | K31: 2 | L31: 2 | M31: 1 | N31: 0 | O31: 1 | P31: 3 | Q31: 2 | R31: =IF(COUNT(H31:Q31)=10,SUM(H31:Q31),"") -> 16 | S31: =IF(ISNUMBER(R31),R31/30*100,"") -> 53.333333 | T31: =IF(COUNT(H31:J31,L31)=4,SUM(H31:J31,L31),"") -> 7 | U31: =IF(COUNT(K31,M31:O31)=4,SUM(K31,M31:O31),"") -> 4 | V31: =IF(COUNT(P31:Q31)=2,SUM(P31:Q31),"") -> 5 | W31: FY2024-25 | X31: Research coder | AC31: unknown | AH31: =IF(AND(ISNUMBER(AG31),ISNUMBER(AF31),AF31>0),AG31/AF31,"") | AM31: Large | AN31: FY2024-25 Annual Report/BRSR | AO31: FY2024-25 | AP31: per indicator - see Evidence_Log | AQ31: Public company filing / annual-report source | AS31: OBS-030 | AT31: CONFLICT: workbook vs report — review | AU31: 12 | AV31: Fertilisers_and_Chemicals_Report.pdf | AW31: PDF pp.18–20; Tables 15–16 | AX31: Yes | AY31: No | AZ31: Report financials transcribed; ₹82.3cr is long-term debt only; do not fill total_debt. No actual revenue or PAT is supplied. | BB31: =COUNT(H31:Q31) -> 10 | BC31: =IF(AND(ISNUMBER(R31),ISNUMBER(AU31)),R31-AU31,"") -> 4 | BD31: Resolve report/workbook version and sample mismatch before analysis. | BF31: 1 | BG31: Directly covered or expected to have direct compliance obligations | BI31: 10 | BK31: Reasonable (Moore Singhi) | BO31: <10% | BP31: 82.3 | BS31: 0.099 | BT31: 5–15% | BV31: Reviewed supplied PDF/DOCX and related sources | BW31: Fertilisers_and_Chemicals_Report.pdf | Fertilisers_and_Chemicals_Report.docx | Supporting material/Primary Interview Transcripts.docx | Supporting material/Shared Survey Form.pdf | Supporting material/Disclosure_Coding_Sheet.xlsx | Supporting material/Survey_Responses.xlsx | Supporting material/Respondent_Log.xlsx | BX31: CCTS_obligated, exchange, second_coder_score, agreed_score, CBAM_covered_product, export_intensity, EU_export, PAT_legacy_entity, revenue, total_assets, PAT, ROA, total_debt, finance_cost, cost_of_debt_proxy, capex, date_accessed; No exact export ratio/EU destination, exchange, final unit-level CCTS obligation, PAT legacy status, comparable total capex, finance costs or second-coder values are provided.
A32: SRF Limited | B32: Fertilisers & chemicals | D32: 1 | F32: listed private | H32: 3 | I32: 2 | J32: 2 | K32: 2 | L32: 1 | M32: 1 | N32: 0 | O32: 1 | P32: 3 | Q32: 2 | R32: =IF(COUNT(H32:Q32)=10,SUM(H32:Q32),"") -> 17 | S32: =IF(ISNUMBER(R32),R32/30*100,"") -> 56.666667 | T32: =IF(COUNT(H32:J32,L32)=4,SUM(H32:J32,L32),"") -> 8 | U32: =IF(COUNT(K32,M32:O32)=4,SUM(K32,M32:O32),"") -> 4 | V32: =IF(COUNT(P32:Q32)=2,SUM(P32:Q32),"") -> 5 | W32: FY2024-25 | X32: Research coder | AC32: unknown | AF32: 22261 | AH32: =IF(AND(ISNUMBER(AG32),ISNUMBER(AF32),AF32>0),AG32/AF32,"") | AI32: 4527 | AM32: Large | AN32: FY2024-25 Annual Report | AO32: FY2024-25 | AP32: per indicator - see Evidence_Log | AQ32: Public company filing / annual-report source | AS32: OBS-031 | AT32: CONFLICT: workbook vs report — review | AV32: Fertilisers_and_Chemicals_Report.pdf | AW32: PDF pp.18–20; Tables 15–16 | AX32: Yes | AY32: No | AZ32: Report financials transcribed; Source does not fully identify standalone/consolidated basis. Do not combine with a different-basis denominator. | BB32: =COUNT(H32:Q32) -> 10 | BC32: =IF(AND(ISNUMBER(R32),ISNUMBER(AU32)),R32-AU32,"") | BD32: Resolve report/workbook version and sample mismatch before analysis. | BF32: 0 | BG32: Directly covered or expected to have direct compliance obligations | BI32: 1 | BK32: Reasonable + limited (BDO) | BL32: 13264 | BO32: >60% | BQ32: 89730 | BT32: 15–30% | BV32: Reviewed supplied PDF/DOCX and related sources | BW32: Fertilisers_and_Chemicals_Report.pdf | Fertilisers_and_Chemicals_Report.docx | Supporting material/Primary Interview Transcripts.docx | Supporting material/Shared Survey Form.pdf | Supporting material/Disclosure_Coding_Sheet.xlsx | Supporting material/Survey_Responses.xlsx | Supporting material/Respondent_Log.xlsx | BX32: CCTS_obligated, exchange, BRSR_filer, second_coder_score, agreed_score, CBAM_covered_product, export_intensity, EU_export, PAT_legacy_entity, revenue, PAT, ROA, finance_cost, cost_of_debt_proxy, capex, date_accessed; No exact export ratio/EU destination, exchange, final unit-level CCTS obligation, PAT legacy status, comparable total capex, finance costs or second-coder values are provided.
A33: PI Industries | B33: Fertilisers & chemicals | D33: 1 | F33: listed private | G33: 1 | H33: 3 | I33: 2 | J33: 2 | K33: 2 | L33: 2 | M33: 2 | N33: 0 | O33: 1 | P33: 3 | Q33: 2 | R33: =IF(COUNT(H33:Q33)=10,SUM(H33:Q33),"") -> 19 | S33: =IF(ISNUMBER(R33),R33/30*100,"") -> 63.333333 | T33: =IF(COUNT(H33:J33,L33)=4,SUM(H33:J33,L33),"") -> 9 | U33: =IF(COUNT(K33,M33:O33)=4,SUM(K33,M33:O33),"") -> 5 | V33: =IF(COUNT(P33:Q33)=2,SUM(P33:Q33),"") -> 5 | W33: FY2024-25 | X33: Research coder | AC33: unknown | AH33: =IF(AND(ISNUMBER(AG33),ISNUMBER(AF33),AF33>0),AG33/AF33,"") | AM33: Large | AN33: FY2024-25 Integrated Annual Report + BRSR | AP33: per indicator - see Evidence_Log | AQ33: Public company filing / annual-report source | AS33: OBS-032 | AT33: CONFLICT: workbook vs report — review | AV33: Fertilisers_and_Chemicals_Report.pdf | AW33: PDF pp.18–20; Tables 15–16 | AX33: Yes | AY33: No | AZ33: Not supplied | BA33: PI Industries appears in two sectors | BB33: =COUNT(H33:Q33) -> 10 | BC33: =IF(AND(ISNUMBER(R33),ISNUMBER(AU33)),R33-AU33,"") | BD33: Resolve report/workbook version and sample mismatch before analysis. | BF33: 0 | BG33: Not sure; Directly covered or expected to have direct compliance obligations | BI33: 2 | BK33: Reasonable (PwC) | BO33: >60% | BT33: No dedicated decarbonisation allocation; 15–30% | BV33: Reviewed supplied PDF/DOCX and related sources | BW33: Fertilisers_and_Chemicals_Report.pdf | Fertilisers_and_Chemicals_Report.docx | Supporting material/Primary Interview Transcripts.docx | Supporting material/Shared Survey Form.pdf | Supporting material/Disclosure_Coding_Sheet.xlsx | Supporting material/Survey_Responses.xlsx | Supporting material/Respondent_Log.xlsx | BX33: CCTS_obligated, exchange, second_coder_score, agreed_score, CBAM_covered_product, export_intensity, EU_export, PAT_legacy_entity, revenue, total_assets, PAT, ROA, total_debt, finance_cost, cost_of_debt_proxy, capex, reporting_year, date_accessed; No exact export ratio/EU destination, exchange, final unit-level CCTS obligation, PAT legacy status, comparable total capex, finance costs or second-coder values are provided. Report explicitly says financial figures not found.
A34: Mangalore Chemicals & Fertilizers | B34: Fertilisers & chemicals | D34: 1 | F34: listed private | G34: 1 | H34: 2 | I34: 2 | J34: 2 | K34: 1 | L34: 1 | M34: 0 | N34: 0 | O34: 0 | P34: 0 | Q34: 2 | R34: =IF(COUNT(H34:Q34)=10,SUM(H34:Q34),"") -> 10 | S34: =IF(ISNUMBER(R34),R34/30*100,"") -> 33.333333 | T34: =IF(COUNT(H34:J34,L34)=4,SUM(H34:J34,L34),"") -> 7 | U34: =IF(COUNT(K34,M34:O34)=4,SUM(K34,M34:O34),"") -> 1 | V34: =IF(COUNT(P34:Q34)=2,SUM(P34:Q34),"") -> 2 | W34: FY2024-25 | X34: Research coder | AC34: unknown | AH34: =IF(AND(ISNUMBER(AG34),ISNUMBER(AF34),AF34>0),AG34/AF34,"") | AM34: Mid | AN34: FY2024-25 BRSR / Annual Report | AP34: per indicator - see Evidence_Log | AQ34: Public company filing / annual-report source | AS34: OBS-033 | AT34: Workbook coded; report total agrees | AU34: 10 | AV34: Fertilisers_and_Chemicals_Report.pdf | AW34: PDF pp.18–20; Tables 15–16 | AX34: No | AY34: Yes | AZ34: Not supplied | BB34: =COUNT(H34:Q34) -> 10 | BC34: =IF(AND(ISNUMBER(R34),ISNUMBER(AU34)),R34-AU34,"") -> 0 | BF34: 1 | BG34: Directly covered or expected to have direct compliance obligations | BI34: 10 | BK34: None | BO34: <10% | BT34: Less than 5% | BV34: Reviewed supplied PDF/DOCX and related sources | BW34: Fertilisers_and_Chemicals_Report.pdf | Fertilisers_and_Chemicals_Report.docx | Supporting material/Primary Interview Transcripts.docx | Supporting material/Shared Survey Form.pdf | Supporting material/Disclosure_Coding_Sheet.xlsx | Supporting material/Survey_Responses.xlsx | Supporting material/Respondent_Log.xlsx | BX34: CCTS_obligated, exchange, second_coder_score, agreed_score, CBAM_covered_product, export_intensity, EU_export, PAT_legacy_entity, revenue, total_assets, PAT, ROA, total_debt, finance_cost, cost_of_debt_proxy, capex, reporting_year, date_accessed; No exact export ratio/EU destination, exchange, final unit-level CCTS obligation, PAT legacy status, comparable total capex, finance costs or second-coder values are provided. Report explicitly says financial figures not found.
A35: Southern Petrochemical Industries Corporation (SPIC) | B35: Fertilisers & chemicals | D35: 1 | F35: listed private | G35: 1 | H35: 1 | I35: 1 | J35: 1 | K35: 1 | L35: 1 | M35: 0 | N35: 0 | O35: 0 | P35: 0 | Q35: 1 | R35: =IF(COUNT(H35:Q35)=10,SUM(H35:Q35),"") -> 6 | S35: =IF(ISNUMBER(R35),R35/30*100,"") -> 20 | T35: =IF(COUNT(H35:J35,L35)=4,SUM(H35:J35,L35),"") -> 4 | U35: =IF(COUNT(K35,M35:O35)=4,SUM(K35,M35:O35),"") -> 1 | V35: =IF(COUNT(P35:Q35)=2,SUM(P35:Q35),"") -> 1 | W35: FY2024-25 | X35: Research coder | AC35: unknown | AH35: =IF(AND(ISNUMBER(AG35),ISNUMBER(AF35),AF35>0),AG35/AF35,"") | AM35: Mid | AN35: FY2024-25 Annual Report/BRSR | AP35: per indicator - see Evidence_Log | AQ35: Public company filing / annual-report source | AS35: OBS-034 | AT35: Workbook coded; report total agrees | AU35: 6 | AV35: Fertilisers_and_Chemicals_Report.pdf | AW35: PDF pp.18–20; Tables 15–16 | AX35: No | AY35: Yes | AZ35: Not supplied | BB35: =COUNT(H35:Q35) -> 10 | BC35: =IF(AND(ISNUMBER(R35),ISNUMBER(AU35)),R35-AU35,"") -> 0 | BF35: 1 | BG35: Directly covered or expected to have direct compliance obligations | BI35: 10 | BK35: None | BO35: <10% | BT35: Less than 5% | BV35: Reviewed supplied PDF/DOCX and related sources | BW35: Fertilisers_and_Chemicals_Report.pdf | Fertilisers_and_Chemicals_Report.docx | Supporting material/Primary Interview Transcripts.docx | Supporting material/Shared Survey Form.pdf | Supporting material/Disclosure_Coding_Sheet.xlsx | Supporting material/Survey_Responses.xlsx | Supporting material/Respondent_Log.xlsx | BX35: CCTS_obligated, exchange, second_coder_score, agreed_score, CBAM_covered_product, export_intensity, EU_export, PAT_legacy_entity, revenue, total_assets, PAT, ROA, total_debt, finance_cost, cost_of_debt_proxy, capex, reporting_year, date_accessed; No exact export ratio/EU destination, exchange, final unit-level CCTS obligation, PAT legacy status, comparable total capex, finance costs or second-coder values are provided. Report explicitly says financial figures not found.
A36: Khaitan Chemicals & Fertilizers | B36: Fertilisers & chemicals | D36: 1 | F36: listed private | G36: 1 | H36: 0 | I36: 0 | J36: 1 | K36: 1 | L36: 1 | M36: 0 | N36: 0 | O36: 0 | P36: 0 | Q36: 1 | R36: =IF(COUNT(H36:Q36)=10,SUM(H36:Q36),"") -> 4 | S36: =IF(ISNUMBER(R36),R36/30*100,"") -> 13.333333 | T36: =IF(COUNT(H36:J36,L36)=4,SUM(H36:J36,L36),"") -> 2 | U36: =IF(COUNT(K36,M36:O36)=4,SUM(K36,M36:O36),"") -> 1 | V36: =IF(COUNT(P36:Q36)=2,SUM(P36:Q36),"") -> 1 | W36: FY2024-25 | X36: Research coder | AC36: unknown | AE36: 1001.6 | AG36: 68.8 | AH36: =IF(AND(ISNUMBER(AG36),ISNUMBER(AF36),AF36>0),AG36/AF36,"") | AM36: Mid | AN36: FY2024-25 BRSR / Annual Report | AO36: FY2025-26 | AP36: per indicator - see Evidence_Log | AQ36: Public company filing / annual-report source | AS36: OBS-035 | AT36: CONFLICT: workbook vs report — review | AU36: 4 | AV36: Fertilisers_and_Chemicals_Report.pdf | AW36: PDF pp.18–20; Tables 15–16 | AX36: Yes | AY36: No | AZ36: Report financials transcribed; Source does not fully identify standalone/consolidated basis. Do not combine with a different-basis denominator. | BB36: =COUNT(H36:Q36) -> 10 | BC36: =IF(AND(ISNUMBER(R36),ISNUMBER(AU36)),R36-AU36,"") -> 0 | BD36: Resolve report/workbook version and sample mismatch before analysis. | BF36: 0 | BG36: Directly covered or expected to have direct compliance obligations | BI36: 10 | BK36: None | BO36: <10% | BT36: Less than 5% | BV36: Reviewed supplied PDF/DOCX and related sources | BW36: Fertilisers_and_Chemicals_Report.pdf | Fertilisers_and_Chemicals_Report.docx | Supporting material/Primary Interview Transcripts.docx | Supporting material/Shared Survey Form.pdf | Supporting material/Disclosure_Coding_Sheet.xlsx | Supporting material/Survey_Responses.xlsx | Supporting material/Respondent_Log.xlsx | BX36: CCTS_obligated, exchange, second_coder_score, agreed_score, CBAM_covered_product, export_intensity, EU_export, PAT_legacy_entity, total_assets, ROA, total_debt, finance_cost, cost_of_debt_proxy, capex, date_accessed; No exact export ratio/EU destination, exchange, final unit-level CCTS obligation, PAT legacy status, comparable total capex, finance costs or second-coder values are provided.
A37: Gujarat State Fertilizers & Chemicals (GSFC) | B37: Fertilisers & chemicals | D37: 1 | G37: 1 | H37: 3 | I37: 2 | J37: 2 | K37: 2 | L37: 1 | M37: 1 | N37: 0 | O37: 1 | P37: 2 | Q37: 2 | R37: =IF(COUNT(H37:Q37)=10,SUM(H37:Q37),"") -> 16 | S37: =IF(ISNUMBER(R37),R37/30*100,"") -> 53.333333 | T37: =IF(COUNT(H37:J37,L37)=4,SUM(H37:J37,L37),"") -> 8 | U37: =IF(COUNT(K37,M37:O37)=4,SUM(K37,M37:O37),"") -> 4 | V37: =IF(COUNT(P37:Q37)=2,SUM(P37:Q37),"") -> 4 | W37: FY2024-25 | X37: Research coder | AC37: unknown | AH37: =IF(AND(ISNUMBER(AG37),ISNUMBER(AF37),AF37>0),AG37/AF37,"") | AN37: FY2024-25 BRSR | AP37: per indicator - see Evidence_Log | AQ37: Public company filing / annual-report source | AS37: OBS-036 | AT37: CONFLICT: workbook vs report — review | AV37: Fertilisers_and_Chemicals_Report.pdf | AW37: PDF pp.18–20; Tables 15–16 | AX37: Yes | AY37: No | AZ37: Not supplied | BB37: =COUNT(H37:Q37) -> 10 | BC37: =IF(AND(ISNUMBER(R37),ISNUMBER(AU37)),R37-AU37,"") | BD37: Resolve report/workbook version and sample mismatch before analysis. | BV37: Reviewed supplied PDF/DOCX and related sources | BW37: Fertilisers_and_Chemicals_Report.pdf | Fertilisers_and_Chemicals_Report.docx | Supporting material/Primary Interview Transcripts.docx | Supporting material/Shared Survey Form.pdf | Supporting material/Disclosure_Coding_Sheet.xlsx | Supporting material/Survey_Responses.xlsx | Supporting material/Respondent_Log.xlsx | BX37: CCTS_obligated, exchange, ownership, second_coder_score, agreed_score, CBAM_covered_product, export_intensity, EU_export, PAT_legacy_entity, revenue, total_assets, PAT, ROA, total_debt, finance_cost, cost_of_debt_proxy, capex, size_band, reporting_year, date_accessed; No exact export ratio/EU destination, exchange, final unit-level CCTS obligation, PAT legacy status, comparable total capex, finance costs or second-coder values are provided. This firm appears only in the conflicting disclosure workbook, not the paper sample; no additional report financial/profile values can be assigned.
A38: Rashtriya Chemicals & Fertilizers (RCF) | B38: Fertilisers & chemicals | D38: 1 | G38: 1 | H38: 3 | I38: 2 | J38: 2 | K38: 2 | L38: 1 | M38: 1 | N38: 0 | O38: 1 | P38: 2 | Q38: 2 | R38: =IF(COUNT(H38:Q38)=10,SUM(H38:Q38),"") -> 16 | S38: =IF(ISNUMBER(R38),R38/30*100,"") -> 53.333333 | T38: =IF(COUNT(H38:J38,L38)=4,SUM(H38:J38,L38),"") -> 8 | U38: =IF(COUNT(K38,M38:O38)=4,SUM(K38,M38:O38),"") -> 4 | V38: =IF(COUNT(P38:Q38)=2,SUM(P38:Q38),"") -> 4 | W38: FY2024-25 | X38: Research coder | AC38: unknown | AH38: =IF(AND(ISNUMBER(AG38),ISNUMBER(AF38),AF38>0),AG38/AF38,"") | AN38: FY2024-25 Annual Report + BRSR | AP38: per indicator - see Evidence_Log | AQ38: Public company filing / annual-report source | AS38: OBS-037 | AT38: CONFLICT: workbook vs report — review | AV38: Fertilisers_and_Chemicals_Report.pdf | AW38: PDF pp.18–20; Tables 15–16 | AX38: Yes | AY38: No | AZ38: Not supplied | BB38: =COUNT(H38:Q38) -> 10 | BC38: =IF(AND(ISNUMBER(R38),ISNUMBER(AU38)),R38-AU38,"") | BD38: Resolve report/workbook version and sample mismatch before analysis. | BV38: Reviewed supplied PDF/DOCX and related sources | BW38: Fertilisers_and_Chemicals_Report.pdf | Fertilisers_and_Chemicals_Report.docx | Supporting material/Primary Interview Transcripts.docx | Supporting material/Shared Survey Form.pdf | Supporting material/Disclosure_Coding_Sheet.xlsx | Supporting material/Survey_Responses.xlsx | Supporting material/Respondent_Log.xlsx | BX38: CCTS_obligated, exchange, ownership, second_coder_score, agreed_score, CBAM_covered_product, export_intensity, EU_export, PAT_legacy_entity, revenue, total_assets, PAT, ROA, total_debt, finance_cost, cost_of_debt_proxy, capex, size_band, reporting_year, date_accessed; No exact export ratio/EU destination, exchange, final unit-level CCTS obligation, PAT legacy status, comparable total capex, finance costs or second-coder values are provided. This firm appears only in the conflicting disclosure workbook, not the paper sample; no additional report financial/profile values can be assigned.
A39: Coromandel International | B39: Fertilisers & chemicals | H39: 3 | I39: 3 | J39: 2 | K39: 2 | L39: 2 | M39: 2 | N39: 0 | O39: 2 | P39: 3 | Q39: 2 | R39: =IF(COUNT(H39:Q39)=10,SUM(H39:Q39),"") -> 21 | S39: =IF(ISNUMBER(R39),R39/30*100,"") -> 70 | T39: =IF(COUNT(H39:J39,L39)=4,SUM(H39:J39,L39),"") -> 10 | U39: =IF(COUNT(K39,M39:O39)=4,SUM(K39,M39:O39),"") -> 6 | V39: =IF(COUNT(P39:Q39)=2,SUM(P39:Q39),"") -> 5 | W39: FY2025-26 | X39: Research coder | AC39: unknown | AH39: =IF(AND(ISNUMBER(AG39),ISNUMBER(AF39),AF39>0),AG39/AF39,"") | AN39: FY2025-26 Integrated Annual Report | AP39: per indicator - see Evidence_Log | AQ39: Public company filing / annual-report source | AS39: OBS-038 | AT39: CONFLICT: workbook vs report — review | AV39: Fertilisers_and_Chemicals_Report.pdf | AW39: PDF pp.18–20; Tables 15–16 | AX39: Yes | AY39: No | AZ39: Not supplied | BB39: =COUNT(H39:Q39) -> 10 | BC39: =IF(AND(ISNUMBER(R39),ISNUMBER(AU39)),R39-AU39,"") | BD39: Resolve report/workbook version and sample mismatch before analysis. | BV39: Reviewed supplied PDF/DOCX and related sources | BW39: Fertilisers_and_Chemicals_Report.pdf | Fertilisers_and_Chemicals_Report.docx | Supporting material/Primary Interview Transcripts.docx | Supporting material/Shared Survey Form.pdf | Supporting material/Disclosure_Coding_Sheet.xlsx | Supporting material/Survey_Responses.xlsx | Supporting material/Respondent_Log.xlsx | BX39: CCTS_obligated, listed, exchange, ownership, BRSR_filer, second_coder_score, agreed_score, CBAM_covered_product, export_intensity, EU_export, PAT_legacy_entity, revenue, total_assets, PAT, ROA, total_debt, finance_cost, cost_of_debt_proxy, capex, size_band, reporting_year, date_accessed; No exact export ratio/EU destination, exchange, final unit-level CCTS obligation, PAT legacy status, comparable total capex, finance costs or second-coder values are provided. This firm appears only in the conflicting disclosure workbook, not the paper sample; no additional report financial/profile values can be assigned.
A40: Grasim | B40: Textiles & apparel | D40: 1 | F40: listed private | G40: 1 | R40: =IF(COUNT(H40:Q40)=10,SUM(H40:Q40),"") | S40: =IF(ISNUMBER(R40),R40/30*100,"") | T40: =IF(COUNT(H40:J40,L40)=4,SUM(H40:J40,L40),"") | U40: =IF(COUNT(K40,M40:O40)=4,SUM(K40,M40:O40),"") | V40: =IF(COUNT(P40:Q40)=2,SUM(P40:Q40),"") | AA40: 0 | AH40: =IF(AND(ISNUMBER(AG40),ISNUMBER(AF40),AF40>0),AG40/AF40,"") | AN40: BRSR, annual and sustainability reports (per-firm document not named in the report) | Textile_and_Apparel_Report.pdf (secondary report; primary firm filings not supplied) | AP40: PDF p.23, Figure 8 (reported DQS); p.10 B1 (period coverage); p.25 C1 (missing underlying dataset) | AS40: OBS-039 | AT40: Report total only; I1–I10 unavailable | AU40: 25 | AV40: Textile_and_Apparel_Report.pdf | AW40: PDF p.23; Figure 8 | AX40: No | AY40: No | AZ40: Not supplied | BB40: =COUNT(H40:Q40) -> 0 | BC40: =IF(AND(ISNUMBER(R40),ISNUMBER(AU40)),R40-AU40,"") | BD40: Report total available; I1–I10, firm-specific FY and financial amounts are not printed. Report coverage is FY2024-25, or FY2025-26 where available. Clean_Shared_Data.xlsx is referenced but absent. | BV40: Reviewed supplied PDF/DOCX and related sources | BW40: Textile/Textile_and_Apparel_Report.pdf | BX40: CCTS_obligated, exchange, I1, I2, I3, I4, I5, I6, I7, I8, I9, I10, DQS_total, DQS_100, sub_quantification, sub_strategy, sub_credibility, reporting_FY, coder_id, second_coder_score, agreed_score, export_intensity, EU_export, PAT_legacy_entity, revenue, total_assets, PAT, ROA, total_debt, finance_cost, cost_of_debt_proxy, capex, size_band, reporting_year, URL, date_accessed; Entire PDF and embedded-image inventory reviewed. It prints aggregate statistics and company DQS totals in Figure 8, but no firm indicator matrix, financial amounts, numeric export shares, exact exchange, individual coder scores, or per-firm fiscal year. C1 names Clean_Shared_Data.xlsx, absent from ZIP. B7 uses mixed ROE/ROA and an ordinal cost signal; neither can populate numeric ROA/debt ratios.
A41: Arvind | B41: Textiles & apparel | D41: 1 | F41: listed private | G41: 1 | R41: =IF(COUNT(H41:Q41)=10,SUM(H41:Q41),"") | S41: =IF(ISNUMBER(R41),R41/30*100,"") | T41: =IF(COUNT(H41:J41,L41)=4,SUM(H41:J41,L41),"") | U41: =IF(COUNT(K41,M41:O41)=4,SUM(K41,M41:O41),"") | V41: =IF(COUNT(P41:Q41)=2,SUM(P41:Q41),"") | AA41: 0 | AH41: =IF(AND(ISNUMBER(AG41),ISNUMBER(AF41),AF41>0),AG41/AF41,"") | AN41: BRSR, annual and sustainability reports (per-firm document not named in the report) | Textile_and_Apparel_Report.pdf (secondary report; primary firm filings not supplied) | AP41: PDF p.23, Figure 8 (reported DQS); p.10 B1 (period coverage); p.25 C1 (missing underlying dataset) | AS41: OBS-040 | AT41: Report total only; I1–I10 unavailable | AU41: 24 | AV41: Textile_and_Apparel_Report.pdf | AW41: PDF p.23; Figure 8 | AX41: No | AY41: No | AZ41: Not supplied | BB41: =COUNT(H41:Q41) -> 0 | BC41: =IF(AND(ISNUMBER(R41),ISNUMBER(AU41)),R41-AU41,"") | BD41: Report total available; I1–I10, firm-specific FY and financial amounts are not printed. Report coverage is FY2024-25, or FY2025-26 where available. Clean_Shared_Data.xlsx is referenced but absent. | BV41: Reviewed supplied PDF/DOCX and related sources | BW41: Textile/Textile_and_Apparel_Report.pdf | BX41: CCTS_obligated, exchange, I1, I2, I3, I4, I5, I6, I7, I8, I9, I10, DQS_total, DQS_100, sub_quantification, sub_strategy, sub_credibility, reporting_FY, coder_id, second_coder_score, agreed_score, export_intensity, EU_export, PAT_legacy_entity, revenue, total_assets, PAT, ROA, total_debt, finance_cost, cost_of_debt_proxy, capex, size_band, reporting_year, URL, date_accessed; Entire PDF and embedded-image inventory reviewed. It prints aggregate statistics and company DQS totals in Figure 8, but no firm indicator matrix, financial amounts, numeric export shares, exact exchange, individual coder scores, or per-firm fiscal year. C1 names Clean_Shared_Data.xlsx, absent from ZIP. B7 uses mixed ROE/ROA and an ordinal cost signal; neither can populate numeric ROA/debt ratios.
A42: Welspun Living | B42: Textiles & apparel | D42: 1 | F42: listed private | G42: 1 | R42: =IF(COUNT(H42:Q42)=10,SUM(H42:Q42),"") | S42: =IF(ISNUMBER(R42),R42/30*100,"") | T42: =IF(COUNT(H42:J42,L42)=4,SUM(H42:J42,L42),"") | U42: =IF(COUNT(K42,M42:O42)=4,SUM(K42,M42:O42),"") | V42: =IF(COUNT(P42:Q42)=2,SUM(P42:Q42),"") | AA42: 0 | AH42: =IF(AND(ISNUMBER(AG42),ISNUMBER(AF42),AF42>0),AG42/AF42,"") | AN42: BRSR, annual and sustainability reports (per-firm document not named in the report) | Textile_and_Apparel_Report.pdf (secondary report; primary firm filings not supplied) | AP42: PDF p.23, Figure 8 (reported DQS); p.10 B1 (period coverage); p.25 C1 (missing underlying dataset) | AS42: OBS-041 | AT42: Report total only; I1–I10 unavailable | AU42: 18 | AV42: Textile_and_Apparel_Report.pdf | AW42: PDF p.23; Figure 8 | AX42: No | AY42: No | AZ42: Not supplied | BB42: =COUNT(H42:Q42) -> 0 | BC42: =IF(AND(ISNUMBER(R42),ISNUMBER(AU42)),R42-AU42,"") | BD42: Report total available; I1–I10, firm-specific FY and financial amounts are not printed. Report coverage is FY2024-25, or FY2025-26 where available. Clean_Shared_Data.xlsx is referenced but absent. | BV42: Reviewed supplied PDF/DOCX and related sources | BW42: Textile/Textile_and_Apparel_Report.pdf | BX42: CCTS_obligated, exchange, I1, I2, I3, I4, I5, I6, I7, I8, I9, I10, DQS_total, DQS_100, sub_quantification, sub_strategy, sub_credibility, reporting_FY, coder_id, second_coder_score, agreed_score, export_intensity, EU_export, PAT_legacy_entity, revenue, total_assets, PAT, ROA, total_debt, finance_cost, cost_of_debt_proxy, capex, size_band, reporting_year, URL, date_accessed; Entire PDF and embedded-image inventory reviewed. It prints aggregate statistics and company DQS totals in Figure 8, but no firm indicator matrix, financial amounts, numeric export shares, exact exchange, individual coder scores, or per-firm fiscal year. C1 names Clean_Shared_Data.xlsx, absent from ZIP. B7 uses mixed ROE/ROA and an ordinal cost signal; neither can populate numeric ROA/debt ratios.
A43: Trident | B43: Textiles & apparel | D43: 1 | F43: listed private | G43: 1 | R43: =IF(COUNT(H43:Q43)=10,SUM(H43:Q43),"") | S43: =IF(ISNUMBER(R43),R43/30*100,"") | T43: =IF(COUNT(H43:J43,L43)=4,SUM(H43:J43,L43),"") | U43: =IF(COUNT(K43,M43:O43)=4,SUM(K43,M43:O43),"") | V43: =IF(COUNT(P43:Q43)=2,SUM(P43:Q43),"") | AA43: 0 | AH43: =IF(AND(ISNUMBER(AG43),ISNUMBER(AF43),AF43>0),AG43/AF43,"") | AN43: BRSR, annual and sustainability reports (per-firm document not named in the report) | Textile_and_Apparel_Report.pdf (secondary report; primary firm filings not supplied) | AP43: PDF p.23, Figure 8 (reported DQS); p.10 B1 (period coverage); p.25 C1 (missing underlying dataset) | AS43: OBS-042 | AT43: Report total only; I1–I10 unavailable | AU43: 17 | AV43: Textile_and_Apparel_Report.pdf | AW43: PDF p.23; Figure 8 | AX43: No | AY43: No | AZ43: Not supplied | BB43: =COUNT(H43:Q43) -> 0 | BC43: =IF(AND(ISNUMBER(R43),ISNUMBER(AU43)),R43-AU43,"") | BD43: Report total available; I1–I10, firm-specific FY and financial amounts are not printed. Report coverage is FY2024-25, or FY2025-26 where available. Clean_Shared_Data.xlsx is referenced but absent. | BV43: Reviewed supplied PDF/DOCX and related sources | BW43: Textile/Textile_and_Apparel_Report.pdf | BX43: CCTS_obligated, exchange, I1, I2, I3, I4, I5, I6, I7, I8, I9, I10, DQS_total, DQS_100, sub_quantification, sub_strategy, sub_credibility, reporting_FY, coder_id, second_coder_score, agreed_score, export_intensity, EU_export, PAT_legacy_entity, revenue, total_assets, PAT, ROA, total_debt, finance_cost, cost_of_debt_proxy, capex, size_band, reporting_year, URL, date_accessed; Entire PDF and embedded-image inventory reviewed. It prints aggregate statistics and company DQS totals in Figure 8, but no firm indicator matrix, financial amounts, numeric export shares, exact exchange, individual coder scores, or per-firm fiscal year. C1 names Clean_Shared_Data.xlsx, absent from ZIP. B7 uses mixed ROE/ROA and an ordinal cost signal; neither can populate numeric ROA/debt ratios.
A44: Indo Count | B44: Textiles & apparel | D44: 1 | F44: listed private | G44: 1 | R44: =IF(COUNT(H44:Q44)=10,SUM(H44:Q44),"") | S44: =IF(ISNUMBER(R44),R44/30*100,"") | T44: =IF(COUNT(H44:J44,L44)=4,SUM(H44:J44,L44),"") | U44: =IF(COUNT(K44,M44:O44)=4,SUM(K44,M44:O44),"") | V44: =IF(COUNT(P44:Q44)=2,SUM(P44:Q44),"") | AA44: 0 | AH44: =IF(AND(ISNUMBER(AG44),ISNUMBER(AF44),AF44>0),AG44/AF44,"") | AN44: BRSR, annual and sustainability reports (per-firm document not named in the report) | Textile_and_Apparel_Report.pdf (secondary report; primary firm filings not supplied) | AP44: PDF p.23, Figure 8 (reported DQS); p.10 B1 (period coverage); p.25 C1 (missing underlying dataset) | AS44: OBS-043 | AT44: Report total only; I1–I10 unavailable | AU44: 15 | AV44: Textile_and_Apparel_Report.pdf | AW44: PDF p.23; Figure 8 | AX44: No | AY44: No | AZ44: Not supplied | BB44: =COUNT(H44:Q44) -> 0 | BC44: =IF(AND(ISNUMBER(R44),ISNUMBER(AU44)),R44-AU44,"") | BD44: Report total available; I1–I10, firm-specific FY and financial amounts are not printed. Report coverage is FY2024-25, or FY2025-26 where available. Clean_Shared_Data.xlsx is referenced but absent. | BV44: Reviewed supplied PDF/DOCX and related sources | BW44: Textile/Textile_and_Apparel_Report.pdf | BX44: CCTS_obligated, exchange, I1, I2, I3, I4, I5, I6, I7, I8, I9, I10, DQS_total, DQS_100, sub_quantification, sub_strategy, sub_credibility, reporting_FY, coder_id, second_coder_score, agreed_score, export_intensity, EU_export, PAT_legacy_entity, revenue, total_assets, PAT, ROA, total_debt, finance_cost, cost_of_debt_proxy, capex, size_band, reporting_year, URL, date_accessed; Entire PDF and embedded-image inventory reviewed. It prints aggregate statistics and company DQS totals in Figure 8, but no firm indicator matrix, financial amounts, numeric export shares, exact exchange, individual coder scores, or per-firm fiscal year. C1 names Clean_Shared_Data.xlsx, absent from ZIP. B7 uses mixed ROE/ROA and an ordinal cost signal; neither can populate numeric ROA/debt ratios.
A45: Vardhman Textiles | B45: Textiles & apparel | D45: 1 | F45: listed private | G45: 1 | R45: =IF(COUNT(H45:Q45)=10,SUM(H45:Q45),"") | S45: =IF(ISNUMBER(R45),R45/30*100,"") | T45: =IF(COUNT(H45:J45,L45)=4,SUM(H45:J45,L45),"") | U45: =IF(COUNT(K45,M45:O45)=4,SUM(K45,M45:O45),"") | V45: =IF(COUNT(P45:Q45)=2,SUM(P45:Q45),"") | AA45: 0 | AH45: =IF(AND(ISNUMBER(AG45),ISNUMBER(AF45),AF45>0),AG45/AF45,"") | AN45: BRSR, annual and sustainability reports (per-firm document not named in the report) | Textile_and_Apparel_Report.pdf (secondary report; primary firm filings not supplied) | AP45: PDF p.23, Figure 8 (reported DQS); p.10 B1 (period coverage); p.25 C1 (missing underlying dataset) | AS45: OBS-044 | AT45: Report total only; I1–I10 unavailable | AU45: 12 | AV45: Textile_and_Apparel_Report.pdf | AW45: PDF p.23; Figure 8 | AX45: No | AY45: No | AZ45: Not supplied | BB45: =COUNT(H45:Q45) -> 0 | BC45: =IF(AND(ISNUMBER(R45),ISNUMBER(AU45)),R45-AU45,"") | BD45: Report total available; I1–I10, firm-specific FY and financial amounts are not printed. Report coverage is FY2024-25, or FY2025-26 where available. Clean_Shared_Data.xlsx is referenced but absent. | BV45: Reviewed supplied PDF/DOCX and related sources | BW45: Textile/Textile_and_Apparel_Report.pdf | BX45: CCTS_obligated, exchange, I1, I2, I3, I4, I5, I6, I7, I8, I9, I10, DQS_total, DQS_100, sub_quantification, sub_strategy, sub_credibility, reporting_FY, coder_id, second_coder_score, agreed_score, export_intensity, EU_export, PAT_legacy_entity, revenue, total_assets, PAT, ROA, total_debt, finance_cost, cost_of_debt_proxy, capex, size_band, reporting_year, URL, date_accessed; Entire PDF and embedded-image inventory reviewed. It prints aggregate statistics and company DQS totals in Figure 8, but no firm indicator matrix, financial amounts, numeric export shares, exact exchange, individual coder scores, or per-firm fiscal year. C1 names Clean_Shared_Data.xlsx, absent from ZIP. B7 uses mixed ROE/ROA and an ordinal cost signal; neither can populate numeric ROA/debt ratios.
A46: Raymond Lifestyle | B46: Textiles & apparel | D46: 1 | F46: listed private | G46: 1 | R46: =IF(COUNT(H46:Q46)=10,SUM(H46:Q46),"") | S46: =IF(ISNUMBER(R46),R46/30*100,"") | T46: =IF(COUNT(H46:J46,L46)=4,SUM(H46:J46,L46),"") | U46: =IF(COUNT(K46,M46:O46)=4,SUM(K46,M46:O46),"") | V46: =IF(COUNT(P46:Q46)=2,SUM(P46:Q46),"") | AA46: 0 | AH46: =IF(AND(ISNUMBER(AG46),ISNUMBER(AF46),AF46>0),AG46/AF46,"") | AN46: BRSR, annual and sustainability reports (per-firm document not named in the report) | Textile_and_Apparel_Report.pdf (secondary report; primary firm filings not supplied) | AP46: PDF p.23, Figure 8 (reported DQS); p.10 B1 (period coverage); p.25 C1 (missing underlying dataset) | AS46: OBS-045 | AT46: Report total only; I1–I10 unavailable | AU46: 12 | AV46: Textile_and_Apparel_Report.pdf | AW46: PDF p.23; Figure 8 | AX46: No | AY46: No | AZ46: Not supplied | BB46: =COUNT(H46:Q46) -> 0 | BC46: =IF(AND(ISNUMBER(R46),ISNUMBER(AU46)),R46-AU46,"") | BD46: Report total available; I1–I10, firm-specific FY and financial amounts are not printed. Report coverage is FY2024-25, or FY2025-26 where available. Clean_Shared_Data.xlsx is referenced but absent. | BV46: Reviewed supplied PDF/DOCX and related sources | BW46: Textile/Textile_and_Apparel_Report.pdf | BX46: CCTS_obligated, exchange, I1, I2, I3, I4, I5, I6, I7, I8, I9, I10, DQS_total, DQS_100, sub_quantification, sub_strategy, sub_credibility, reporting_FY, coder_id, second_coder_score, agreed_score, export_intensity, EU_export, PAT_legacy_entity, revenue, total_assets, PAT, ROA, total_debt, finance_cost, cost_of_debt_proxy, capex, size_band, reporting_year, URL, date_accessed; Entire PDF and embedded-image inventory reviewed. It prints aggregate statistics and company DQS totals in Figure 8, but no firm indicator matrix, financial amounts, numeric export shares, exact exchange, individual coder scores, or per-firm fiscal year. C1 names Clean_Shared_Data.xlsx, absent from ZIP. B7 uses mixed ROE/ROA and an ordinal cost signal; neither can populate numeric ROA/debt ratios.
A47: Page Industries | B47: Textiles & apparel | D47: 1 | F47: listed private | G47: 1 | R47: =IF(COUNT(H47:Q47)=10,SUM(H47:Q47),"") | S47: =IF(ISNUMBER(R47),R47/30*100,"") | T47: =IF(COUNT(H47:J47,L47)=4,SUM(H47:J47,L47),"") | U47: =IF(COUNT(K47,M47:O47)=4,SUM(K47,M47:O47),"") | V47: =IF(COUNT(P47:Q47)=2,SUM(P47:Q47),"") | AA47: 0 | AH47: =IF(AND(ISNUMBER(AG47),ISNUMBER(AF47),AF47>0),AG47/AF47,"") | AN47: BRSR, annual and sustainability reports (per-firm document not named in the report) | Textile_and_Apparel_Report.pdf (secondary report; primary firm filings not supplied) | AP47: PDF p.23, Figure 8 (reported DQS); p.10 B1 (period coverage); p.25 C1 (missing underlying dataset) | AS47: OBS-046 | AT47: Report total only; I1–I10 unavailable | AU47: 12 | AV47: Textile_and_Apparel_Report.pdf | AW47: PDF p.23; Figure 8 | AX47: No | AY47: No | AZ47: Not supplied | BB47: =COUNT(H47:Q47) -> 0 | BC47: =IF(AND(ISNUMBER(R47),ISNUMBER(AU47)),R47-AU47,"") | BD47: Report total available; I1–I10, firm-specific FY and financial amounts are not printed. Report coverage is FY2024-25, or FY2025-26 where available. Clean_Shared_Data.xlsx is referenced but absent. | BV47: Reviewed supplied PDF/DOCX and related sources | BW47: Textile/Textile_and_Apparel_Report.pdf | BX47: CCTS_obligated, exchange, I1, I2, I3, I4, I5, I6, I7, I8, I9, I10, DQS_total, DQS_100, sub_quantification, sub_strategy, sub_credibility, reporting_FY, coder_id, second_coder_score, agreed_score, export_intensity, EU_export, PAT_legacy_entity, revenue, total_assets, PAT, ROA, total_debt, finance_cost, cost_of_debt_proxy, capex, size_band, reporting_year, URL, date_accessed; Entire PDF and embedded-image inventory reviewed. It prints aggregate statistics and company DQS totals in Figure 8, but no firm indicator matrix, financial amounts, numeric export shares, exact exchange, individual coder scores, or per-firm fiscal year. C1 names Clean_Shared_Data.xlsx, absent from ZIP. B7 uses mixed ROE/ROA and an ordinal cost signal; neither can populate numeric ROA/debt ratios.
A48: Nahar Spinning | B48: Textiles & apparel | D48: 1 | F48: listed private | G48: 1 | R48: =IF(COUNT(H48:Q48)=10,SUM(H48:Q48),"") | S48: =IF(ISNUMBER(R48),R48/30*100,"") | T48: =IF(COUNT(H48:J48,L48)=4,SUM(H48:J48,L48),"") | U48: =IF(COUNT(K48,M48:O48)=4,SUM(K48,M48:O48),"") | V48: =IF(COUNT(P48:Q48)=2,SUM(P48:Q48),"") | AA48: 0 | AH48: =IF(AND(ISNUMBER(AG48),ISNUMBER(AF48),AF48>0),AG48/AF48,"") | AN48: BRSR, annual and sustainability reports (per-firm document not named in the report) | Textile_and_Apparel_Report.pdf (secondary report; primary firm filings not supplied) | AP48: PDF p.23, Figure 8 (reported DQS); p.10 B1 (period coverage); p.25 C1 (missing underlying dataset) | AS48: OBS-047 | AT48: Report total only; I1–I10 unavailable | AU48: 10 | AV48: Textile_and_Apparel_Report.pdf | AW48: PDF p.23; Figure 8 | AX48: No | AY48: No | AZ48: Not supplied | BB48: =COUNT(H48:Q48) -> 0 | BC48: =IF(AND(ISNUMBER(R48),ISNUMBER(AU48)),R48-AU48,"") | BD48: Report total available; I1–I10, firm-specific FY and financial amounts are not printed. Report coverage is FY2024-25, or FY2025-26 where available. Clean_Shared_Data.xlsx is referenced but absent. | BV48: Reviewed supplied PDF/DOCX and related sources | BW48: Textile/Textile_and_Apparel_Report.pdf | BX48: CCTS_obligated, exchange, I1, I2, I3, I4, I5, I6, I7, I8, I9, I10, DQS_total, DQS_100, sub_quantification, sub_strategy, sub_credibility, reporting_FY, coder_id, second_coder_score, agreed_score, export_intensity, EU_export, PAT_legacy_entity, revenue, total_assets, PAT, ROA, total_debt, finance_cost, cost_of_debt_proxy, capex, size_band, reporting_year, URL, date_accessed; Entire PDF and embedded-image inventory reviewed. It prints aggregate statistics and company DQS totals in Figure 8, but no firm indicator matrix, financial amounts, numeric export shares, exact exchange, individual coder scores, or per-firm fiscal year. C1 names Clean_Shared_Data.xlsx, absent from ZIP. B7 uses mixed ROE/ROA and an ordinal cost signal; neither can populate numeric ROA/debt ratios.
A49: K.P.R. Mill | B49: Textiles & apparel | D49: 1 | F49: listed private | G49: 1 | R49: =IF(COUNT(H49:Q49)=10,SUM(H49:Q49),"") | S49: =IF(ISNUMBER(R49),R49/30*100,"") | T49: =IF(COUNT(H49:J49,L49)=4,SUM(H49:J49,L49),"") | U49: =IF(COUNT(K49,M49:O49)=4,SUM(K49,M49:O49),"") | V49: =IF(COUNT(P49:Q49)=2,SUM(P49:Q49),"") | AA49: 0 | AH49: =IF(AND(ISNUMBER(AG49),ISNUMBER(AF49),AF49>0),AG49/AF49,"") | AN49: BRSR, annual and sustainability reports (per-firm document not named in the report) | Textile_and_Apparel_Report.pdf (secondary report; primary firm filings not supplied) | AP49: PDF p.23, Figure 8 (reported DQS); p.10 B1 (period coverage); p.25 C1 (missing underlying dataset) | AS49: OBS-048 | AT49: Report total only; I1–I10 unavailable | AU49: 10 | AV49: Textile_and_Apparel_Report.pdf | AW49: PDF p.23; Figure 8 | AX49: No | AY49: No | AZ49: Not supplied | BB49: =COUNT(H49:Q49) -> 0 | BC49: =IF(AND(ISNUMBER(R49),ISNUMBER(AU49)),R49-AU49,"") | BD49: Report total available; I1–I10, firm-specific FY and financial amounts are not printed. Report coverage is FY2024-25, or FY2025-26 where available. Clean_Shared_Data.xlsx is referenced but absent. | BV49: Reviewed supplied PDF/DOCX and related sources | BW49: Textile/Textile_and_Apparel_Report.pdf | BX49: CCTS_obligated, exchange, I1, I2, I3, I4, I5, I6, I7, I8, I9, I10, DQS_total, DQS_100, sub_quantification, sub_strategy, sub_credibility, reporting_FY, coder_id, second_coder_score, agreed_score, export_intensity, EU_export, PAT_legacy_entity, revenue, total_assets, PAT, ROA, total_debt, finance_cost, cost_of_debt_proxy, capex, size_band, reporting_year, URL, date_accessed; Entire PDF and embedded-image inventory reviewed. It prints aggregate statistics and company DQS totals in Figure 8, but no firm indicator matrix, financial amounts, numeric export shares, exact exchange, individual coder scores, or per-firm fiscal year. C1 names Clean_Shared_Data.xlsx, absent from ZIP. B7 uses mixed ROE/ROA and an ordinal cost signal; neither can populate numeric ROA/debt ratios.
A50: Gokaldas Exports | B50: Textiles & apparel | D50: 1 | F50: listed private | G50: 1 | R50: =IF(COUNT(H50:Q50)=10,SUM(H50:Q50),"") | S50: =IF(ISNUMBER(R50),R50/30*100,"") | T50: =IF(COUNT(H50:J50,L50)=4,SUM(H50:J50,L50),"") | U50: =IF(COUNT(K50,M50:O50)=4,SUM(K50,M50:O50),"") | V50: =IF(COUNT(P50:Q50)=2,SUM(P50:Q50),"") | AA50: 0 | AH50: =IF(AND(ISNUMBER(AG50),ISNUMBER(AF50),AF50>0),AG50/AF50,"") | AN50: BRSR, annual and sustainability reports (per-firm document not named in the report) | Textile_and_Apparel_Report.pdf (secondary report; primary firm filings not supplied) | AP50: PDF p.23, Figure 8 (reported DQS); p.10 B1 (period coverage); p.25 C1 (missing underlying dataset) | AS50: OBS-049 | AT50: Report total only; I1–I10 unavailable | AU50: 9 | AV50: Textile_and_Apparel_Report.pdf | AW50: PDF p.23; Figure 8 | AX50: No | AY50: No | AZ50: Not supplied | BB50: =COUNT(H50:Q50) -> 0 | BC50: =IF(AND(ISNUMBER(R50),ISNUMBER(AU50)),R50-AU50,"") | BD50: Report total available; I1–I10, firm-specific FY and financial amounts are not printed. Report coverage is FY2024-25, or FY2025-26 where available. Clean_Shared_Data.xlsx is referenced but absent. | BV50: Reviewed supplied PDF/DOCX and related sources | BW50: Textile/Textile_and_Apparel_Report.pdf | BX50: CCTS_obligated, exchange, I1, I2, I3, I4, I5, I6, I7, I8, I9, I10, DQS_total, DQS_100, sub_quantification, sub_strategy, sub_credibility, reporting_FY, coder_id, second_coder_score, agreed_score, export_intensity, EU_export, PAT_legacy_entity, revenue, total_assets, PAT, ROA, total_debt, finance_cost, cost_of_debt_proxy, capex, size_band, reporting_year, URL, date_accessed; Entire PDF and embedded-image inventory reviewed. It prints aggregate statistics and company DQS totals in Figure 8, but no firm indicator matrix, financial amounts, numeric export shares, exact exchange, individual coder scores, or per-firm fiscal year. C1 names Clean_Shared_Data.xlsx, absent from ZIP. B7 uses mixed ROE/ROA and an ordinal cost signal; neither can populate numeric ROA/debt ratios.
A51: Lux Industries | B51: Textiles & apparel | D51: 1 | F51: listed private | G51: 1 | R51: =IF(COUNT(H51:Q51)=10,SUM(H51:Q51),"") | S51: =IF(ISNUMBER(R51),R51/30*100,"") | T51: =IF(COUNT(H51:J51,L51)=4,SUM(H51:J51,L51),"") | U51: =IF(COUNT(K51,M51:O51)=4,SUM(K51,M51:O51),"") | V51: =IF(COUNT(P51:Q51)=2,SUM(P51:Q51),"") | AA51: 0 | AH51: =IF(AND(ISNUMBER(AG51),ISNUMBER(AF51),AF51>0),AG51/AF51,"") | AN51: BRSR, annual and sustainability reports (per-firm document not named in the report) | Textile_and_Apparel_Report.pdf (secondary report; primary firm filings not supplied) | AP51: PDF p.23, Figure 8 (reported DQS); p.10 B1 (period coverage); p.25 C1 (missing underlying dataset) | AS51: OBS-050 | AT51: Report total only; I1–I10 unavailable | AU51: 6 | AV51: Textile_and_Apparel_Report.pdf | AW51: PDF p.23; Figure 8 | AX51: No | AY51: No | AZ51: Not supplied | BB51: =COUNT(H51:Q51) -> 0 | BC51: =IF(AND(ISNUMBER(R51),ISNUMBER(AU51)),R51-AU51,"") | BD51: Report total available; I1–I10, firm-specific FY and financial amounts are not printed. Report coverage is FY2024-25, or FY2025-26 where available. Clean_Shared_Data.xlsx is referenced but absent. | BV51: Reviewed supplied PDF/DOCX and related sources | BW51: Textile/Textile_and_Apparel_Report.pdf | BX51: CCTS_obligated, exchange, I1, I2, I3, I4, I5, I6, I7, I8, I9, I10, DQS_total, DQS_100, sub_quantification, sub_strategy, sub_credibility, reporting_FY, coder_id, second_coder_score, agreed_score, export_intensity, EU_export, PAT_legacy_entity, revenue, total_assets, PAT, ROA, total_debt, finance_cost, cost_of_debt_proxy, capex, size_band, reporting_year, URL, date_accessed; Entire PDF and embedded-image inventory reviewed. It prints aggregate statistics and company DQS totals in Figure 8, but no firm indicator matrix, financial amounts, numeric export shares, exact exchange, individual coder scores, or per-firm fiscal year. C1 names Clean_Shared_Data.xlsx, absent from ZIP. B7 uses mixed ROE/ROA and an ordinal cost signal; neither can populate numeric ROA/debt ratios.
A52: RSWM | B52: Textiles & apparel | D52: 1 | F52: listed private | G52: 1 | R52: =IF(COUNT(H52:Q52)=10,SUM(H52:Q52),"") | S52: =IF(ISNUMBER(R52),R52/30*100,"") | T52: =IF(COUNT(H52:J52,L52)=4,SUM(H52:J52,L52),"") | U52: =IF(COUNT(K52,M52:O52)=4,SUM(K52,M52:O52),"") | V52: =IF(COUNT(P52:Q52)=2,SUM(P52:Q52),"") | AA52: 0 | AH52: =IF(AND(ISNUMBER(AG52),ISNUMBER(AF52),AF52>0),AG52/AF52,"") | AN52: BRSR, annual and sustainability reports (per-firm document not named in the report) | Textile_and_Apparel_Report.pdf (secondary report; primary firm filings not supplied) | AP52: PDF p.23, Figure 8 (reported DQS); p.10 B1 (period coverage); p.25 C1 (missing underlying dataset) | AS52: OBS-051 | AT52: Report total only; I1–I10 unavailable | AU52: 3 | AV52: Textile_and_Apparel_Report.pdf | AW52: PDF p.23; Figure 8 | AX52: No | AY52: No | AZ52: Not supplied | BB52: =COUNT(H52:Q52) -> 0 | BC52: =IF(AND(ISNUMBER(R52),ISNUMBER(AU52)),R52-AU52,"") | BD52: Report total available; I1–I10, firm-specific FY and financial amounts are not printed. Report coverage is FY2024-25, or FY2025-26 where available. Clean_Shared_Data.xlsx is referenced but absent. | BV52: Reviewed supplied PDF/DOCX and related sources | BW52: Textile/Textile_and_Apparel_Report.pdf | BX52: CCTS_obligated, exchange, I1, I2, I3, I4, I5, I6, I7, I8, I9, I10, DQS_total, DQS_100, sub_quantification, sub_strategy, sub_credibility, reporting_FY, coder_id, second_coder_score, agreed_score, export_intensity, EU_export, PAT_legacy_entity, revenue, total_assets, PAT, ROA, total_debt, finance_cost, cost_of_debt_proxy, capex, size_band, reporting_year, URL, date_accessed; Entire PDF and embedded-image inventory reviewed. It prints aggregate statistics and company DQS totals in Figure 8, but no firm indicator matrix, financial amounts, numeric export shares, exact exchange, individual coder scores, or per-firm fiscal year. C1 names Clean_Shared_Data.xlsx, absent from ZIP. B7 uses mixed ROE/ROA and an ordinal cost signal; neither can populate numeric ROA/debt ratios.
A53: Ahluwalia Contracts (India) Ltd | B53: Buildings & construction | D53: 1 | F53: listed private | G53: 1 | H53: 1 | I53: 1 | J53: 0 | K53: 1 | L53: 2 | M53: 0 | N53: 0 | O53: 0 | P53: 1 | Q53: 2 | R53: =IF(COUNT(H53:Q53)=10,SUM(H53:Q53),"") -> 8 | S53: =IF(ISNUMBER(R53),R53/30*100,"") -> 26.666667 | T53: =IF(COUNT(H53:J53,L53)=4,SUM(H53:J53,L53),"") -> 4 | U53: =IF(COUNT(K53,M53:O53)=4,SUM(K53,M53:O53),"") -> 1 | V53: =IF(COUNT(P53:Q53)=2,SUM(P53:Q53),"") -> 3 | W53: FY 2024-25 | X53: You (Researcher 1) | Y53: 8 | Z53: =IF(ISNUMBER(R53),R53,"") -> 8 | AA53: 0 | AB53: 0 | AC53: 0 | AE53: 4098.62 | AF53: 3705.95 | AG53: 202.08 | AH53: =IF(AND(ISNUMBER(AG53),ISNUMBER(AF53),AF53>0),AG53/AF53,"") -> 0.054528528 | AI53: 14 | AK53: 1.8385 | AM53: Large | AN53: Company BRSR / annual report; per-indicator source is inside the Evidence_Log text | AO53: FY 2024-25 | AP53: per indicator - see Evidence_Log | AS53: OBS-052 | AT53: Workbook final scores; two coders supplied | AU53: 8 | AV53: Buildings_and_Construction_Report.pdf | AW53: PDF pp.20–21; disclosure scoring | AX53: No | AY53: Yes | AZ53: Inherited source values; verify scope/year | BB53: =COUNT(H53:Q53) -> 10 | BC53: =IF(AND(ISNUMBER(R53),ISNUMBER(AU53)),R53-AU53,"") -> 0 | BV53: Reviewed supplied PDF/DOCX and related sources | BW53: Buildings_and_Construction_Report.pdf (all sections; especially 6 and 11) | Appendices_A_to_G.pdf (full; Appendix G score matrix) | In Depth Interview Transcript.pdf (full) | Climate_Disclosure_Scoring_MASTER_10Firms_v1.xlsx (scoring and evidence) | Consolidated_Firm_Panel_FY24-FY26.xlsx (finance rows and definitions) | BX53: CCTS_obligated, exchange, PAT_legacy_entity, finance_cost, capex, URL, date_accessed; No exact annual finance-cost amount or total-capex amount is present in supplied files; BRSR I5 narratives concern environmental/social/R&D shares, not total company capex. No named exchange or firm/unit CCTS legal evidence. Unknown original access dates cannot be reconstructed.
A54: Astral Limited | B54: Buildings & construction | D54: 1 | F54: listed private | G54: 1 | H54: 3 | I54: 1 | J54: 2 | K54: 2 | L54: 2 | M54: 1 | N54: 0 | O54: 1 | P54: 3 | Q54: 2 | R54: =IF(COUNT(H54:Q54)=10,SUM(H54:Q54),"") -> 17 | S54: =IF(ISNUMBER(R54),R54/30*100,"") -> 56.666667 | T54: =IF(COUNT(H54:J54,L54)=4,SUM(H54:J54,L54),"") -> 8 | U54: =IF(COUNT(K54,M54:O54)=4,SUM(K54,M54:O54),"") -> 4 | V54: =IF(COUNT(P54:Q54)=2,SUM(P54:Q54),"") -> 5 | W54: FY 2025-26 | X54: You (Researcher 1) | Y54: 16 | Z54: =IF(ISNUMBER(R54),R54,"") -> 17 | AA54: 0 | AB54: 0.075646389 | AC54: unknown | AE54: 5832.4 | AF54: 5056 | AG54: 518.9 | AH54: =IF(AND(ISNUMBER(AG54),ISNUMBER(AF54),AF54>0),AG54/AF54,"") -> 0.10263054 | AI54: 143.9 | AK54: 0.3437 | AM54: Large | AN54: Company BRSR / annual report; per-indicator source is inside the Evidence_Log text | AO54: FY 2024-25 | AP54: per indicator - see Evidence_Log | AS54: OBS-053 | AT54: Workbook final scores; two coders supplied | AU54: 17 | AV54: Buildings_and_Construction_Report.pdf | AW54: PDF pp.20–21; disclosure scoring | AX54: No | AY54: Yes | AZ54: Inherited source values; verify scope/year | BB54: =COUNT(H54:Q54) -> 10 | BC54: =IF(AND(ISNUMBER(R54),ISNUMBER(AU54)),R54-AU54,"") -> 0 | BV54: Reviewed supplied PDF/DOCX and related sources | BW54: Buildings_and_Construction_Report.pdf (all sections; especially 6 and 11) | Appendices_A_to_G.pdf (full; Appendix G score matrix) | In Depth Interview Transcript.pdf (full) | Climate_Disclosure_Scoring_MASTER_10Firms_v1.xlsx (scoring and evidence) | Consolidated_Firm_Panel_FY24-FY26.xlsx (finance rows and definitions) | BX54: CCTS_obligated, exchange, EU_export, PAT_legacy_entity, finance_cost, capex, URL, date_accessed; No exact annual finance-cost amount or total-capex amount is present in supplied files; BRSR I5 narratives concern environmental/social/R&D shares, not total company capex. No named exchange or firm/unit CCTS legal evidence. Unknown original access dates cannot be reconstructed.
A55: NBCC (India) Limited | B55: Buildings & construction | D55: 1 | F55: PSU | G55: 1 | H55: 3 | I55: 0 | J55: 1 | K55: 2 | L55: 2 | M55: 1 | N55: 0 | O55: 1 | P55: 1 | Q55: 2 | R55: =IF(COUNT(H55:Q55)=10,SUM(H55:Q55),"") -> 13 | S55: =IF(ISNUMBER(R55),R55/30*100,"") -> 43.333333 | T55: =IF(COUNT(H55:J55,L55)=4,SUM(H55:J55,L55),"") -> 6 | U55: =IF(COUNT(K55,M55:O55)=4,SUM(K55,M55:O55),"") -> 4 | V55: =IF(COUNT(P55:Q55)=2,SUM(P55:Q55),"") -> 3 | W55: FY 2024-25 | X55: You (Researcher 1) | Y55: 14 | Z55: =IF(ISNUMBER(R55),R55,"") -> 13 | AB55: 0.0459 | AC55: unknown | AD55: 0 | AH55: =IF(AND(ISNUMBER(AG55),ISNUMBER(AF55),AF55>0),AG55/AF55,"") | AN55: Company BRSR / annual report; per-indicator source is inside the Evidence_Log text | AP55: per indicator - see Evidence_Log | AS55: OBS-054 | AT55: Workbook final scores; two coders supplied | AU55: 13 | AV55: Buildings_and_Construction_Report.pdf | AW55: PDF pp.20–21; disclosure scoring | AX55: No | AY55: Yes | AZ55: Not supplied | BB55: =COUNT(H55:Q55) -> 10 | BC55: =IF(AND(ISNUMBER(R55),ISNUMBER(AU55)),R55-AU55,"") -> 0 | BV55: Reviewed supplied PDF/DOCX and related sources | BW55: Buildings_and_Construction_Report.pdf (all sections; especially 6 and 11) | Appendices_A_to_G.pdf (full; Appendix G score matrix) | In Depth Interview Transcript.pdf (full) | Climate_Disclosure_Scoring_MASTER_10Firms_v1.xlsx (scoring and evidence) | Consolidated_Firm_Panel_FY24-FY26.xlsx (finance rows and definitions) | BX55: CCTS_obligated, exchange, CBAM_covered_product, EU_export, revenue, total_assets, PAT, ROA, total_debt, finance_cost, cost_of_debt_proxy, capex, size_band, reporting_year, URL, date_accessed; Report section 11.1 explicitly says NBCC consolidated financials unavailable; no financial workbook in archive. Leave revenue/assets/PAT/debt/finance-cost/capex/size blank. PAT-negative and export-share notes are available in the scoring workbook.
A56: Kajaria Ceramics Limited | B56: Buildings & construction | D56: 1 | F56: listed private | G56: 1 | H56: 3 | I56: 0 | J56: 1 | K56: 2 | L56: 1 | M56: 0 | N56: 0 | O56: 0 | P56: 1 | Q56: 2 | R56: =IF(COUNT(H56:Q56)=10,SUM(H56:Q56),"") -> 10 | S56: =IF(ISNUMBER(R56),R56/30*100,"") -> 33.333333 | T56: =IF(COUNT(H56:J56,L56)=4,SUM(H56:J56,L56),"") -> 5 | U56: =IF(COUNT(K56,M56:O56)=4,SUM(K56,M56:O56),"") -> 2 | V56: =IF(COUNT(P56:Q56)=2,SUM(P56:Q56),"") -> 3 | W56: FY 2024-25 | X56: You (Researcher 1) | Y56: 9 | Z56: =IF(ISNUMBER(R56),R56,"") -> 10 | AA56: 0 | AB56: 0.011820749 | AC56: unknown | AD56: 0 | AE56: 4635.07 | AF56: 3756.2 | AG56: 300.02 | AH56: =IF(AND(ISNUMBER(AG56),ISNUMBER(AF56),AF56>0),AG56/AF56,"") -> 0.079873276 | AI56: 175.94 | AK56: 0.1156 | AM56: Large | AN56: Company BRSR / annual report; per-indicator source is inside the Evidence_Log text | AO56: FY 2024-25 | AP56: per indicator - see Evidence_Log | AS56: OBS-055 | AT56: Workbook final scores; two coders supplied | AU56: 10 | AV56: Buildings_and_Construction_Report.pdf | AW56: PDF pp.20–21; disclosure scoring | AX56: No | AY56: Yes | AZ56: Inherited source values; verify scope/year | BB56: =COUNT(H56:Q56) -> 10 | BC56: =IF(AND(ISNUMBER(R56),ISNUMBER(AU56)),R56-AU56,"") -> 0 | BV56: Reviewed supplied PDF/DOCX and related sources | BW56: Buildings_and_Construction_Report.pdf (all sections; especially 6 and 11) | Appendices_A_to_G.pdf (full; Appendix G score matrix) | In Depth Interview Transcript.pdf (full) | Climate_Disclosure_Scoring_MASTER_10Firms_v1.xlsx (scoring and evidence) | Consolidated_Firm_Panel_FY24-FY26.xlsx (finance rows and definitions) | BX56: CCTS_obligated, exchange, EU_export, finance_cost, capex, URL, date_accessed; No exact annual finance-cost amount or total-capex amount is present in supplied files; BRSR I5 narratives concern environmental/social/R&D shares, not total company capex. No named exchange or firm/unit CCTS legal evidence. Unknown original access dates cannot be reconstructed.
A57: Mahindra Lifespace Developers Ltd | B57: Buildings & construction | D57: 1 | F57: listed private | G57: 1 | H57: 3 | I57: 3 | J57: 3 | K57: 3 | L57: 2 | M57: 1 | N57: 0 | O57: 2 | P57: 3 | Q57: 3 | R57: =IF(COUNT(H57:Q57)=10,SUM(H57:Q57),"") -> 23 | S57: =IF(ISNUMBER(R57),R57/30*100,"") -> 76.666667 | T57: =IF(COUNT(H57:J57,L57)=4,SUM(H57:J57,L57),"") -> 11 | U57: =IF(COUNT(K57,M57:O57)=4,SUM(K57,M57:O57),"") -> 6 | V57: =IF(COUNT(P57:Q57)=2,SUM(P57:Q57),"") -> 6 | W57: FY 2025-26 | X57: You (Researcher 1) | Y57: 24 | Z57: =IF(ISNUMBER(R57),R57,"") -> 23 | AA57: 0 | AB57: 0 | AC57: 0 | AD57: 0 | AE57: 372.27 | AF57: 6420.77 | AG57: 61.35 | AH57: =IF(AND(ISNUMBER(AG57),ISNUMBER(AF57),AF57>0),AG57/AF57,"") -> 0.0095549288 | AI57: 1431.74 | AK57: 0.0927 | AM57: Large | AN57: Company BRSR / annual report; per-indicator source is inside the Evidence_Log text | AO57: FY 2024-25 | AP57: per indicator - see Evidence_Log | AS57: OBS-056 | AT57: Workbook final scores; two coders supplied | AU57: 23 | AV57: Buildings_and_Construction_Report.pdf | AW57: PDF pp.20–21; disclosure scoring | AX57: No | AY57: Yes | AZ57: Inherited source values; verify scope/year | BB57: =COUNT(H57:Q57) -> 10 | BC57: =IF(AND(ISNUMBER(R57),ISNUMBER(AU57)),R57-AU57,"") -> 0 | BV57: Reviewed supplied PDF/DOCX and related sources | BW57: Buildings_and_Construction_Report.pdf (all sections; especially 6 and 11) | Appendices_A_to_G.pdf (full; Appendix G score matrix) | In Depth Interview Transcript.pdf (full) | Climate_Disclosure_Scoring_MASTER_10Firms_v1.xlsx (scoring and evidence) | Consolidated_Firm_Panel_FY24-FY26.xlsx (finance rows and definitions) | BX57: CCTS_obligated, exchange, finance_cost, capex, URL, date_accessed; No exact annual finance-cost amount or total-capex amount is present in supplied files; BRSR I5 narratives concern environmental/social/R&D shares, not total company capex. No named exchange or firm/unit CCTS legal evidence. Unknown original access dates cannot be reconstructed.
A58: DLF Limited | B58: Buildings & construction | D58: 1 | F58: listed private | G58: 1 | H58: 3 | I58: 1 | J58: 2 | K58: 2 | L58: 2 | M58: 1 | N58: 0 | O58: 2 | P58: 3 | Q58: 2 | R58: =IF(COUNT(H58:Q58)=10,SUM(H58:Q58),"") -> 18 | S58: =IF(ISNUMBER(R58),R58/30*100,"") -> 60 | T58: =IF(COUNT(H58:J58,L58)=4,SUM(H58:J58,L58),"") -> 8 | U58: =IF(COUNT(K58,M58:O58)=4,SUM(K58,M58:O58),"") -> 5 | V58: =IF(COUNT(P58:Q58)=2,SUM(P58:Q58),"") -> 5 | W58: FY2025-26 | X58: Teammate B (Researcher 1) | Y58: 18 | Z58: =IF(ISNUMBER(R58),R58,"") -> 18 | AA58: 0 | AB58: 0 | AC58: 0 | AE58: 7993.66 | AF58: 69475.37 | AG58: 4366.82 | AH58: =IF(AND(ISNUMBER(AG58),ISNUMBER(AF58),AF58>0),AG58/AF58,"") -> 0.062854217 | AI58: 3854.03 | AK58: 0.094 | AM58: Large | AN58: Company BRSR / annual report; per-indicator source is inside the Evidence_Log text | AO58: FY 2024-25 | AP58: per indicator - see Evidence_Log | AQ58: https://www.dlf.in/annual_docket/Annual-report-2025-26.pdf | AS58: OBS-057 | AT58: Workbook final scores; two coders supplied | AU58: 18 | AV58: Buildings_and_Construction_Report.pdf | AW58: PDF pp.20–21; disclosure scoring | AX58: No | AY58: Yes | AZ58: Inherited source values; verify scope/year | BB58: =COUNT(H58:Q58) -> 10 | BC58: =IF(AND(ISNUMBER(R58),ISNUMBER(AU58)),R58-AU58,"") -> 0 | BV58: Reviewed supplied PDF/DOCX and related sources | BW58: Buildings_and_Construction_Report.pdf (all sections; especially 6 and 11) | Appendices_A_to_G.pdf (full; Appendix G score matrix) | In Depth Interview Transcript.pdf (full) | Climate_Disclosure_Scoring_MASTER_10Firms_v1.xlsx (scoring and evidence) | Consolidated_Firm_Panel_FY24-FY26.xlsx (finance rows and definitions) | BX58: CCTS_obligated, exchange, PAT_legacy_entity, finance_cost, capex, date_accessed; No exact annual finance-cost amount or total-capex amount is present in supplied files; BRSR I5 narratives concern environmental/social/R&D shares, not total company capex. No named exchange or firm/unit CCTS legal evidence. Unknown original access dates cannot be reconstructed.
A59: Larsen & Toubro Limited | B59: Buildings & construction | D59: 1 | F59: listed private | G59: 1 | H59: 3 | I59: 3 | J59: 3 | K59: 3 | L59: 2 | M59: 2 | N59: 1 | O59: 2 | P59: 3 | Q59: 2 | R59: =IF(COUNT(H59:Q59)=10,SUM(H59:Q59),"") -> 24 | S59: =IF(ISNUMBER(R59),R59/30*100,"") -> 80 | T59: =IF(COUNT(H59:J59,L59)=4,SUM(H59:J59,L59),"") -> 11 | U59: =IF(COUNT(K59,M59:O59)=4,SUM(K59,M59:O59),"") -> 8 | V59: =IF(COUNT(P59:Q59)=2,SUM(P59:Q59),"") -> 5 | W59: FY2025-26 | X59: Teammate B (Researcher 1) | Y59: 22 | Z59: =IF(ISNUMBER(R59),R59,"") -> 24 | AA59: 1 | AB59: 0.49882161 | AC59: unknown | AE59: 255734.45 | AF59: 379524.1 | AG59: 17673.33 | AH59: =IF(AND(ISNUMBER(AG59),ISNUMBER(AF59),AF59>0),AG59/AF59,"") -> 0.046567082 | AI59: 129559.34 | AK59: 0.0775 | AM59: Large | AN59: Company BRSR / annual report; per-indicator source is inside the Evidence_Log text | AO59: FY 2024-25 | AP59: per indicator - see Evidence_Log | AQ59: https://investors.larsentoubro.com/pdf/2026/Integrated%20Report%202025-26.pdf | AS59: OBS-058 | AT59: Workbook final scores; two coders supplied | AU59: 24 | AV59: Buildings_and_Construction_Report.pdf | AW59: PDF pp.20–21; disclosure scoring | AX59: No | AY59: Yes | AZ59: Inherited source values; verify scope/year | BB59: =COUNT(H59:Q59) -> 10 | BC59: =IF(AND(ISNUMBER(R59),ISNUMBER(AU59)),R59-AU59,"") -> 0 | BV59: Reviewed supplied PDF/DOCX and related sources | BW59: Buildings_and_Construction_Report.pdf (all sections; especially 6 and 11) | Appendices_A_to_G.pdf (full; Appendix G score matrix) | In Depth Interview Transcript.pdf (full) | Climate_Disclosure_Scoring_MASTER_10Firms_v1.xlsx (scoring and evidence) | Consolidated_Firm_Panel_FY24-FY26.xlsx (finance rows and definitions) | BX59: CCTS_obligated, exchange, EU_export, PAT_legacy_entity, finance_cost, capex, date_accessed; No exact annual finance-cost amount or total-capex amount is present in supplied files; BRSR I5 narratives concern environmental/social/R&D shares, not total company capex. No named exchange or firm/unit CCTS legal evidence. Unknown original access dates cannot be reconstructed.
A60: Lodha Developers Limited (Macrotech Developers) | B60: Buildings & construction | D60: 1 | F60: listed private | G60: 1 | H60: 3 | I60: 3 | J60: 3 | K60: 2 | L60: 2 | M60: 1 | N60: 0 | O60: 1 | P60: 3 | Q60: 2 | R60: =IF(COUNT(H60:Q60)=10,SUM(H60:Q60),"") -> 20 | S60: =IF(ISNUMBER(R60),R60/30*100,"") -> 66.666667 | T60: =IF(COUNT(H60:J60,L60)=4,SUM(H60:J60,L60),"") -> 11 | U60: =IF(COUNT(K60,M60:O60)=4,SUM(K60,M60:O60),"") -> 4 | V60: =IF(COUNT(P60:Q60)=2,SUM(P60:Q60),"") -> 5 | W60: FY2025-26 | X60: Teammate B (Researcher 1) | Y60: 20 | Z60: =IF(ISNUMBER(R60),R60,"") -> 20 | AA60: 0 | AB60: 0 | AC60: 0 | AE60: 13779.5 | AF60: 49840.6 | AG60: 2766.6 | AH60: =IF(AND(ISNUMBER(AG60),ISNUMBER(AF60),AF60>0),AG60/AF60,"") -> 0.055508963 | AI60: 7080.4 | AK60: 0.0958 | AM60: Large | AN60: Company BRSR / annual report; per-indicator source is inside the Evidence_Log text | AO60: FY 2024-25 | AP60: per indicator - see Evidence_Log | AQ60: https://www.lodhagroup.com/sites/default/files/2026-07/Integrated_Report_FY2026.pdf | AS60: OBS-059 | AT60: Workbook final scores; two coders supplied | AU60: 20 | AV60: Buildings_and_Construction_Report.pdf | AW60: PDF pp.20–21; disclosure scoring | AX60: No | AY60: Yes | AZ60: Inherited source values; verify scope/year | BB60: =COUNT(H60:Q60) -> 10 | BC60: =IF(AND(ISNUMBER(R60),ISNUMBER(AU60)),R60-AU60,"") -> 0 | BV60: Reviewed supplied PDF/DOCX and related sources | BW60: Buildings_and_Construction_Report.pdf (all sections; especially 6 and 11) | Appendices_A_to_G.pdf (full; Appendix G score matrix) | In Depth Interview Transcript.pdf (full) | Climate_Disclosure_Scoring_MASTER_10Firms_v1.xlsx (scoring and evidence) | Consolidated_Firm_Panel_FY24-FY26.xlsx (finance rows and definitions) | BX60: CCTS_obligated, exchange, PAT_legacy_entity, finance_cost, capex, date_accessed; No exact annual finance-cost amount or total-capex amount is present in supplied files; BRSR I5 narratives concern environmental/social/R&D shares, not total company capex. No named exchange or firm/unit CCTS legal evidence. Unknown original access dates cannot be reconstructed.
A61: Godrej Properties Limited | B61: Buildings & construction | D61: 1 | F61: listed private | G61: 1 | H61: 3 | I61: 3 | J61: 3 | K61: 2 | L61: 2 | M61: 1 | N61: 0 | O61: 1 | P61: 3 | Q61: 3 | R61: =IF(COUNT(H61:Q61)=10,SUM(H61:Q61),"") -> 21 | S61: =IF(ISNUMBER(R61),R61/30*100,"") -> 70 | T61: =IF(COUNT(H61:J61,L61)=4,SUM(H61:J61,L61),"") -> 11 | U61: =IF(COUNT(K61,M61:O61)=4,SUM(K61,M61:O61),"") -> 4 | V61: =IF(COUNT(P61:Q61)=2,SUM(P61:Q61),"") -> 6 | W61: FY2025-26 | X61: Teammate B (Researcher 1) | Y61: 21 | Z61: =IF(ISNUMBER(R61),R61,"") -> 21 | AA61: 0 | AB61: 0 | AC61: 0 | AE61: 4922.84 | AF61: 55465.52 | AG61: 1389.23 | AH61: =IF(AND(ISNUMBER(AG61),ISNUMBER(AF61),AF61>0),AG61/AF61,"") -> 0.025046732 | AI61: 12561.16 | AK61: 0.0898 | AM61: Large | AN61: Company BRSR / annual report; per-indicator source is inside the Evidence_Log text | AO61: FY 2024-25 | AP61: per indicator - see Evidence_Log | AQ61: https://gplwebsitecdnblob.blob.core.windows.net/godrej-cdn/Files/integrated-annual-report-2025-26-cmr3h9e05000iyuph5mm4d3e6.pdf | AS61: OBS-060 | AT61: Workbook final scores; two coders supplied | AU61: 21 | AV61: Buildings_and_Construction_Report.pdf | AW61: PDF pp.20–21; disclosure scoring | AX61: No | AY61: Yes | AZ61: Inherited source values; verify scope/year | BB61: =COUNT(H61:Q61) -> 10 | BC61: =IF(AND(ISNUMBER(R61),ISNUMBER(AU61)),R61-AU61,"") -> 0 | BV61: Reviewed supplied PDF/DOCX and related sources | BW61: Buildings_and_Construction_Report.pdf (all sections; especially 6 and 11) | Appendices_A_to_G.pdf (full; Appendix G score matrix) | In Depth Interview Transcript.pdf (full) | Climate_Disclosure_Scoring_MASTER_10Firms_v1.xlsx (scoring and evidence) | Consolidated_Firm_Panel_FY24-FY26.xlsx (finance rows and definitions) | BX61: CCTS_obligated, exchange, PAT_legacy_entity, finance_cost, capex, date_accessed; No exact annual finance-cost amount or total-capex amount is present in supplied files; BRSR I5 narratives concern environmental/social/R&D shares, not total company capex. No named exchange or firm/unit CCTS legal evidence. Unknown original access dates cannot be reconstructed.
A62: NCC Limited | B62: Buildings & construction | D62: 1 | F62: listed private | G62: 1 | H62: 3 | I62: 3 | J62: 1 | K62: 2 | L62: 2 | M62: 1 | N62: 0 | O62: 1 | P62: 3 | Q62: 2 | R62: =IF(COUNT(H62:Q62)=10,SUM(H62:Q62),"") -> 18 | S62: =IF(ISNUMBER(R62),R62/30*100,"") -> 60 | T62: =IF(COUNT(H62:J62,L62)=4,SUM(H62:J62,L62),"") -> 9 | U62: =IF(COUNT(K62,M62:O62)=4,SUM(K62,M62:O62),"") -> 4 | V62: =IF(COUNT(P62:Q62)=2,SUM(P62:Q62),"") -> 5 | W62: FY2025-26 | X62: Teammate B (Researcher 1) | Y62: 18 | Z62: =IF(ISNUMBER(R62),R62,"") -> 18 | AA62: 0 | AB62: 0.0016604082 | AC62: unknown | AE62: 22199.36 | AF62: 21006.38 | AG62: 868.25 | AH62: =IF(AND(ISNUMBER(AG62),ISNUMBER(AF62),AF62>0),AG62/AF62,"") -> 0.041332681 | AI62: 1593.58 | AK62: 0.5285 | AM62: Large | AN62: Company BRSR / annual report; per-indicator source is inside the Evidence_Log text | AO62: FY 2024-25 | AP62: per indicator - see Evidence_Log | AQ62: https://www.ncclimited.com/annual-reports/NCCAnnualReport202526.pdf | AS62: OBS-061 | AT62: Workbook final scores; two coders supplied | AU62: 18 | AV62: Buildings_and_Construction_Report.pdf | AW62: PDF pp.20–21; disclosure scoring | AX62: No | AY62: Yes | AZ62: Inherited source values; verify scope/year | BB62: =COUNT(H62:Q62) -> 10 | BC62: =IF(AND(ISNUMBER(R62),ISNUMBER(AU62)),R62-AU62,"") -> 0 | BV62: Reviewed supplied PDF/DOCX and related sources | BW62: Buildings_and_Construction_Report.pdf (all sections; especially 6 and 11) | Appendices_A_to_G.pdf (full; Appendix G score matrix) | In Depth Interview Transcript.pdf (full) | Climate_Disclosure_Scoring_MASTER_10Firms_v1.xlsx (scoring and evidence) | Consolidated_Firm_Panel_FY24-FY26.xlsx (finance rows and definitions) | BX62: CCTS_obligated, exchange, EU_export, PAT_legacy_entity, finance_cost, capex, date_accessed; No exact annual finance-cost amount or total-capex amount is present in supplied files; BRSR I5 narratives concern environmental/social/R&D shares, not total company capex. No named exchange or firm/unit CCTS legal evidence. Unknown original access dates cannot be reconstructed.
A63: Adani Ports & SEZ | B63: Transport & logistics | R63: =IF(COUNT(H63:Q63)=10,SUM(H63:Q63),"") | S63: =IF(ISNUMBER(R63),R63/30*100,"") | T63: =IF(COUNT(H63:J63,L63)=4,SUM(H63:J63,L63),"") | U63: =IF(COUNT(K63,M63:O63)=4,SUM(K63,M63:O63),"") | V63: =IF(COUNT(P63:Q63)=2,SUM(P63:Q63),"") | W63: FY2024-25 | AA63: 0 | AH63: =IF(AND(ISNUMBER(AG63),ISNUMBER(AF63),AF63>0),AG63/AF63,"") | AK63: 0.0681 | AN63: FY2024-25 annual report, BRSR/climate disclosure and official investor pages (firm-specific documents not named in the report) | Transport_and_Logistics_Report.pdf (secondary report; FY2024-25 source dataset) | AO63: FY2024-25 | AP63: PDF pp.19–20, section 8.9: DQS and financing-cost tables | AS63: OBS-062 | AT63: Report total only; I1–I10 unavailable | AU63: 24 | AV63: Transport_and_Logistics_Report.pdf | AW63: PDF pp.19–20; section 8.9 | AX63: No | AY63: No | AZ63: Report financing ratio only; finance-cost and borrowing amounts not supplied. | BB63: =COUNT(H63:Q63) -> 0 | BC63: =IF(AND(ISNUMBER(R63),ISNUMBER(AU63)),R63-AU63,"") | BD63: Report provides total DQS only; I1–I10 are unavailable. Source dataset is FY2024-25 and was verified by the report team on 16 August 2026 (not a new verification here). Reported ratio is finance cost divided by average borrowings; underlying amounts and consistent statement basis are not given. | BV63: Reviewed supplied PDF/DOCX and related sources | BW63: Transport and Logistics/Transport_and_Logistics_Report.pdf | BX63: CCTS_obligated, listed, exchange, ownership, BRSR_filer, I1, I2, I3, I4, I5, I6, I7, I8, I9, I10, DQS_total, DQS_100, sub_quantification, sub_strategy, sub_credibility, coder_id, second_coder_score, agreed_score, export_intensity, EU_export, PAT_legacy_entity, revenue, total_assets, PAT, ROA, total_debt, finance_cost, capex, size_band, URL, date_accessed; Entire PDF reviewed including charts, appendices, links and attachments. DQS totals and some financing-cost ratios are printed; I1–I10, revenue, assets, PAT, debt, finance-cost amounts, capex, firm-specific ownership/size/export fractions, exact exchanges and primary URLs are not provided. Survey firmographics are pooled and cannot assign attributes to individual companies. Report financing ratio only; finance-cost and borrowing amounts not supplied.
A64: Tata Motors | B64: Transport & logistics | R64: =IF(COUNT(H64:Q64)=10,SUM(H64:Q64),"") | S64: =IF(ISNUMBER(R64),R64/30*100,"") | T64: =IF(COUNT(H64:J64,L64)=4,SUM(H64:J64,L64),"") | U64: =IF(COUNT(K64,M64:O64)=4,SUM(K64,M64:O64),"") | V64: =IF(COUNT(P64:Q64)=2,SUM(P64:Q64),"") | W64: FY2024-25 | AA64: 0 | AH64: =IF(AND(ISNUMBER(AG64),ISNUMBER(AF64),AF64>0),AG64/AF64,"") | AK64: 0.0621 | AN64: FY2024-25 annual report, BRSR/climate disclosure and official investor pages (firm-specific documents not named in the report) | Transport_and_Logistics_Report.pdf (secondary report; FY2024-25 source dataset) | AO64: FY2024-25 | AP64: PDF pp.19–20, section 8.9: DQS and financing-cost tables | AS64: OBS-063 | AT64: Report total only; I1–I10 unavailable | AU64: 21 | AV64: Transport_and_Logistics_Report.pdf | AW64: PDF pp.19–20; section 8.9 | AX64: No | AY64: No | AZ64: Report financing ratio only; finance-cost and borrowing amounts not supplied. | BB64: =COUNT(H64:Q64) -> 0 | BC64: =IF(AND(ISNUMBER(R64),ISNUMBER(AU64)),R64-AU64,"") | BD64: Report provides total DQS only; I1–I10 are unavailable. Source dataset is FY2024-25 and was verified by the report team on 16 August 2026 (not a new verification here). Reported ratio is finance cost divided by average borrowings; underlying amounts and consistent statement basis are not given. | BV64: Reviewed supplied PDF/DOCX and related sources | BW64: Transport and Logistics/Transport_and_Logistics_Report.pdf | BX64: CCTS_obligated, listed, exchange, ownership, BRSR_filer, I1, I2, I3, I4, I5, I6, I7, I8, I9, I10, DQS_total, DQS_100, sub_quantification, sub_strategy, sub_credibility, coder_id, second_coder_score, agreed_score, export_intensity, EU_export, PAT_legacy_entity, revenue, total_assets, PAT, ROA, total_debt, finance_cost, capex, size_band, URL, date_accessed; Entire PDF reviewed including charts, appendices, links and attachments. DQS totals and some financing-cost ratios are printed; I1–I10, revenue, assets, PAT, debt, finance-cost amounts, capex, firm-specific ownership/size/export fractions, exact exchanges and primary URLs are not provided. Survey firmographics are pooled and cannot assign attributes to individual companies. Report financing ratio only; finance-cost and borrowing amounts not supplied.
A65: Ashok Leyland | B65: Transport & logistics | R65: =IF(COUNT(H65:Q65)=10,SUM(H65:Q65),"") | S65: =IF(ISNUMBER(R65),R65/30*100,"") | T65: =IF(COUNT(H65:J65,L65)=4,SUM(H65:J65,L65),"") | U65: =IF(COUNT(K65,M65:O65)=4,SUM(K65,M65:O65),"") | V65: =IF(COUNT(P65:Q65)=2,SUM(P65:Q65),"") | W65: FY2024-25 | AA65: 0 | AH65: =IF(AND(ISNUMBER(AG65),ISNUMBER(AF65),AF65>0),AG65/AF65,"") | AK65: 0.1649 | AN65: FY2024-25 annual report, BRSR/climate disclosure and official investor pages (firm-specific documents not named in the report) | Transport_and_Logistics_Report.pdf (secondary report; FY2024-25 source dataset) | AO65: FY2024-25 | AP65: PDF pp.19–20, section 8.9: DQS and financing-cost tables | AS65: OBS-064 | AT65: Report total only; I1–I10 unavailable | AU65: 17 | AV65: Transport_and_Logistics_Report.pdf | AW65: PDF pp.19–20; section 8.9 | AX65: No | AY65: No | AZ65: Report financing ratio only; finance-cost and borrowing amounts not supplied. | BB65: =COUNT(H65:Q65) -> 0 | BC65: =IF(AND(ISNUMBER(R65),ISNUMBER(AU65)),R65-AU65,"") | BD65: Report provides total DQS only; I1–I10 are unavailable. Source dataset is FY2024-25 and was verified by the report team on 16 August 2026 (not a new verification here). Reported ratio is finance cost divided by average borrowings; underlying amounts and consistent statement basis are not given. | BV65: Reviewed supplied PDF/DOCX and related sources | BW65: Transport and Logistics/Transport_and_Logistics_Report.pdf | BX65: CCTS_obligated, listed, exchange, ownership, BRSR_filer, I1, I2, I3, I4, I5, I6, I7, I8, I9, I10, DQS_total, DQS_100, sub_quantification, sub_strategy, sub_credibility, coder_id, second_coder_score, agreed_score, export_intensity, EU_export, PAT_legacy_entity, revenue, total_assets, PAT, ROA, total_debt, finance_cost, capex, size_band, URL, date_accessed; Entire PDF reviewed including charts, appendices, links and attachments. DQS totals and some financing-cost ratios are printed; I1–I10, revenue, assets, PAT, debt, finance-cost amounts, capex, firm-specific ownership/size/export fractions, exact exchanges and primary URLs are not provided. Survey firmographics are pooled and cannot assign attributes to individual companies. Report financing ratio only; finance-cost and borrowing amounts not supplied.
A66: Maruti Suzuki | B66: Transport & logistics | R66: =IF(COUNT(H66:Q66)=10,SUM(H66:Q66),"") | S66: =IF(ISNUMBER(R66),R66/30*100,"") | T66: =IF(COUNT(H66:J66,L66)=4,SUM(H66:J66,L66),"") | U66: =IF(COUNT(K66,M66:O66)=4,SUM(K66,M66:O66),"") | V66: =IF(COUNT(P66:Q66)=2,SUM(P66:Q66),"") | W66: FY2024-25 | AA66: 0 | AH66: =IF(AND(ISNUMBER(AG66),ISNUMBER(AF66),AF66>0),AG66/AF66,"") | AN66: FY2024-25 annual report, BRSR/climate disclosure and official investor pages (firm-specific documents not named in the report) | Transport_and_Logistics_Report.pdf (secondary report; FY2024-25 source dataset) | AO66: FY2024-25 | AP66: PDF pp.19–20, section 8.9: DQS and financing-cost tables | AS66: OBS-065 | AT66: Report total only; I1–I10 unavailable | AU66: 17 | AV66: Transport_and_Logistics_Report.pdf | AW66: PDF pp.19–20; section 8.9 | AX66: No | AY66: No | AZ66: Not applicable: report calls firm effectively debt-free. | BB66: =COUNT(H66:Q66) -> 0 | BC66: =IF(AND(ISNUMBER(R66),ISNUMBER(AU66)),R66-AU66,"") | BD66: Report provides total DQS only; I1–I10 are unavailable. Source dataset is FY2024-25 and was verified by the report team on 16 August 2026 (not a new verification here). Not applicable: report calls firm effectively debt-free. | BV66: Reviewed supplied PDF/DOCX and related sources | BW66: Transport and Logistics/Transport_and_Logistics_Report.pdf | BX66: CCTS_obligated, listed, exchange, ownership, BRSR_filer, I1, I2, I3, I4, I5, I6, I7, I8, I9, I10, DQS_total, DQS_100, sub_quantification, sub_strategy, sub_credibility, coder_id, second_coder_score, agreed_score, export_intensity, EU_export, PAT_legacy_entity, revenue, total_assets, PAT, ROA, total_debt, finance_cost, cost_of_debt_proxy, capex, size_band, URL, date_accessed; Entire PDF reviewed including charts, appendices, links and attachments. DQS totals and some financing-cost ratios are printed; I1–I10, revenue, assets, PAT, debt, finance-cost amounts, capex, firm-specific ownership/size/export fractions, exact exchanges and primary URLs are not provided. Survey firmographics are pooled and cannot assign attributes to individual companies. Not applicable: report calls firm effectively debt-free.
A67: Delhivery | B67: Transport & logistics | R67: =IF(COUNT(H67:Q67)=10,SUM(H67:Q67),"") | S67: =IF(ISNUMBER(R67),R67/30*100,"") | T67: =IF(COUNT(H67:J67,L67)=4,SUM(H67:J67,L67),"") | U67: =IF(COUNT(K67,M67:O67)=4,SUM(K67,M67:O67),"") | V67: =IF(COUNT(P67:Q67)=2,SUM(P67:Q67),"") | W67: FY2024-25 | AA67: 0 | AH67: =IF(AND(ISNUMBER(AG67),ISNUMBER(AF67),AF67>0),AG67/AF67,"") | AK67: 1.5222 | AN67: FY2024-25 annual report, BRSR/climate disclosure and official investor pages (firm-specific documents not named in the report) | Transport_and_Logistics_Report.pdf (secondary report; FY2024-25 source dataset) | AO67: FY2024-25 | AP67: PDF pp.19–20, section 8.9: DQS and financing-cost tables | AS67: OBS-066 | AT67: Report total only; I1–I10 unavailable | AU67: 17 | AV67: Transport_and_Logistics_Report.pdf | AW67: PDF pp.19–20; section 8.9 | AX67: No | AY67: No | AZ67: Report financing ratio only; finance-cost and borrowing amounts not supplied. | BB67: =COUNT(H67:Q67) -> 0 | BC67: =IF(AND(ISNUMBER(R67),ISNUMBER(AU67)),R67-AU67,"") | BD67: Report provides total DQS only; I1–I10 are unavailable. Source dataset is FY2024-25 and was verified by the report team on 16 August 2026 (not a new verification here). Reported ratio is finance cost divided by average borrowings; underlying amounts and consistent statement basis are not given. Delhivery 152.22% is explicitly a lease-distorted outlier and should not be treated as an effective interest rate. | BV67: Reviewed supplied PDF/DOCX and related sources | BW67: Transport and Logistics/Transport_and_Logistics_Report.pdf | BX67: CCTS_obligated, listed, exchange, ownership, BRSR_filer, I1, I2, I3, I4, I5, I6, I7, I8, I9, I10, DQS_total, DQS_100, sub_quantification, sub_strategy, sub_credibility, coder_id, second_coder_score, agreed_score, export_intensity, EU_export, PAT_legacy_entity, revenue, total_assets, PAT, ROA, total_debt, finance_cost, capex, size_band, URL, date_accessed; Entire PDF reviewed including charts, appendices, links and attachments. DQS totals and some financing-cost ratios are printed; I1–I10, revenue, assets, PAT, debt, finance-cost amounts, capex, firm-specific ownership/size/export fractions, exact exchanges and primary URLs are not provided. Survey firmographics are pooled and cannot assign attributes to individual companies. Report financing ratio only; finance-cost and borrowing amounts not supplied.
A68: Blue Dart | B68: Transport & logistics | R68: =IF(COUNT(H68:Q68)=10,SUM(H68:Q68),"") | S68: =IF(ISNUMBER(R68),R68/30*100,"") | T68: =IF(COUNT(H68:J68,L68)=4,SUM(H68:J68,L68),"") | U68: =IF(COUNT(K68,M68:O68)=4,SUM(K68,M68:O68),"") | V68: =IF(COUNT(P68:Q68)=2,SUM(P68:Q68),"") | W68: FY2024-25 | AA68: 0 | AH68: =IF(AND(ISNUMBER(AG68),ISNUMBER(AF68),AF68>0),AG68/AF68,"") | AN68: FY2024-25 annual report, BRSR/climate disclosure and official investor pages (firm-specific documents not named in the report) | Transport_and_Logistics_Report.pdf (secondary report; FY2024-25 source dataset) | AO68: FY2024-25 | AP68: PDF pp.19–20, section 8.9: DQS and financing-cost tables | AS68: OBS-067 | AT68: Report total only; I1–I10 unavailable | AU68: 17 | AV68: Transport_and_Logistics_Report.pdf | AW68: PDF pp.19–20; section 8.9 | AX68: No | AY68: No | AZ68: Not applicable: report states no outstanding external borrowings. | BB68: =COUNT(H68:Q68) -> 0 | BC68: =IF(AND(ISNUMBER(R68),ISNUMBER(AU68)),R68-AU68,"") | BD68: Report provides total DQS only; I1–I10 are unavailable. Source dataset is FY2024-25 and was verified by the report team on 16 August 2026 (not a new verification here). Not applicable: report states no outstanding external borrowings. | BV68: Reviewed supplied PDF/DOCX and related sources | BW68: Transport and Logistics/Transport_and_Logistics_Report.pdf | BX68: CCTS_obligated, listed, exchange, ownership, BRSR_filer, I1, I2, I3, I4, I5, I6, I7, I8, I9, I10, DQS_total, DQS_100, sub_quantification, sub_strategy, sub_credibility, coder_id, second_coder_score, agreed_score, export_intensity, EU_export, PAT_legacy_entity, revenue, total_assets, PAT, ROA, total_debt, finance_cost, cost_of_debt_proxy, capex, size_band, URL, date_accessed; Entire PDF reviewed including charts, appendices, links and attachments. DQS totals and some financing-cost ratios are printed; I1–I10, revenue, assets, PAT, debt, finance-cost amounts, capex, firm-specific ownership/size/export fractions, exact exchanges and primary URLs are not provided. Survey firmographics are pooled and cannot assign attributes to individual companies. Not applicable: report states no outstanding external borrowings.
A69: CONCOR | B69: Transport & logistics | R69: =IF(COUNT(H69:Q69)=10,SUM(H69:Q69),"") | S69: =IF(ISNUMBER(R69),R69/30*100,"") | T69: =IF(COUNT(H69:J69,L69)=4,SUM(H69:J69,L69),"") | U69: =IF(COUNT(K69,M69:O69)=4,SUM(K69,M69:O69),"") | V69: =IF(COUNT(P69:Q69)=2,SUM(P69:Q69),"") | W69: FY2024-25 | AA69: 0 | AH69: =IF(AND(ISNUMBER(AG69),ISNUMBER(AF69),AF69>0),AG69/AF69,"") | AN69: FY2024-25 annual report, BRSR/climate disclosure and official investor pages (firm-specific documents not named in the report) | Transport_and_Logistics_Report.pdf (secondary report; FY2024-25 source dataset) | AO69: FY2024-25 | AP69: PDF pp.19–20, section 8.9: DQS and financing-cost tables | AS69: OBS-068 | AT69: Report total only; I1–I10 unavailable | AU69: 16 | AV69: Transport_and_Logistics_Report.pdf | AW69: PDF pp.19–20; section 8.9 | AX69: No | AY69: No | AZ69: Missing: FY25 finance-cost figure could not be safely extracted. | BB69: =COUNT(H69:Q69) -> 0 | BC69: =IF(AND(ISNUMBER(R69),ISNUMBER(AU69)),R69-AU69,"") | BD69: Report provides total DQS only; I1–I10 are unavailable. Source dataset is FY2024-25 and was verified by the report team on 16 August 2026 (not a new verification here). Missing: FY25 finance-cost figure could not be safely extracted. | BV69: Reviewed supplied PDF/DOCX and related sources | BW69: Transport and Logistics/Transport_and_Logistics_Report.pdf | BX69: CCTS_obligated, listed, exchange, ownership, BRSR_filer, I1, I2, I3, I4, I5, I6, I7, I8, I9, I10, DQS_total, DQS_100, sub_quantification, sub_strategy, sub_credibility, coder_id, second_coder_score, agreed_score, export_intensity, EU_export, PAT_legacy_entity, revenue, total_assets, PAT, ROA, total_debt, finance_cost, cost_of_debt_proxy, capex, size_band, URL, date_accessed; Entire PDF reviewed including charts, appendices, links and attachments. DQS totals and some financing-cost ratios are printed; I1–I10, revenue, assets, PAT, debt, finance-cost amounts, capex, firm-specific ownership/size/export fractions, exact exchanges and primary URLs are not provided. Survey firmographics are pooled and cannot assign attributes to individual companies. Missing: FY25 finance-cost figure could not be safely extracted.
A70: TCI | B70: Transport & logistics | R70: =IF(COUNT(H70:Q70)=10,SUM(H70:Q70),"") | S70: =IF(ISNUMBER(R70),R70/30*100,"") | T70: =IF(COUNT(H70:J70,L70)=4,SUM(H70:J70,L70),"") | U70: =IF(COUNT(K70,M70:O70)=4,SUM(K70,M70:O70),"") | V70: =IF(COUNT(P70:Q70)=2,SUM(P70:Q70),"") | W70: FY2024-25 | AA70: 0 | AH70: =IF(AND(ISNUMBER(AG70),ISNUMBER(AF70),AF70>0),AG70/AF70,"") | AK70: 0.4595 | AN70: FY2024-25 annual report, BRSR/climate disclosure and official investor pages (firm-specific documents not named in the report) | Transport_and_Logistics_Report.pdf (secondary report; FY2024-25 source dataset) | AO70: FY2024-25 | AP70: PDF pp.19–20, section 8.9: DQS and financing-cost tables | AS70: OBS-069 | AT70: Report total only; I1–I10 unavailable | AU70: 14 | AV70: Transport_and_Logistics_Report.pdf | AW70: PDF pp.19–20; section 8.9 | AX70: No | AY70: No | AZ70: Report financing ratio only; finance-cost and borrowing amounts not supplied. | BB70: =COUNT(H70:Q70) -> 0 | BC70: =IF(AND(ISNUMBER(R70),ISNUMBER(AU70)),R70-AU70,"") | BD70: Report provides total DQS only; I1–I10 are unavailable. Source dataset is FY2024-25 and was verified by the report team on 16 August 2026 (not a new verification here). Reported ratio is finance cost divided by average borrowings; underlying amounts and consistent statement basis are not given. | BV70: Reviewed supplied PDF/DOCX and related sources | BW70: Transport and Logistics/Transport_and_Logistics_Report.pdf | BX70: CCTS_obligated, listed, exchange, ownership, BRSR_filer, I1, I2, I3, I4, I5, I6, I7, I8, I9, I10, DQS_total, DQS_100, sub_quantification, sub_strategy, sub_credibility, coder_id, second_coder_score, agreed_score, export_intensity, EU_export, PAT_legacy_entity, revenue, total_assets, PAT, ROA, total_debt, finance_cost, capex, size_band, URL, date_accessed; Entire PDF reviewed including charts, appendices, links and attachments. DQS totals and some financing-cost ratios are printed; I1–I10, revenue, assets, PAT, debt, finance-cost amounts, capex, firm-specific ownership/size/export fractions, exact exchanges and primary URLs are not provided. Survey firmographics are pooled and cannot assign attributes to individual companies. Report financing ratio only; finance-cost and borrowing amounts not supplied.
A71: VRL Logistics | B71: Transport & logistics | R71: =IF(COUNT(H71:Q71)=10,SUM(H71:Q71),"") | S71: =IF(ISNUMBER(R71),R71/30*100,"") | T71: =IF(COUNT(H71:J71,L71)=4,SUM(H71:J71,L71),"") | U71: =IF(COUNT(K71,M71:O71)=4,SUM(K71,M71:O71),"") | V71: =IF(COUNT(P71:Q71)=2,SUM(P71:Q71),"") | W71: FY2024-25 | AA71: 0 | AH71: =IF(AND(ISNUMBER(AG71),ISNUMBER(AF71),AF71>0),AG71/AF71,"") | AK71: 0.2611 | AN71: FY2024-25 annual report, BRSR/climate disclosure and official investor pages (firm-specific documents not named in the report) | Transport_and_Logistics_Report.pdf (secondary report; FY2024-25 source dataset) | AO71: FY2024-25 | AP71: PDF pp.19–20, section 8.9: DQS and financing-cost tables | AS71: OBS-070 | AT71: Report total only; I1–I10 unavailable | AU71: 10 | AV71: Transport_and_Logistics_Report.pdf | AW71: PDF pp.19–20; section 8.9 | AX71: No | AY71: No | AZ71: Report financing ratio only; finance-cost and borrowing amounts not supplied. | BB71: =COUNT(H71:Q71) -> 0 | BC71: =IF(AND(ISNUMBER(R71),ISNUMBER(AU71)),R71-AU71,"") | BD71: Report provides total DQS only; I1–I10 are unavailable. Source dataset is FY2024-25 and was verified by the report team on 16 August 2026 (not a new verification here). Reported ratio is finance cost divided by average borrowings; underlying amounts and consistent statement basis are not given. | BV71: Reviewed supplied PDF/DOCX and related sources | BW71: Transport and Logistics/Transport_and_Logistics_Report.pdf | BX71: CCTS_obligated, listed, exchange, ownership, BRSR_filer, I1, I2, I3, I4, I5, I6, I7, I8, I9, I10, DQS_total, DQS_100, sub_quantification, sub_strategy, sub_credibility, coder_id, second_coder_score, agreed_score, export_intensity, EU_export, PAT_legacy_entity, revenue, total_assets, PAT, ROA, total_debt, finance_cost, capex, size_band, URL, date_accessed; Entire PDF reviewed including charts, appendices, links and attachments. DQS totals and some financing-cost ratios are printed; I1–I10, revenue, assets, PAT, debt, finance-cost amounts, capex, firm-specific ownership/size/export fractions, exact exchanges and primary URLs are not provided. Survey firmographics are pooled and cannot assign attributes to individual companies. Report financing ratio only; finance-cost and borrowing amounts not supplied.
A72: Gateway Distriparks | B72: Transport & logistics | R72: =IF(COUNT(H72:Q72)=10,SUM(H72:Q72),"") | S72: =IF(ISNUMBER(R72),R72/30*100,"") | T72: =IF(COUNT(H72:J72,L72)=4,SUM(H72:J72,L72),"") | U72: =IF(COUNT(K72,M72:O72)=4,SUM(K72,M72:O72),"") | V72: =IF(COUNT(P72:Q72)=2,SUM(P72:Q72),"") | W72: FY2024-25 | AA72: 0 | AH72: =IF(AND(ISNUMBER(AG72),ISNUMBER(AF72),AF72>0),AG72/AF72,"") | AK72: 0.1116 | AN72: FY2024-25 annual report, BRSR/climate disclosure and official investor pages (firm-specific documents not named in the report) | Transport_and_Logistics_Report.pdf (secondary report; FY2024-25 source dataset) | AO72: FY2024-25 | AP72: PDF pp.19–20, section 8.9: DQS and financing-cost tables | AS72: OBS-071 | AT72: Report total only; I1–I10 unavailable | AU72: 10 | AV72: Transport_and_Logistics_Report.pdf | AW72: PDF pp.19–20; section 8.9 | AX72: No | AY72: No | AZ72: Report financing ratio only; finance-cost and borrowing amounts not supplied. | BB72: =COUNT(H72:Q72) -> 0 | BC72: =IF(AND(ISNUMBER(R72),ISNUMBER(AU72)),R72-AU72,"") | BD72: Report provides total DQS only; I1–I10 are unavailable. Source dataset is FY2024-25 and was verified by the report team on 16 August 2026 (not a new verification here). Reported ratio is finance cost divided by average borrowings; underlying amounts and consistent statement basis are not given. | BV72: Reviewed supplied PDF/DOCX and related sources | BW72: Transport and Logistics/Transport_and_Logistics_Report.pdf | BX72: CCTS_obligated, listed, exchange, ownership, BRSR_filer, I1, I2, I3, I4, I5, I6, I7, I8, I9, I10, DQS_total, DQS_100, sub_quantification, sub_strategy, sub_credibility, coder_id, second_coder_score, agreed_score, export_intensity, EU_export, PAT_legacy_entity, revenue, total_assets, PAT, ROA, total_debt, finance_cost, capex, size_band, URL, date_accessed; Entire PDF reviewed including charts, appendices, links and attachments. DQS totals and some financing-cost ratios are printed; I1–I10, revenue, assets, PAT, debt, finance-cost amounts, capex, firm-specific ownership/size/export fractions, exact exchanges and primary URLs are not provided. Survey firmographics are pooled and cannot assign attributes to individual companies. Report financing ratio only; finance-cost and borrowing amounts not supplied.
A73: ITC | B73: Agriculture & agrofoods | H73: 3 | I73: 3 | J73: 3 | K73: 3 | L73: 3 | M73: 3 | N73: 2 | O73: 3 | P73: 3 | Q73: 3 | R73: =IF(COUNT(H73:Q73)=10,SUM(H73:Q73),"") -> 29 | S73: =IF(ISNUMBER(R73),R73/30*100,"") -> 96.666667 | T73: =IF(COUNT(H73:J73,L73)=4,SUM(H73:J73,L73),"") -> 12 | U73: =IF(COUNT(K73,M73:O73)=4,SUM(K73,M73:O73),"") -> 11 | V73: =IF(COUNT(P73:Q73)=2,SUM(P73:Q73),"") -> 6 | AA73: 0 | AH73: =IF(AND(ISNUMBER(AG73),ISNUMBER(AF73),AF73>0),AG73/AF73,"") | AN73: ITC sustainability report 2026 | AP73: not given in the sector report | Uploaded sector report PDF p.35, section 8 (scores); p.36 (company source list) | AQ73: https://itcportal.com/content/dam/itc-corporate/pdfs/sustainability-report/itc-sustainability-report-2026.pdf | AS73: OBS-072 | AT73: Report matrix only; not independently verified | AU73: 29 | AV73: Agriculture_and_Agrofoods_Report.pdf | AW73: PDF p.35; section 8 | AX73: No | AY73: No | AZ73: Not supplied | BB73: =COUNT(H73:Q73) -> 10 | BC73: =IF(AND(ISNUMBER(R73),ISNUMBER(AU73)),R73-AU73,"") -> 0 | BD73: Agriculture narrative incorrectly mentions 30/33; the ten 0–3 indicators have a maximum of 30. | BE73: Correctly company-matched embedded URL transcribed; destination document has not been independently fetched. | BV73: Reviewed supplied PDF/DOCX and related sources | BW73: Agriculture group/Agriculture_and_Agrofoods_Report.pdf (all 41 pages, including image-only statistical tables and URI annotations) | BX73: CCTS_obligated, listed, exchange, ownership, BRSR_filer, reporting_FY, coder_id, second_coder_score, agreed_score, export_intensity, EU_export, PAT_legacy_entity, revenue, total_assets, PAT, ROA, total_debt, finance_cost, cost_of_debt_proxy, capex, size_band, reporting_year, date_accessed; No firm-specific exchange, export intensity, EU-export result, legal CCTS obligation/PAT-legacy status, revenue/assets/PAT/debt/finance-cost/capex data, named coder or access date is supplied. The report describes only aggregate survey regressions and coded DQS; survey prompts are not observed company answers. Scoring fiscal year is not stated.
A74: Godrej Agrovet | B74: Agriculture & agrofoods | H74: 3 | I74: 3 | J74: 3 | K74: 3 | L74: 3 | M74: 3 | N74: 0 | O74: 3 | P74: 3 | Q74: 3 | R74: =IF(COUNT(H74:Q74)=10,SUM(H74:Q74),"") -> 27 | S74: =IF(ISNUMBER(R74),R74/30*100,"") -> 90 | T74: =IF(COUNT(H74:J74,L74)=4,SUM(H74:J74,L74),"") -> 12 | U74: =IF(COUNT(K74,M74:O74)=4,SUM(K74,M74:O74),"") -> 9 | V74: =IF(COUNT(P74:Q74)=2,SUM(P74:Q74),"") -> 6 | W74: FY2025-26 | AA74: 0 | AH74: =IF(AND(ISNUMBER(AG74),ISNUMBER(AF74),AF74>0),AG74/AF74,"") | AN74: Godrej Agrovet Annual Report 2025-26 | AP74: not given in the sector report | Uploaded sector report PDF p.35, section 8 (scores); p.36 (company source list) | AQ74: https://www.godrejagrovet.com/uploads/Annual_Report_2025_26_1eec0f8033.pdf | AS74: OBS-073 | AT74: Report matrix only; not independently verified | AU74: 27 | AV74: Agriculture_and_Agrofoods_Report.pdf | AW74: PDF p.35; section 8 | AX74: No | AY74: No | AZ74: Not supplied | BB74: =COUNT(H74:Q74) -> 10 | BC74: =IF(AND(ISNUMBER(R74),ISNUMBER(AU74)),R74-AU74,"") -> 0 | BD74: Agriculture narrative incorrectly mentions 30/33; the ten 0–3 indicators have a maximum of 30. | BE74: Correctly company-matched embedded URL transcribed; destination document has not been independently fetched. | BV74: Reviewed supplied PDF/DOCX and related sources | BW74: Agriculture group/Agriculture_and_Agrofoods_Report.pdf (all 41 pages, including image-only statistical tables and URI annotations) | BX74: CCTS_obligated, listed, exchange, ownership, BRSR_filer, coder_id, second_coder_score, agreed_score, export_intensity, EU_export, PAT_legacy_entity, revenue, total_assets, PAT, ROA, total_debt, finance_cost, cost_of_debt_proxy, capex, size_band, reporting_year, date_accessed; No firm-specific exchange, export intensity, EU-export result, legal CCTS obligation/PAT-legacy status, revenue/assets/PAT/debt/finance-cost/capex data, named coder or access date is supplied. The report describes only aggregate survey regressions and coded DQS; survey prompts are not observed company answers. Scoring fiscal year is not stated. Existing FY2025-26 is supported only by the linked Annual_Report_2025_26 filename, not an explicit scoring-period statement.
A75: Corteva | B75: Agriculture & agrofoods | F75: foreign | H75: 3 | I75: 3 | J75: 3 | K75: 3 | L75: 3 | M75: 3 | N75: 3 | O75: 3 | P75: 3 | Q75: 3 | R75: =IF(COUNT(H75:Q75)=10,SUM(H75:Q75),"") -> 30 | S75: =IF(ISNUMBER(R75),R75/30*100,"") -> 100 | T75: =IF(COUNT(H75:J75,L75)=4,SUM(H75:J75,L75),"") -> 12 | U75: =IF(COUNT(K75,M75:O75)=4,SUM(K75,M75:O75),"") -> 12 | V75: =IF(COUNT(P75:Q75)=2,SUM(P75:Q75),"") -> 6 | AA75: 0 | AH75: =IF(AND(ISNUMBER(AG75),ISNUMBER(AF75),AF75>0),AG75/AF75,"") | AN75: Corteva "Our 2025 Impact Report" (global) | AP75: not given in the sector report | Uploaded sector report PDF p.35, section 8 (scores); p.36 (company source list) | AQ75: https://reports.corteva.com/sustainability/impactreport2025/static/Corteva_Our_2025_Impact_Report.pdf?v=1775742674 | AS75: OBS-074 | AT75: Report matrix only; not independently verified | AU75: 30 | AV75: Agriculture_and_Agrofoods_Report.pdf | AW75: PDF p.35; section 8 | AX75: No | AY75: No | AZ75: Not supplied | BB75: =COUNT(H75:Q75) -> 10 | BC75: =IF(AND(ISNUMBER(R75),ISNUMBER(AU75)),R75-AU75,"") -> 0 | BD75: Agriculture narrative incorrectly mentions 30/33; the ten 0–3 indicators have a maximum of 30. | BE75: Correctly company-matched embedded URL transcribed; destination document has not been independently fetched. | BV75: Reviewed supplied PDF/DOCX and related sources | BW75: Agriculture group/Agriculture_and_Agrofoods_Report.pdf (all 41 pages, including image-only statistical tables and URI annotations) | BX75: CCTS_obligated, listed, exchange, BRSR_filer, reporting_FY, coder_id, second_coder_score, agreed_score, export_intensity, EU_export, PAT_legacy_entity, revenue, total_assets, PAT, ROA, total_debt, finance_cost, cost_of_debt_proxy, capex, size_band, reporting_year, date_accessed; No firm-specific exchange, export intensity, EU-export result, legal CCTS obligation/PAT-legacy status, revenue/assets/PAT/debt/finance-cost/capex data, named coder or access date is supplied. The report describes only aggregate survey regressions and coded DQS; survey prompts are not observed company answers. Scoring fiscal year is not stated. Linked source is a global company impact report, so it cannot establish Indian subsidiary financials or Indian listed/BRSR status.
A76: Bayer CropScience | B76: Agriculture & agrofoods | F76: foreign | H76: 3 | I76: 3 | J76: 3 | K76: 3 | L76: 3 | M76: 3 | N76: 3 | O76: 3 | P76: 3 | Q76: 3 | R76: =IF(COUNT(H76:Q76)=10,SUM(H76:Q76),"") -> 30 | S76: =IF(ISNUMBER(R76),R76/30*100,"") -> 100 | T76: =IF(COUNT(H76:J76,L76)=4,SUM(H76:J76,L76),"") -> 12 | U76: =IF(COUNT(K76,M76:O76)=4,SUM(K76,M76:O76),"") -> 12 | V76: =IF(COUNT(P76:Q76)=2,SUM(P76:Q76),"") -> 6 | AA76: 0 | AH76: =IF(AND(ISNUMBER(AG76),ISNUMBER(AF76),AF76>0),AG76/AF76,"") | AN76: Sustainability report named in the agriculture report; link not recoverable from the PDF | AP76: not given in the sector report | Uploaded sector report PDF p.35, section 8 (scores); p.36 (company source list) | AS76: OBS-075 | AT76: Report matrix only; not independently verified | AU76: 30 | AV76: Agriculture_and_Agrofoods_Report.pdf | AW76: PDF p.35; section 8 | AX76: No | AY76: No | AZ76: Not supplied | BB76: =COUNT(H76:Q76) -> 10 | BC76: =IF(AND(ISNUMBER(R76),ISNUMBER(AU76)),R76-AU76,"") -> 0 | BD76: Agriculture narrative incorrectly mentions 30/33; the ten 0–3 indicators have a maximum of 30. | BE76: Incorrect embedded link: Bayer row points to Corteva impact report; no correct Bayer URL supplied. | BV76: Reviewed supplied PDF/DOCX and related sources | BW76: Agriculture group/Agriculture_and_Agrofoods_Report.pdf (all 41 pages, including image-only statistical tables and URI annotations) | BX76: CCTS_obligated, listed, exchange, BRSR_filer, reporting_FY, coder_id, second_coder_score, agreed_score, export_intensity, EU_export, PAT_legacy_entity, revenue, total_assets, PAT, ROA, total_debt, finance_cost, cost_of_debt_proxy, capex, size_band, reporting_year, URL, date_accessed; No firm-specific exchange, export intensity, EU-export result, legal CCTS obligation/PAT-legacy status, revenue/assets/PAT/debt/finance-cost/capex data, named coder or access date is supplied. The report describes only aggregate survey regressions and coded DQS; survey prompts are not observed company answers. Scoring fiscal year is not stated. Indian listed entity versus global Bayer scope is unresolved; PDF link points to Corteva.
A77: Tata Consumer | B77: Agriculture & agrofoods | H77: 3 | I77: 0 | J77: 3 | K77: 3 | L77: 3 | M77: 3 | N77: 3 | O77: 3 | P77: 3 | Q77: 3 | R77: =IF(COUNT(H77:Q77)=10,SUM(H77:Q77),"") -> 27 | S77: =IF(ISNUMBER(R77),R77/30*100,"") -> 90 | T77: =IF(COUNT(H77:J77,L77)=4,SUM(H77:J77,L77),"") -> 9 | U77: =IF(COUNT(K77,M77:O77)=4,SUM(K77,M77:O77),"") -> 12 | V77: =IF(COUNT(P77:Q77)=2,SUM(P77:Q77),"") -> 6 | AA77: 0 | AH77: =IF(AND(ISNUMBER(AG77),ISNUMBER(AF77),AF77>0),AG77/AF77,"") | AN77: Tata Consumer BRSR website PDF (URL path dated 2023-05; year not confirmed) | AP77: not given in the sector report | Uploaded sector report PDF p.35, section 8 (scores); p.36 (company source list) | AQ77: https://www.tataconsumer.com/sites/g/files/gfwrlq316/files/2023-05/BRSR%20for%20Website.pdf | AS77: OBS-076 | AT77: Report matrix only; not independently verified | AU77: 27 | AV77: Agriculture_and_Agrofoods_Report.pdf | AW77: PDF p.35; section 8 | AX77: No | AY77: No | AZ77: Not supplied | BB77: =COUNT(H77:Q77) -> 10 | BC77: =IF(AND(ISNUMBER(R77),ISNUMBER(AU77)),R77-AU77,"") -> 0 | BD77: Agriculture narrative incorrectly mentions 30/33; the ten 0–3 indicators have a maximum of 30. | BE77: Correctly company-matched embedded URL transcribed; destination document has not been independently fetched. | BV77: Reviewed supplied PDF/DOCX and related sources | BW77: Agriculture group/Agriculture_and_Agrofoods_Report.pdf (all 41 pages, including image-only statistical tables and URI annotations) | BX77: CCTS_obligated, listed, exchange, ownership, BRSR_filer, reporting_FY, coder_id, second_coder_score, agreed_score, export_intensity, EU_export, PAT_legacy_entity, revenue, total_assets, PAT, ROA, total_debt, finance_cost, cost_of_debt_proxy, capex, size_band, reporting_year, date_accessed; No firm-specific exchange, export intensity, EU-export result, legal CCTS obligation/PAT-legacy status, revenue/assets/PAT/debt/finance-cost/capex data, named coder or access date is supplied. The report describes only aggregate survey regressions and coded DQS; survey prompts are not observed company answers. Scoring fiscal year is not stated.
A78: Marico | B78: Agriculture & agrofoods | H78: 3 | I78: 3 | J78: 3 | K78: 3 | L78: 3 | M78: 3 | N78: 1 | O78: 3 | P78: 3 | Q78: 3 | R78: =IF(COUNT(H78:Q78)=10,SUM(H78:Q78),"") -> 28 | S78: =IF(ISNUMBER(R78),R78/30*100,"") -> 93.333333 | T78: =IF(COUNT(H78:J78,L78)=4,SUM(H78:J78,L78),"") -> 12 | U78: =IF(COUNT(K78,M78:O78)=4,SUM(K78,M78:O78),"") -> 10 | V78: =IF(COUNT(P78:Q78)=2,SUM(P78:Q78),"") -> 6 | AA78: 0 | AH78: =IF(AND(ISNUMBER(AG78),ISNUMBER(AF78),AF78>0),AG78/AF78,"") | AN78: Sustainability report named in the agriculture report; link not recoverable from the PDF | AP78: not given in the sector report | Uploaded sector report PDF p.35, section 8 (scores); p.36 (company source list) | AS78: OBS-077 | AT78: Report matrix only; not independently verified | AU78: 28 | AV78: Agriculture_and_Agrofoods_Report.pdf | AW78: PDF p.35; section 8 | AX78: No | AY78: No | AZ78: Not supplied | BB78: =COUNT(H78:Q78) -> 10 | BC78: =IF(AND(ISNUMBER(R78),ISNUMBER(AU78)),R78-AU78,"") -> 0 | BD78: Agriculture narrative incorrectly mentions 30/33; the ten 0–3 indicators have a maximum of 30. | BE78: Incorrect embedded link: Marico row points to Tata Consumer PDF; no correct Marico URL supplied. | BV78: Reviewed supplied PDF/DOCX and related sources | BW78: Agriculture group/Agriculture_and_Agrofoods_Report.pdf (all 41 pages, including image-only statistical tables and URI annotations) | BX78: CCTS_obligated, listed, exchange, ownership, BRSR_filer, reporting_FY, coder_id, second_coder_score, agreed_score, export_intensity, EU_export, PAT_legacy_entity, revenue, total_assets, PAT, ROA, total_debt, finance_cost, cost_of_debt_proxy, capex, size_band, reporting_year, URL, date_accessed; No firm-specific exchange, export intensity, EU-export result, legal CCTS obligation/PAT-legacy status, revenue/assets/PAT/debt/finance-cost/capex data, named coder or access date is supplied. The report describes only aggregate survey regressions and coded DQS; survey prompts are not observed company answers. Scoring fiscal year is not stated. PDF link points to Tata Consumer; correct Marico source is absent.
A79: Cargill | B79: Agriculture & agrofoods | F79: foreign | H79: 3 | I79: 3 | J79: 3 | K79: 3 | L79: 3 | M79: 3 | N79: 3 | O79: 3 | P79: 3 | Q79: 3 | R79: =IF(COUNT(H79:Q79)=10,SUM(H79:Q79),"") -> 30 | S79: =IF(ISNUMBER(R79),R79/30*100,"") -> 100 | T79: =IF(COUNT(H79:J79,L79)=4,SUM(H79:J79,L79),"") -> 12 | U79: =IF(COUNT(K79,M79:O79)=4,SUM(K79,M79:O79),"") -> 12 | V79: =IF(COUNT(P79:Q79)=2,SUM(P79:Q79),"") -> 6 | AA79: 0 | AH79: =IF(AND(ISNUMBER(AG79),ISNUMBER(AF79),AF79>0),AG79/AF79,"") | AN79: Cargill 2025 Impact Report (global) | AP79: not given in the sector report | Uploaded sector report PDF p.35, section 8 (scores); p.36 (company source list) | AQ79: https://www.cargill.com/sustainability/doc/1451372729493/2025-cargill-impact-report.pdf | AS79: OBS-078 | AT79: Report matrix only; not independently verified | AU79: 30 | AV79: Agriculture_and_Agrofoods_Report.pdf | AW79: PDF p.35; section 8 | AX79: No | AY79: No | AZ79: Not supplied | BB79: =COUNT(H79:Q79) -> 10 | BC79: =IF(AND(ISNUMBER(R79),ISNUMBER(AU79)),R79-AU79,"") -> 0 | BD79: Agriculture narrative incorrectly mentions 30/33; the ten 0–3 indicators have a maximum of 30. | BE79: Correctly company-matched embedded URL transcribed; destination document has not been independently fetched. | BV79: Reviewed supplied PDF/DOCX and related sources | BW79: Agriculture group/Agriculture_and_Agrofoods_Report.pdf (all 41 pages, including image-only statistical tables and URI annotations) | BX79: CCTS_obligated, listed, exchange, BRSR_filer, reporting_FY, coder_id, second_coder_score, agreed_score, export_intensity, EU_export, PAT_legacy_entity, revenue, total_assets, PAT, ROA, total_debt, finance_cost, cost_of_debt_proxy, capex, size_band, reporting_year, date_accessed; No firm-specific exchange, export intensity, EU-export result, legal CCTS obligation/PAT-legacy status, revenue/assets/PAT/debt/finance-cost/capex data, named coder or access date is supplied. The report describes only aggregate survey regressions and coded DQS; survey prompts are not observed company answers. Scoring fiscal year is not stated. Linked source is a global company impact report, so it cannot establish Indian subsidiary financials or Indian listed/BRSR status.
A80: Krishana Phoschem | B80: Fertilisers & chemicals | D80: 1 | F80: listed private | R80: =IF(COUNT(H80:Q80)=10,SUM(H80:Q80),"") | S80: =IF(ISNUMBER(R80),R80/30*100,"") | T80: =IF(COUNT(H80:J80,L80)=4,SUM(H80:J80,L80),"") | U80: =IF(COUNT(K80,M80:O80)=4,SUM(K80,M80:O80),"") | V80: =IF(COUNT(P80:Q80)=2,SUM(P80:Q80),"") | AE80: 2418 | AG80: 180.1 | AH80: =IF(AND(ISNUMBER(AG80),ISNUMBER(AF80),AF80>0),AG80/AF80,"") | AM80: Mid | AN80: Fertilisers_and_Chemicals_Report.pdf; Fertilisers_and_Chemicals_Report.docx | AO80: FY2025-26 | AP80: PDF p.5 Table1; p.18 Table15; p.20 Table16 | AS80: OBS-079 | AT80: Report roster; indicators unavailable | AV80: Fertilisers_and_Chemicals_Report.pdf | AW80: PDF pp.18–20; Tables 15–16 | AX80: No | AY80: No | AZ80: Report financials transcribed; Source does not fully identify standalone/consolidated basis. Do not combine with a different-basis denominator. | BB80: =COUNT(H80:Q80) -> 0 | BC80: =IF(AND(ISNUMBER(R80),ISNUMBER(AU80)),R80-AU80,"") | BF80: 1 | BG80: Directly covered or expected to have direct compliance obligations | BI80: 3 | BO80: <10% | BT80: Less than 5% | BV80: Reviewed supplied PDF/DOCX and related sources | BW80: Fertilisers_and_Chemicals_Report.pdf | Fertilisers_and_Chemicals_Report.docx | Supporting material/Primary Interview Transcripts.docx | Supporting material/Shared Survey Form.pdf | Supporting material/Disclosure_Coding_Sheet.xlsx | Supporting material/Survey_Responses.xlsx | Supporting material/Respondent_Log.xlsx | BX80: CCTS_obligated, exchange, BRSR_filer, I1, I2, I3, I4, I5, I6, I7, I8, I9, I10, DQS_total, DQS_100, sub_quantification, sub_strategy, sub_credibility, reporting_FY, coder_id, second_coder_score, agreed_score, CBAM_covered_product, export_intensity, EU_export, PAT_legacy_entity, total_assets, ROA, total_debt, finance_cost, cost_of_debt_proxy, capex, URL, date_accessed; No exact export ratio/EU destination, exchange, final unit-level CCTS obligation, PAT legacy status, comparable total capex, finance costs or second-coder values are provided. No indicator-level 0–3 scores are supplied for the report-only row; coverage counts cannot reconstruct indicator scores.
A81: Madras Fertilizers | B81: Fertilisers & chemicals | F81: PSU | R81: =IF(COUNT(H81:Q81)=10,SUM(H81:Q81),"") | S81: =IF(ISNUMBER(R81),R81/30*100,"") | T81: =IF(COUNT(H81:J81,L81)=4,SUM(H81:J81,L81),"") | U81: =IF(COUNT(K81,M81:O81)=4,SUM(K81,M81:O81),"") | V81: =IF(COUNT(P81:Q81)=2,SUM(P81:Q81),"") | AH81: =IF(AND(ISNUMBER(AG81),ISNUMBER(AF81),AF81>0),AG81/AF81,"") | AM81: Mid | AN81: Fertilisers_and_Chemicals_Report.pdf; Fertilisers_and_Chemicals_Report.docx | AP81: PDF p.5 Table1; p.18 Table15; p.20 Table16 | AS81: OBS-080 | AT81: Report roster; indicators unavailable | AV81: Fertilisers_and_Chemicals_Report.pdf | AW81: PDF pp.18–20; Tables 15–16 | AX81: No | AY81: No | AZ81: Not supplied | BB81: =COUNT(H81:Q81) -> 0 | BC81: =IF(AND(ISNUMBER(R81),ISNUMBER(AU81)),R81-AU81,"") | BF81: 1 | BG81: Directly covered or expected to have direct compliance obligations | BI81: 0 | BO81: <10% | BT81: Less than 5% | BV81: Reviewed supplied PDF/DOCX and related sources | BW81: Fertilisers_and_Chemicals_Report.pdf | Fertilisers_and_Chemicals_Report.docx | Supporting material/Primary Interview Transcripts.docx | Supporting material/Shared Survey Form.pdf | Supporting material/Disclosure_Coding_Sheet.xlsx | Supporting material/Survey_Responses.xlsx | Supporting material/Respondent_Log.xlsx | BX81: CCTS_obligated, listed, exchange, BRSR_filer, I1, I2, I3, I4, I5, I6, I7, I8, I9, I10, DQS_total, DQS_100, sub_quantification, sub_strategy, sub_credibility, reporting_FY, coder_id, second_coder_score, agreed_score, CBAM_covered_product, export_intensity, EU_export, PAT_legacy_entity, revenue, total_assets, PAT, ROA, total_debt, finance_cost, cost_of_debt_proxy, capex, reporting_year, URL, date_accessed; No exact export ratio/EU destination, exchange, final unit-level CCTS obligation, PAT legacy status, comparable total capex, finance costs or second-coder values are provided. No indicator-level 0–3 scores are supplied for the report-only row; coverage counts cannot reconstruct indicator scores.
A82: Madhya Bharat Agro Products | B82: Fertilisers & chemicals | D82: 1 | F82: listed private | R82: =IF(COUNT(H82:Q82)=10,SUM(H82:Q82),"") | S82: =IF(ISNUMBER(R82),R82/30*100,"") | T82: =IF(COUNT(H82:J82,L82)=4,SUM(H82:J82,L82),"") | U82: =IF(COUNT(K82,M82:O82)=4,SUM(K82,M82:O82),"") | V82: =IF(COUNT(P82:Q82)=2,SUM(P82:Q82),"") | AE82: 1867 | AG82: 150.2 | AH82: =IF(AND(ISNUMBER(AG82),ISNUMBER(AF82),AF82>0),AG82/AF82,"") | AM82: Mid | AN82: Fertilisers_and_Chemicals_Report.pdf; Fertilisers_and_Chemicals_Report.docx | AO82: FY2025-26 | AP82: PDF p.5 Table1; p.18 Table15; p.20 Table16 | AS82: OBS-081 | AT82: Report roster; indicators unavailable | AV82: Fertilisers_and_Chemicals_Report.pdf | AW82: PDF pp.18–20; Tables 15–16 | AX82: No | AY82: No | AZ82: Report financials transcribed; Source does not fully identify standalone/consolidated basis. Do not combine with a different-basis denominator. | BB82: =COUNT(H82:Q82) -> 0 | BC82: =IF(AND(ISNUMBER(R82),ISNUMBER(AU82)),R82-AU82,"") | BF82: 1 | BG82: Directly covered or expected to have direct compliance obligations | BI82: 0 | BO82: <10% | BT82: Less than 5% | BV82: Reviewed supplied PDF/DOCX and related sources | BW82: Fertilisers_and_Chemicals_Report.pdf | Fertilisers_and_Chemicals_Report.docx | Supporting material/Primary Interview Transcripts.docx | Supporting material/Shared Survey Form.pdf | Supporting material/Disclosure_Coding_Sheet.xlsx | Supporting material/Survey_Responses.xlsx | Supporting material/Respondent_Log.xlsx | BX82: CCTS_obligated, exchange, BRSR_filer, I1, I2, I3, I4, I5, I6, I7, I8, I9, I10, DQS_total, DQS_100, sub_quantification, sub_strategy, sub_credibility, reporting_FY, coder_id, second_coder_score, agreed_score, CBAM_covered_product, export_intensity, EU_export, PAT_legacy_entity, total_assets, ROA, total_debt, finance_cost, cost_of_debt_proxy, capex, URL, date_accessed; No exact export ratio/EU destination, exchange, final unit-level CCTS obligation, PAT legacy status, comparable total capex, finance costs or second-coder values are provided. No indicator-level 0–3 scores are supplied for the report-only row; coverage counts cannot reconstruct indicator scores.
A83: PI Industries | B83: Agriculture & agrofoods | H83: 3 | I83: 0 | J83: 3 | K83: 3 | L83: 3 | M83: 0 | N83: 0 | O83: 3 | P83: 1 | Q83: 3 | R83: =IF(COUNT(H83:Q83)=10,SUM(H83:Q83),"") -> 19 | S83: =IF(ISNUMBER(R83),R83/30*100,"") -> 63.333333 | T83: =IF(COUNT(H83:J83,L83)=4,SUM(H83:J83,L83),"") -> 9 | U83: =IF(COUNT(K83,M83:O83)=4,SUM(K83,M83:O83),"") -> 6 | V83: =IF(COUNT(P83:Q83)=2,SUM(P83:Q83),"") -> 4 | AH83: =IF(AND(ISNUMBER(AG83),ISNUMBER(AF83),AF83>0),AG83/AF83,"") | AN83: Agriculture_and_Agrofoods_Report.pdf | AP83: PDF p.35; section 8 | Uploaded sector report PDF p.35, section 8 (scores); p.36 (company source list) | AS83: OBS-082 | AT83: Report matrix only; not independently verified | AU83: 19 | AV83: Agriculture_and_Agrofoods_Report.pdf | AW83: PDF p.35; section 8 | AX83: No | AY83: No | AZ83: Not supplied | BA83: PI Industries appears in two sectors | BB83: =COUNT(H83:Q83) -> 10 | BC83: =IF(AND(ISNUMBER(R83),ISNUMBER(AU83)),R83-AU83,"") -> 0 | BD83: Same company as fertilisers PI Industries; this is an agriculture-report observation with different source basis. Agriculture narrative incorrectly mentions 30/33; the ten 0–3 indicators have a maximum of 30. | BE83: Company source link absent: blue link text has no recoverable PDF annotation. | BV83: Reviewed supplied PDF/DOCX and related sources | BW83: Agriculture group/Agriculture_and_Agrofoods_Report.pdf (all 41 pages, including image-only statistical tables and URI annotations) | BX83: CCTS_obligated, listed, exchange, ownership, BRSR_filer, reporting_FY, coder_id, second_coder_score, agreed_score, CBAM_covered_product, export_intensity, EU_export, PAT_legacy_entity, revenue, total_assets, PAT, ROA, total_debt, finance_cost, cost_of_debt_proxy, capex, size_band, reporting_year, URL, date_accessed; No firm-specific exchange, export intensity, EU-export result, legal CCTS obligation/PAT-legacy status, revenue/assets/PAT/debt/finance-cost/capex data, named coder or access date is supplied. The report describes only aggregate survey regressions and coded DQS; survey prompts are not observed company answers. Scoring fiscal year is not stated. Distinct agriculture observation: do not copy the fertiliser report score/basis across sectors.

Sheet Firm_Review
A1: firm_name | B1: sector | C1: reporting_FY | D1: reporting_year | E1: revenue | F1: total_assets | G1: PAT | H1: total_debt | I1: finance_cost | J1: cost_of_debt_proxy | K1: export_intensity | L1: EU_export | M1: CBAM_covered_product | N1: CCTS_obligated | O1: source_document | P1: calculated_DQS | Q1: report_DQS | R1: data_status | S1: remaining limitations
A2: Tata Steel Ltd | B2: Steel | C2: FY2024-25 | D2: FY2025 | E2: 218543 | F2: 275459 | G2: 3174 | H2: 94801 | I2: 7341 | J2: Not stated in supplied documents | K2: 0.03325071 | L2: 1 | M2: Not stated in supplied documents | N2: Not stated in supplied documents | O2: Annual Report (BRSR embedded) | P2: 18 | Q2: 18 | R2: Workbook final scores; two coders supplied | S2: Official unit-level legal notices, exact exchange identity, access dates, and additional comparable annual capex/finance inputs are not supplied. No valid prior-year debt series was located for average-debt proxy.
A3: JSW Steel Ltd | B3: Steel | C3: FY2025-26 | D3: FY2025 | E3: 168824 | F3: 240445 | G3: 3491 | H3: 98752 | I3: 8412 | J3: Not stated in supplied documents | K3: 0.047558404 | L3: 1 | M3: Not stated in supplied documents | N3: Not stated in supplied documents | O3: Business Responsibility and Sustainability Report (standalone filing) | P3: 16 | Q3: 16 | R3: Workbook final scores; two coders supplied | S3: Official unit-level legal notices, exact exchange identity, access dates, and additional comparable annual capex/finance inputs are not supplied. No valid prior-year debt series was located for average-debt proxy.
A4: Steel Authority of India (SAIL) | B4: Steel | C4: FY2024-25 | D4: FY2025 | E4: 102479 | F4: 136718 | G4: 2372 | H4: 36934 | I4: 2793 | J4: Not stated in supplied documents | K4: 0.0048012764 | L4: unknown | M4: Not stated in supplied documents | N4: Not stated in supplied documents | O4: Business Responsibility and Sustainability Report (standalone filing) | P4: 16 | Q4: 16 | R4: Workbook final scores; two coders supplied | S4: Official unit-level legal notices, exact exchange identity, access dates, and additional comparable annual capex/finance inputs are not supplied. No valid prior-year debt series was located for average-debt proxy.
A5: Jindal Steel Ltd (JSPL) | B5: Steel | C5: FY2025-26 | D5: FY2025 | E5: 50129 | F5: 85766 | G5: 2846 | H5: 18406 | I5: 1312 | J5: Not stated in supplied documents | K5: 0.052451675 | L5: unknown | M5: Not stated in supplied documents | N5: Not stated in supplied documents | O5: Integrated Report (BRSR embedded) | P5: 19 | Q5: 19 | R5: Workbook final scores; two coders supplied | S5: Official unit-level legal notices, exact exchange identity, access dates, and additional comparable annual capex/finance inputs are not supplied. No valid prior-year debt series was located for average-debt proxy.
A6: Jindal Stainless Ltd | B6: Steel | C6: FY2024-25 | D6: FY2025 | E6: 39312 | F6: 35917 | G6: 2500 | H6: 6402 | I6: 612 | J6: Not stated in supplied documents | K6: 0.14722451 | L6: 1 | M6: Not stated in supplied documents | N6: Not stated in supplied documents | O6: Business Responsibility and Sustainability Report (standalone filing) | P6: 17 | Q6: 17 | R6: Workbook final scores; two coders supplied | S6: Official unit-level legal notices, exact exchange identity, access dates, and additional comparable annual capex/finance inputs are not supplied. No valid prior-year debt series was located for average-debt proxy.
A7: NMDC Steel Ltd | B7: Steel | C7: Not stated in supplied documents | D7: FY2025 | E7: 8503 | F7: 28470 | G7: -2374 | H7: 5909 | I7: 652 | J7: Not stated in supplied documents | K7: 0 | L7: unknown | M7: Not stated in supplied documents | N7: Not stated in supplied documents | O7: Annual Report, NMDC Limited (BRSR embedded) | P7: 14 | Q7: 14 | R7: Workbook final scores; two coders supplied | S7: Official unit-level legal notices, exact exchange identity, access dates, and additional comparable annual capex/finance inputs are not supplied. No valid prior-year debt series was located for average-debt proxy. NMDC Limited/NMDC Steel Ltd entity mismatch prevents copying miner disclosure/year/capex into steel row.
A8: Shyam Metalics & Energy Ltd | B8: Steel | C8: FY2024-25 | D8: FY2025 | E8: 15138 | F8: 16320 | G8: 909 | H8: 789 | I8: 144 | J8: Not stated in supplied documents | K8: 0.0054868543 | L8: unknown | M8: Not stated in supplied documents | N8: Not stated in supplied documents | O8: Business Responsibility and Sustainability Report + Annual Report | P8: 6 | Q8: 6 | R8: Workbook final scores; two coders supplied | S8: Official unit-level legal notices, exact exchange identity, access dates, and additional comparable annual capex/finance inputs are not supplied. No valid prior-year debt series was located for average-debt proxy.
A9: Godawari Power & Ispat Ltd | B9: Steel | C9: FY2024-25 | D9: FY2025 | E9: 5375.73 | F9: 6157 | G9: 813 | H9: 309 | I9: 55.39 | J9: Not stated in supplied documents | K9: 0.013298659 | L9: unknown | M9: Not stated in supplied documents | N9: Not stated in supplied documents | O9: Annual Report (BRSR embedded) | P9: 13 | Q9: 13 | R9: Workbook final scores; two coders supplied | S9: Official unit-level legal notices, exact exchange identity, access dates, and additional comparable annual capex/finance inputs are not supplied. No valid prior-year debt series was located for average-debt proxy.
A10: Kalyani Steels Ltd | B10: Steel | C10: FY2025-26 | D10: FY2025 | E10: 1982 | F10: 2732 | G10: 256 | H10: 438 | I10: 19 | J10: Not stated in supplied documents | K10: 0.0070479314 | L10: unknown | M10: Not stated in supplied documents | N10: Not stated in supplied documents | O10: Annual Report (BRSR embedded) | P10: 5 | Q10: 5 | R10: Workbook final scores; two coders supplied | S10: Official unit-level legal notices, exact exchange identity, access dates, and additional comparable annual capex/finance inputs are not supplied. No valid prior-year debt series was located for average-debt proxy.
A11: Dalmia Bharat | B11: Cement | C11: FY 2025-26 | D11: Not stated in supplied documents | E11: Not stated in supplied documents | F11: Not stated in supplied documents | G11: Not stated in supplied documents | H11: Not stated in supplied documents | I11: Not stated in supplied documents | J11: Not stated in supplied documents | K11: Not stated in supplied documents | L11: unknown | M11: 1 | N11: Not stated in supplied documents | O11: Dalmia Bharat IR 2025-26; Dalmia Bharat IR 2025-26 (reviewed) | P11: 23 | Q11: 23 | R11: Workbook coded; single coder | S11: No firm-level revenue/PAT/assets/debt/finance-cost table in supplied report or Word interviews. Survey and MDS values are respondent/perception data and cannot fill company financials. Single-coder identity and second coder are unrecorded. EU-specific exports not disclosed. Exact company-report URLs and access dates not supplied.
A12: Shree Cement | B12: Cement | C12: FY 2025-26 | D12: Not stated in supplied documents | E12: Not stated in supplied documents | F12: Not stated in supplied documents | G12: Not stated in supplied documents | H12: Not stated in supplied documents | I12: Not stated in supplied documents | J12: Not stated in supplied documents | K12: 0 | L12: unknown | M12: 1 | N12: Not stated in supplied documents | O12: Shree Cement IR 2025-26; Shree Cement IR 2025-26 (reviewed) | P12: 22 | Q12: 22 | R12: Workbook coded; single coder | S12: No firm-level revenue/PAT/assets/debt/finance-cost table in supplied report or Word interviews. Survey and MDS values are respondent/perception data and cannot fill company financials. Single-coder identity and second coder are unrecorded. EU-specific exports not disclosed. Exact company-report URLs and access dates not supplied.
A13: ACC Limited | B13: Cement | C13: FY 2024-25 | D13: Not stated in supplied documents | E13: Not stated in supplied documents | F13: Not stated in supplied documents | G13: Not stated in supplied documents | H13: Not stated in supplied documents | I13: Not stated in supplied documents | J13: Not stated in supplied documents | K13: 0 | L13: unknown | M13: 1 | N13: Not stated in supplied documents | O13: ACC IR 2024-25 | P13: 25 | Q13: 25 | R13: Workbook coded; single coder | S13: No firm-level revenue/PAT/assets/debt/finance-cost table in supplied report or Word interviews. Survey and MDS values are respondent/perception data and cannot fill company financials. Single-coder identity and second coder are unrecorded. EU-specific exports not disclosed. Exact company-report URLs and access dates not supplied.
A14: JK Cement | B14: Cement | C14: FY 2025-26 | D14: Not stated in supplied documents | E14: Not stated in supplied documents | F14: Not stated in supplied documents | G14: Not stated in supplied documents | H14: Not stated in supplied documents | I14: Not stated in supplied documents | J14: Not stated in supplied documents | K14: Not stated in supplied documents | L14: unknown | M14: 1 | N14: Not stated in supplied documents | O14: JK Cement IR 2025-26 | P14: 29 | Q14: 29 | R14: Workbook coded; single coder | S14: No firm-level revenue/PAT/assets/debt/finance-cost table in supplied report or Word interviews. Survey and MDS values are respondent/perception data and cannot fill company financials. Single-coder identity and second coder are unrecorded. EU-specific exports not disclosed. Exact company-report URLs and access dates not supplied.
A15: UltraTech | B15: Cement | C15: FY 2025-26 | D15: Not stated in supplied documents | E15: Not stated in supplied documents | F15: Not stated in supplied documents | G15: Not stated in supplied documents | H15: Not stated in supplied documents | I15: Not stated in supplied documents | J15: Not stated in supplied documents | K15: 0.0025 | L15: unknown | M15: 1 | N15: Not stated in supplied documents | O15: UltraTech IR & Sustainability Report 2025-26 | P15: 27 | Q15: 27 | R15: Workbook coded; single coder | S15: No firm-level revenue/PAT/assets/debt/finance-cost table in supplied report or Word interviews. Survey and MDS values are respondent/perception data and cannot fill company financials. Single-coder identity and second coder are unrecorded. EU-specific exports not disclosed. Exact company-report URLs and access dates not supplied.
A16: Ambuja Cements | B16: Cement | C16: FY 2024-25 | D16: Not stated in supplied documents | E16: Not stated in supplied documents | F16: Not stated in supplied documents | G16: Not stated in supplied documents | H16: Not stated in supplied documents | I16: Not stated in supplied documents | J16: Not stated in supplied documents | K16: 0 | L16: unknown | M16: 1 | N16: Not stated in supplied documents | O16: Ambuja IR 2024-25; Ambuja IR 2024-25 (reviewed) | P16: 21 | Q16: 21 | R16: Workbook coded; single coder | S16: No firm-level revenue/PAT/assets/debt/finance-cost table in supplied report or Word interviews. Survey and MDS values are respondent/perception data and cannot fill company financials. Single-coder identity and second coder are unrecorded. EU-specific exports not disclosed. Exact company-report URLs and access dates not supplied.
A17: JSW Cement | B17: Cement | C17: FY 2025-26 | D17: Not stated in supplied documents | E17: Not stated in supplied documents | F17: Not stated in supplied documents | G17: Not stated in supplied documents | H17: Not stated in supplied documents | I17: Not stated in supplied documents | J17: Not stated in supplied documents | K17: 0 | L17: unknown | M17: 1 | N17: Not stated in supplied documents | O17: JSW Cement IAR 2025-26; JSW Cement IAR 2025-26 (reviewed) | P17: 21 | Q17: 21 | R17: Workbook coded; single coder | S17: No firm-level revenue/PAT/assets/debt/finance-cost table in supplied report or Word interviews. Survey and MDS values are respondent/perception data and cannot fill company financials. Single-coder identity and second coder are unrecorded. EU-specific exports not disclosed. Exact company-report URLs and access dates not supplied.
A18: Hindalco | B18: Aluminium | C18: FY2024-25 | D18: FY2024-25 | E18: 238496 | F18: 265991 | G18: 16002 | H18: Not stated in supplied documents | I18: Not stated in supplied documents | J18: 0.0587 | K18: Not stated in supplied documents | L18: Not stated in supplied documents | M18: 1 | N18: Not stated in supplied documents | O18: Hindalco Integrated Annual Report 2024-25 incl. BRSR and assurance (report ref. 5) | P18: 30 | Q18: 30 | R18: Report matrix only; not independently verified | S18: No exchange name, exact export/EU-export share, PAT legacy status, finance-cost numerator, debt balance, total capex, coder identity or access date supplied. Table 14 reports the already-transcribed financial values but does not supply debt, finance cost or capex inputs. The interview firms differ from the ten listed disclosure-panel names, so their loan/export claims cannot populate these rows. Firm-level CCTS obligation needs legal/unit evidence not present.
A19: Vedanta | B19: Aluminium | C19: FY2024-25 | D19: Not stated in supplied documents | E19: Not stated in supplied documents | F19: Not stated in supplied documents | G19: Not stated in supplied documents | H19: Not stated in supplied documents | I19: Not stated in supplied documents | J19: Not stated in supplied documents | K19: Not stated in supplied documents | L19: Not stated in supplied documents | M19: 1 | N19: Not stated in supplied documents | O19: Vedanta Integrated Report and Annual Accounts FY2024-25; Climate Action Report 2025 (ref. 14) | P19: 30 | Q19: 30 | R19: Report matrix only; not independently verified | S19: No exchange name, exact export/EU-export share, PAT legacy status, finance-cost numerator, debt balance, total capex, coder identity or access date supplied. Table 14 explicitly says no financial document sourced for this firm; no financial values can be filled from these documents. The interview firms differ from the ten listed disclosure-panel names, so their loan/export claims cannot populate these rows. Firm-level CCTS obligation needs legal/unit evidence not present.
A20: NALCO | B20: Aluminium | C20: FY2024-25 | D20: FY2024-25 | E20: 16662.21 | F20: 22882 | G20: 5324.67 | H20: Not stated in supplied documents | I20: Not stated in supplied documents | J20: Not stated in supplied documents | K20: Not stated in supplied documents | L20: Not stated in supplied documents | M20: 1 | N20: Not stated in supplied documents | O20: NALCO 44th Annual Report 2024-25 incl. BRSR (ref. 9) | P20: 30 | Q20: 30 | R20: Report matrix only; not independently verified | S20: No exchange name, exact export/EU-export share, PAT legacy status, finance-cost numerator, debt balance, total capex, coder identity or access date supplied. Cost-of-debt proxy is N/M because of no material borrowing, not a numeric zero. Total assets ~₹22,882 crore are approximate. The interview firms differ from the ten listed disclosure-panel names, so their loan/export claims cannot populate these rows. Firm-level CCTS obligation needs legal/unit evidence not present.
A21: BALCO | B21: Aluminium | C21: FY2024-25 | D21: Not stated in supplied documents | E21: Not stated in supplied documents | F21: Not stated in supplied documents | G21: Not stated in supplied documents | H21: Not stated in supplied documents | I21: Not stated in supplied documents | J21: Not stated in supplied documents | K21: Not stated in supplied documents | L21: Not stated in supplied documents | M21: 1 | N21: Not stated in supplied documents | O21: BALCO Integrated Annual Report and sustainability pages | P21: 17 | Q21: 17 | R21: Report matrix only; not independently verified | S21: No exchange name, exact export/EU-export share, PAT legacy status, finance-cost numerator, debt balance, total capex, coder identity or access date supplied. Table 14 explicitly says no financial document sourced for this firm; no financial values can be filled from these documents. The interview firms differ from the ten listed disclosure-panel names, so their loan/export claims cannot populate these rows. Firm-level CCTS obligation needs legal/unit evidence not present.
A22: Maan Aluminium | B22: Aluminium | C22: FY2024-25 | D22: FY2024-25 | E22: 810.17 | F22: 299.63 | G22: 15.51 | H22: Not stated in supplied documents | I22: Not stated in supplied documents | J22: 0.0536 | K22: Not stated in supplied documents | L22: Not stated in supplied documents | M22: Not stated in supplied documents | N22: Not stated in supplied documents | O22: Aluminium sector report, Table 8 | P22: 10 | Q22: 10 | R22: Report matrix only; not independently verified | S22: No exchange name, exact export/EU-export share, PAT legacy status, finance-cost numerator, debt balance, total capex, coder identity or access date supplied. Table 14 reports the already-transcribed financial values but does not supply debt, finance cost or capex inputs. The interview firms differ from the ten listed disclosure-panel names, so their loan/export claims cannot populate these rows. Firm-level CCTS obligation needs legal/unit evidence not present.
A23: Century Extrusions | B23: Aluminium | C23: FY2024-25 | D23: FY2025-26 | E23: 479.3 | F23: Not stated in supplied documents | G23: 10.97 | H23: Not stated in supplied documents | I23: Not stated in supplied documents | J23: Not stated in supplied documents | K23: Not stated in supplied documents | L23: Not stated in supplied documents | M23: Not stated in supplied documents | N23: Not stated in supplied documents | O23: Aluminium sector report, Table 8 | P23: 9 | Q23: 9 | R23: Report matrix only; not independently verified | S23: No exchange name, exact export/EU-export share, PAT legacy status, finance-cost numerator, debt balance, total capex, coder identity or access date supplied. Financial context is FY2025-26, whereas DQS is FY2024-25; assets/ROA/debt proxy are N/A and cannot be reconstructed. The interview firms differ from the ten listed disclosure-panel names, so their loan/export claims cannot populate these rows. Firm-level CCTS obligation needs legal/unit evidence not present.
A24: PG Foils | B24: Aluminium | C24: FY2024-25 | D24: FY2024-25 | E24: 491.4 | F24: 423.81 | G24: 31.66 | H24: Not stated in supplied documents | I24: Not stated in supplied documents | J24: Not stated in supplied documents | K24: Not stated in supplied documents | L24: Not stated in supplied documents | M24: Not stated in supplied documents | N24: Not stated in supplied documents | O24: PG Foils annual report and corporate disclosures FY2024-25 (ref. 11) | P24: 9 | Q24: 9 | R24: Report matrix only; not independently verified | S24: No exchange name, exact export/EU-export share, PAT legacy status, finance-cost numerator, debt balance, total capex, coder identity or access date supplied. Table 14 reports the already-transcribed financial values but does not supply debt, finance cost or capex inputs. The interview firms differ from the ten listed disclosure-panel names, so their loan/export claims cannot populate these rows. Firm-level CCTS obligation needs legal/unit evidence not present.
A25: Manaksia Aluminium | B25: Aluminium | C25: FY2024-25 | D25: FY2024-25 | E25: 509.15 | F25: 504.26 | G25: 6.05 | H25: Not stated in supplied documents | I25: Not stated in supplied documents | J25: 0.1339 | K25: Not stated in supplied documents | L25: Not stated in supplied documents | M25: Not stated in supplied documents | N25: Not stated in supplied documents | O25: Aluminium sector report, Table 8 | P25: 8 | Q25: 8 | R25: Report matrix only; not independently verified | S25: No exchange name, exact export/EU-export share, PAT legacy status, finance-cost numerator, debt balance, total capex, coder identity or access date supplied. Table 14 reports the already-transcribed financial values but does not supply debt, finance cost or capex inputs. The interview firms differ from the ten listed disclosure-panel names, so their loan/export claims cannot populate these rows. Firm-level CCTS obligation needs legal/unit evidence not present.
A26: Alufluoride | B26: Aluminium | C26: FY2024-25 | D26: FY2024-25 | E26: 188.52 | F26: 149.23 | G26: 18.09 | H26: Not stated in supplied documents | I26: Not stated in supplied documents | J26: 0.1264 | K26: Not stated in supplied documents | L26: Not stated in supplied documents | M26: Not stated in supplied documents | N26: Not stated in supplied documents | O26: Aluminium sector report, Table 8 | P26: 8 | Q26: 8 | R26: Report matrix only; not independently verified | S26: No exchange name, exact export/EU-export share, PAT legacy status, finance-cost numerator, debt balance, total capex, coder identity or access date supplied. Table 14 reports the already-transcribed financial values but does not supply debt, finance cost or capex inputs. The interview firms differ from the ten listed disclosure-panel names, so their loan/export claims cannot populate these rows. Firm-level CCTS obligation needs legal/unit evidence not present.
A27: Euro Panel Products | B27: Aluminium | C27: FY2024-25 | D27: Not stated in supplied documents | E27: Not stated in supplied documents | F27: Not stated in supplied documents | G27: Not stated in supplied documents | H27: Not stated in supplied documents | I27: Not stated in supplied documents | J27: Not stated in supplied documents | K27: Not stated in supplied documents | L27: Not stated in supplied documents | M27: Not stated in supplied documents | N27: Not stated in supplied documents | O27: Aluminium sector report, Table 8 | P27: 7 | Q27: 7 | R27: Report matrix only; not independently verified | S27: No exchange name, exact export/EU-export share, PAT legacy status, finance-cost numerator, debt balance, total capex, coder identity or access date supplied. Table 14 explicitly says no financial document sourced for this firm; no financial values can be filled from these documents. The interview firms differ from the ten listed disclosure-panel names, so their loan/export claims cannot populate these rows. Firm-level CCTS obligation needs legal/unit evidence not present.
A28: IFFCO | B28: Fertilisers & chemicals | C28: FY2025-26 | D28: Not stated in supplied documents | E28: Not stated in supplied documents | F28: Not stated in supplied documents | G28: Not stated in supplied documents | H28: Not stated in supplied documents | I28: Not stated in supplied documents | J28: Not stated in supplied documents | K28: Not stated in supplied documents | L28: unknown | M28: Not stated in supplied documents | N28: Not stated in supplied documents | O28: IFFCO Annual Report / public disclosures | P28: Indicator inputs incomplete | Q28: Not reported | R28: Out of scope (BRSR); no zero assigned | S28: No exact export ratio/EU destination, exchange, final unit-level CCTS obligation, PAT legacy status, comparable total capex, finance costs or second-coder values are provided. DQS is out of scope, not zero; report states public financials not found.
A29: DCM Shriram | B29: Fertilisers & chemicals | C29: FY2024-25 | D29: FY2025-26 | E29: 13538 | F29: Not stated in supplied documents | G29: Not stated in supplied documents | H29: Not stated in supplied documents | I29: Not stated in supplied documents | J29: Not stated in supplied documents | K29: Not stated in supplied documents | L29: unknown | M29: Not stated in supplied documents | N29: Not stated in supplied documents | O29: FY2024-25 Annual Report + Sustainability Report | P29: 21 | Q29: Not reported | R29: REVIEW: source conflict | S29: No exact export ratio/EU destination, exchange, final unit-level CCTS obligation, PAT legacy status, comparable total capex, finance costs or second-coder values are provided.
A30: National Fertilizers Limited (NFL) | B30: Fertilisers & chemicals | C30: FY2024-25 | D30: FY2025-26 | E30: 21567.9 | F30: Not stated in supplied documents | G30: 169.7 | H30: Not stated in supplied documents | I30: Not stated in supplied documents | J30: Not stated in supplied documents | K30: Not stated in supplied documents | L30: unknown | M30: Not stated in supplied documents | N30: Not stated in supplied documents | O30: FY2024-25 Annual Report + BRSR | P30: 16 | Q30: Not reported | R30: REVIEW: source conflict | S30: No exact export ratio/EU destination, exchange, final unit-level CCTS obligation, PAT legacy status, comparable total capex, finance costs or second-coder values are provided.
A31: Chambal Fertilisers & Chemicals | B31: Fertilisers & chemicals | C31: FY2024-25 | D31: FY2024-25 | E31: Not stated in supplied documents | F31: Not stated in supplied documents | G31: Not stated in supplied documents | H31: Not stated in supplied documents | I31: Not stated in supplied documents | J31: Not stated in supplied documents | K31: Not stated in supplied documents | L31: unknown | M31: Not stated in supplied documents | N31: Not stated in supplied documents | O31: FY2024-25 Annual Report/BRSR | P31: 16 | Q31: 12 | R31: REVIEW: source conflict | S31: No exact export ratio/EU destination, exchange, final unit-level CCTS obligation, PAT legacy status, comparable total capex, finance costs or second-coder values are provided.
A32: SRF Limited | B32: Fertilisers & chemicals | C32: FY2024-25 | D32: FY2024-25 | E32: Not stated in supplied documents | F32: 22261 | G32: Not stated in supplied documents | H32: 4527 | I32: Not stated in supplied documents | J32: Not stated in supplied documents | K32: Not stated in supplied documents | L32: unknown | M32: Not stated in supplied documents | N32: Not stated in supplied documents | O32: FY2024-25 Annual Report | P32: 17 | Q32: Not reported | R32: REVIEW: source conflict | S32: No exact export ratio/EU destination, exchange, final unit-level CCTS obligation, PAT legacy status, comparable total capex, finance costs or second-coder values are provided.
A33: PI Industries | B33: Fertilisers & chemicals | C33: FY2024-25 | D33: Not stated in supplied documents | E33: Not stated in supplied documents | F33: Not stated in supplied documents | G33: Not stated in supplied documents | H33: Not stated in supplied documents | I33: Not stated in supplied documents | J33: Not stated in supplied documents | K33: Not stated in supplied documents | L33: unknown | M33: Not stated in supplied documents | N33: Not stated in supplied documents | O33: FY2024-25 Integrated Annual Report + BRSR | P33: 19 | Q33: Not reported | R33: REVIEW: source conflict | S33: No exact export ratio/EU destination, exchange, final unit-level CCTS obligation, PAT legacy status, comparable total capex, finance costs or second-coder values are provided. Report explicitly says financial figures not found.
